Workbook

Sheet Original Articles
A1: CSV Row | B1: Article ID | C1: Ticker | D1: Title | E1: Snippet | F1: Embedded Text (format_news_content) | G1: Embedding (all-MiniLM-L6-v2, normalized)
A2: 1 | B2: 99d3c240-a69d-471e-9754-bd53d542c01f | C2: CBA.AX | D2: Banks warn AI shopping agents could increase risk of scams, fraud and data privacy breaches | E2: A coalition of global banks says agentic AI tools that make purchases on behalf of consumers could expose card details and weaken payment security. | F2: Banks warn AI shopping agents could increase risk of scams, fraud and data privacy breaches - A coalition of global banks says agentic AI tools that make purchases on behalf of consumers could expose card details and weaken payment security. | G2: [-0.05099, 0.004412, -0.082482, -0.00913, 0.029339, 0.028803, 0.101072, 0.00717, -0.007238, -0.039414, 0.014977, 0.009957, 0.065063, -0.006501, 0.091146, -0.010006, 0.065569, 0.027633, -0.030093, 0.03226, 0.012441, -0.015713, -0.057893, 0.010292, -0.081095, -0.000567, 0.019981, -0.057118, -0.066315, 0.0045, 0.0651, 0.052246, 0.077569, 0.026662, 0.041609, -0.050985, -0.05682, 7e-06, 0.042773, -0.028856, -0.014416, -0.063962, -0.038921, -0.021972, 0.051355, 0.032223, 0.000866, 0.041038, -0.017591, 0.053122, -0.104528, -0.013055, 0.040316, -0.03307, -0.122557, -0.025499, 0.021914, -0.039072, -0.006576, -0.043162, 0.052584, -0.042594, 0.084833, 0.058371, 0.033079, 0.063096, -0.090461, -0.013011, -0.02028, -0.026112, 0.066991, -0.067103, -0.016, -0.027572, 0.054057, 0.035637, 0.028802, -0.027993, 0.073102, -0.045159, -0.063143, -0.068805, 0.028951, 0.043257, -0.037864, 0.038604, 0.024515, -0.049827, 0.021122, -0.099248, 0.062209, -0.021909, 0.038176, -0.020397, 0.088372, -0.025704, -0.090235, -0.093952, -0.010388, 0.009677, -0.000255, 0.073757, -0.000626, 0.042575, 0.0067, 0.008111, 0.088226, -0.020191, 0.059429, -0.019434, -0.033579, -0.014326, 0.075382, -0.04656, 0.068378, 0.035451, -0.050109, 0.117464, 0.020812, 0.040952, 0.034025, 0.028701, -0.016637, 0.025626, 0.040662, 0.083395, -0.036628, 0.0, -0.054546, 0.024338, -0.000492, -0.068857, 0.039155, -0.031431, -0.013725, -0.029859, -0.008222, 0.066394, -0.023904, 0.021657, -0.009874, 0.082266, 0.030508, 0.052272, -0.037285, 0.049946, 0.082813, 0.020965, 0.064095, -0.107464, 0.073249, -0.011519, 0.066541, 0.020555, -0.031472, -0.035378, 0.174533, -0.008025, -0.016096, 0.01118, 0.018817, 0.056434, -0.067001, 0.094482, -0.079703, -0.008869, 0.006112, 0.049279, -0.038548, 0.044344, 0.105616, -0.027287, -0.033099, 0.035546, -0.014505, -0.030543, -0.03355, 0.012601, -0.092761, 0.032837, -0.013977, -0.03536, 0.006683, -0.088972, 0.039513, 0.005256, 0.01559, -0.085081, -0.073783, -0.087139, -0.011515, 0.020903, -0.054392, 0.012227, 0.086426, -0.014613, -0.02314, 0.041929, -0.055382, 0.069087, 0.026036, -0.001456, -0.09131, -0.033181, -0.009703, -0.005643, 0.049566, -0.058714, -0.06178, -0.045808, 0.05009, 0.049834, -0.026879, 0.046048, -0.021584, -0.043527, 0.000112, -0.019484, -0.042224, -0.015445, -0.023148, 0.078251, 0.012675, -0.0, -0.104166, -0.089025, -0.083373, 0.034755, -0.076815, -0.037809, -0.044349, -0.009624, 0.068169, -0.021879, -0.029096, 0.072552, 0.024484, -0.020722, 0.043729, -0.035542, 0.035032, 0.003899, 0.054166, -0.07354, 0.045652, 0.047305, -0.023853, -0.022713, 0.049573, 0.021564, -0.032365, 0.010826, 0.03973, -0.024102, 0.002156, -0.003416, -0.01151, 0.080337, 0.001068, 0.027009, 0.019146, 0.040513, 0.010143, 0.039225, 0.013669, -0.008982, -0.077711, -0.042164, -0.006047, -0.035713, 0.027992, 0.049739, 0.055225, -0.01387, -0.06409, -0.002908, -0.012435, -0.054806, -0.127222, 0.105058, 0.096047, 0.009248, -0.005084, -0.012462, -0.06232, 0.020445, 0.023395, -0.020478, -0.026781, 0.001754, -0.034308, 0.024179, 0.092956, -0.051956, 0.066057, -0.057776, -0.041301, 0.095131, 0.002462, -0.009359, -0.016876, -0.047969, -0.01358, -0.053396, -0.003545, -0.017476, 0.073317, 0.029122, 0.037275, 7.7e-05, -0.021865, -0.064412, -0.022443, -0.046687, -0.062153, 0.000644, 0.002986, 0.015992, -0.160437, -0.0, 0.025506, -0.034105, 0.086399, 0.03195, 0.044405, -0.059996, -0.034972, 0.033038, -0.105735, -0.046228, 0.0641, -0.031094, -0.033533, -0.021565, 0.06694, 0.031769, 0.022583, -0.058074, -0.027038, -0.051849, 0.042193, -0.011359, 0.012225, -0.053224, -0.017197, -0.026852, 0.036719, 0.046726, -0.017839, 0.071291, -0.052169, 0.002605, 0.107915, 0.035795, 0.093559, 0.035945, 0.028255, -0.053848, -0.060115, -0.004305, 0.003053, -0.054078, -0.000731, -0.061221, 0.046472, -0.063913, -0.013961, -0.112885, 0.137237, -0.020816, -0.079606, -0.008166, 0.049255, 0.114267, 0.07705, -0.078099, 0.023855, -0.070955, 0.109279, 0.040944, -0.006684, 0.010301, 0.031, -0.094949]
A3: 2 | B3: b1b83951-4c53-41ff-a55f-9a52d2b6570d | C3: CBA.AX | D3: Banks warn AI shopping agents outpace fraud protections | E3: NatWest, Bank of America, and four other banks say consumers risk scams and data breaches as AI commerce tools advance faster than industry safeguards | F3: Banks warn AI shopping agents outpace fraud protections - NatWest, Bank of America, and four other banks say consumers risk scams and data breaches as AI commerce tools advance faster than industry safeguards | G3: [-0.014682, -0.07234, -0.054475, -0.0042, 0.091505, 0.025968, 0.079649, -0.013261, 0.008069, -0.032533, 0.021076, 0.042247, 0.083079, -0.044598, 0.066689, 0.012786, 0.033938, 0.005379, -0.034333, -0.009791, 0.026608, -0.011332, -0.045449, 0.048694, -0.056949, -0.008387, 0.012224, -0.063886, -0.085033, -0.040651, -0.000701, 0.01526, 0.051502, 0.016273, 0.044642, -0.044168, -0.001241, -0.009924, 0.072087, -0.07836, 0.017584, -0.062724, -0.021652, 0.007999, 0.047123, 0.05284, 0.002984, 0.022436, -0.003995, 0.042775, -0.077769, -0.029279, 0.033146, 0.004387, -0.106084, 0.012608, 0.031972, 0.011636, 0.0018, 0.008478, 0.10695, -0.041439, 0.069278, 0.050113, 0.028973, 0.068716, -0.115218, 0.008757, -0.03658, -0.007114, 0.062306, -0.117635, -0.076255, 0.016987, 0.020302, 0.054841, 0.021542, -0.022179, 0.090914, -0.03083, -0.028192, -0.071816, -0.007991, 0.046258, -0.010754, 0.002887, -0.009926, -0.044687, 0.013775, -0.080033, 0.063373, -0.047075, 0.042719, 0.011706, 0.055678, -0.082157, -0.070915, -0.047362, 0.03023, -0.014906, 0.025387, 0.097655, -0.03198, 0.026616, -0.013732, -0.034767, 0.049769, -0.019794, 0.062153, 0.032335, 0.023819, 0.021401, 0.104675, 0.006455, 0.048386, 0.050984, -0.071615, 0.094216, 0.039845, 0.04164, 0.01236, 0.10067, 0.003205, -0.01093, 0.030131, 0.045112, -0.03338, 0.0, -0.067817, 0.0302, 0.00518, -0.074722, 0.028347, -0.021197, -0.046504, 0.019061, -0.002501, 0.111221, -0.084189, 0.001976, -0.005517, 0.024142, 0.020884, 0.066327, 0.020269, 0.044258, 0.03045, -0.006614, 0.066167, -0.08323, 0.054544, 0.030425, 0.063573, -0.021464, -0.039843, 0.003477, 0.144367, 0.009627, -0.012916, 0.024691, 0.012457, 0.031795, -0.047305, 0.069026, -0.066962, -0.035555, -0.025933, 0.035944, -0.078983, 0.06349, 0.071547, 0.04146, -0.006889, 0.023129, -0.023316, -0.023302, -0.029594, 0.033954, -0.117273, 0.050591, -0.027656, -0.007776, 0.015747, -0.071559, 0.040774, -0.000371, 0.042934, -0.002683, -0.0183, -0.045794, -0.053187, 0.014631, -0.061277, 0.021235, 0.073244, -0.003916, -0.057869, 0.03633, -0.0053, 0.03825, 0.004742, 0.011284, -0.103126, -0.069024, -0.012102, -0.018272, 0.021264, -0.107209, -0.035144, -0.054191, 0.102573, 0.057985, -0.052416, 0.007263, -0.016079, -0.023021, 0.003788, -0.000416, -0.081468, -0.019793, 0.053786, 0.06766, -0.02576, -0.0, -0.104301, -0.079946, -0.038072, 0.029913, -0.054901, -0.031646, -0.051896, -0.002555, 0.052064, -0.040671, -0.059612, 0.052462, 0.069309, 0.016511, 0.024392, -0.039951, 0.087157, -0.004604, 0.010604, -0.08797, 0.129662, 0.051487, -0.001961, -0.017384, -0.015924, 0.025813, -0.042515, 0.04171, 0.057651, -0.009072, 0.003138, 0.020354, 0.006395, 0.109905, -0.035543, -0.046641, 0.035064, 0.006737, -0.015815, 0.029449, 0.020024, 0.032935, -0.111043, -0.051666, -0.000581, -0.01218, 0.013732, 0.023595, 0.062445, 0.009036, -0.052202, -0.026131, -0.008636, -0.014548, -0.116487, 0.077669, 0.093303, -0.000328, -0.014678, 0.014919, -0.041454, 0.014801, 0.042395, -0.005187, -0.012171, -0.008358, -0.007644, 0.06363, 0.071983, -0.076715, 0.026447, -0.055226, -0.057355, 0.06936, -0.062141, -0.001094, -0.035778, -0.063426, -0.032451, -0.04084, 0.03048, -0.040764, 0.093319, 0.073305, 0.055694, 0.047797, -0.000252, -0.078255, -0.029191, -0.042534, -0.078872, -0.050017, -0.033068, 0.019379, -0.098648, -0.0, 0.027222, -0.040245, 0.090737, 0.021558, 0.078811, -0.04827, -0.017831, 0.085447, -0.074698, -0.079585, 0.018362, -0.05194, -0.048252, -0.018593, 0.060891, 0.015276, -0.014853, -0.029133, -0.016393, -0.011511, 0.034712, 0.017073, -0.009595, -0.074804, -0.019317, -0.032944, 0.015718, 0.090807, -0.002497, 0.030578, -0.084149, -0.022018, 0.117919, -0.018006, 0.03045, 0.031125, 0.068317, -0.010896, -0.03126, -0.002592, -0.034444, -0.073048, -0.012392, -0.041141, 0.036489, -0.088281, -0.026767, -0.038617, 0.150308, -0.007221, -0.042086, -0.053598, 0.056777, 0.106801, 0.097661, -0.080815, -0.025991, -0.089444, 0.041097, 0.03388, 0.005198, -0.070446, 0.059856, -0.092247]
A4: 3 | B4: d1b0bef8-6caa-4a64-88c9-3a0aa08b588b | C4: CBA.AX | D4: Interview: CBA AI chief on scaling A$400m in AI value with humans in loop | E4: Ranil Boteju, the chief AI officer at CBA, tells Satarupa Bhowmik how 80% of the bank's engineers use AI agents to triple code output and resolve over 15,000 security issues. | F4: Interview: CBA AI chief on scaling A$400m in AI value with humans in loop - Ranil Boteju, the chief AI officer at CBA, tells Satarupa Bhowmik how 80% of the bank's engineers use AI agents to triple code output and resolve over 15,000 security issues. | G4: [-0.012538, 0.012886, -0.11598, -0.005814, -0.089956, -0.032957, 0.043721, 0.082678, -0.035048, 0.01316, -0.038461, -0.068234, 0.036145, -0.036582, -0.028382, 0.116206, 0.019069, 0.014053, -0.070664, -0.1064, -0.031932, -0.077033, -0.036367, -0.034444, 0.003838, 0.030171, 0.040133, -0.088762, 0.010082, -0.058986, 0.006572, 0.054676, 0.100891, 0.004948, 0.009633, 0.012246, -0.018043, -0.011169, 0.093883, 0.019782, 0.010248, 0.002191, -0.024807, -0.092982, 0.066974, 0.027927, -0.021135, 0.063507, 0.021954, -0.008183, -0.060854, 0.036045, 0.011878, -0.00715, -0.042957, -0.060149, 0.049593, 0.001918, 0.088954, 0.022975, 0.034834, 0.034375, 0.053378, 0.066969, 0.183508, 0.005532, -0.085799, -0.076195, -0.058584, -0.018338, 0.040762, -0.048662, -0.040217, -0.060891, 0.07552, -0.00237, -0.012567, -0.017897, 0.053917, -0.061292, -0.004508, -0.08257, 0.004646, 0.047036, -0.010004, 0.030193, 0.02728, 0.003996, 0.041833, 0.048937, 0.090065, -0.035102, 0.042766, 0.003832, 0.035909, 0.048584, -0.076269, -0.028611, -0.015235, 0.008419, 0.080715, 0.001148, -0.000155, -0.03026, -0.075797, 0.016371, 0.143877, -0.008828, 0.0454, -0.038075, -0.012482, 0.020257, 0.027133, -0.034793, 0.024219, 0.002945, -0.010138, 0.109592, 0.01223, 0.022075, 0.074014, 0.00107, -0.027407, 0.020481, 0.0196, 0.020437, -0.070226, 0.0, -0.042624, 0.0452, 0.023326, -0.045375, 0.018921, -0.031081, -0.02153, -0.00581, -0.003386, 0.030854, -0.081154, 0.041718, -0.010982, 0.033067, 0.001511, -0.032408, -0.026142, 0.017773, -0.004157, 0.002231, 0.092136, -0.110355, 0.016975, 0.006774, 0.058758, 0.072965, 0.034642, -0.015586, 0.056088, 0.017174, -0.087615, 0.035706, -0.070798, -0.02006, -0.033862, -0.000653, 0.029476, -0.017115, -0.017309, 0.095296, -0.080477, 0.085855, 0.05475, -0.038629, -0.05171, 0.034664, -0.001804, -0.015514, -0.02503, -0.027074, -0.081002, 0.004528, -0.01965, -0.072604, 0.096105, -0.068194, 0.030492, 0.021384, 0.080379, 0.116826, -0.009728, 0.018497, -0.117222, 0.113315, -0.057496, 0.028934, -0.023902, 0.040191, 0.032796, -0.007122, -0.003107, 0.060485, 0.030315, 0.015759, -0.072871, -0.049024, 0.029475, -0.012195, 0.011905, 0.000665, -0.070253, 0.041145, 0.051313, -0.046775, 0.052161, -0.029634, -0.051861, -0.015458, -0.044089, 0.041592, -0.047138, -0.058207, 0.040225, 0.039614, -0.049135, -0.0, -0.1088, -0.02088, 0.002344, 0.001043, 0.037515, -0.017319, 0.000204, -0.007947, 0.018575, 0.037813, -0.055391, 0.002078, 0.030917, 0.055635, 0.054329, -0.040387, 0.005575, -0.054586, 0.026178, -0.032376, 0.041309, 0.039063, -0.00494, 0.04099, 0.019094, 0.033209, -0.103917, 0.026027, 0.052565, 0.017713, -0.0255, -0.06144, -0.063419, 0.073401, -0.056011, 0.033297, 0.041506, -0.034539, 0.02213, 0.080139, 0.013188, -0.027608, -0.115665, -0.04915, 0.030941, -0.001455, -0.00201, -0.020398, -0.025183, -0.045501, 0.018307, -0.008492, -0.013365, -0.023606, -0.103591, 0.054052, 0.04594, 0.017769, 0.018514, -0.043038, 0.021456, -0.02933, 0.035968, 0.030423, -0.08433, 0.035473, 0.053018, 0.050903, -0.063372, -0.039404, 0.051286, -0.099418, -0.011927, 0.052264, -0.070936, 0.04837, -0.053236, -0.062916, 0.047004, -0.029872, -0.078039, -0.030709, 0.026335, 0.027209, 0.065038, 0.086251, 0.044912, -0.057703, 0.0024, 0.07178, -0.060155, -0.009911, 0.026767, 0.004656, -0.10232, -0.0, -0.057239, -0.028972, 0.034136, 0.007394, 0.074098, -0.040717, -0.108153, -0.004753, -0.0204, -0.011062, 0.054615, -0.033423, -0.052624, 0.057077, 0.06337, 0.010182, -0.026861, 0.003649, 0.004236, -0.064013, 0.067049, 0.051329, -0.027514, -0.069233, 0.002067, -0.04136, -0.05192, 0.079587, -0.032464, 0.035908, -0.052478, 0.056316, -0.001441, -0.017247, 0.10305, -0.027211, -0.021575, 0.019025, -0.004455, -0.044715, -0.00861, -0.004309, 0.017782, -0.031841, 0.080898, -0.032403, -0.136556, -0.082605, 0.074137, -0.094088, 0.01561, -0.044086, 0.007668, 0.116952, 0.177159, -0.028598, -0.017508, -0.046684, -0.016376, 0.017031, -0.014366, -0.033761, -0.046361, -0.060704]
A5: 4 | B5: c23b800e-0d81-4f22-b84c-948dcb872f02 | C5: CBA.AX | D5: Asian Stocks Choppy as Investors Weigh Pause in Bond Selloff | E5: Asian equities fluctuated between gains and losses Thursday afternoon as investors weighed a pause in the global bond selloff, while the yen strengthened to nearly a four-week high against the dollar. | F5: Asian Stocks Choppy as Investors Weigh Pause in Bond Selloff - Asian equities fluctuated between gains and losses Thursday afternoon as investors weighed a pause in the global bond selloff, while the yen strengthened to nearly a four-week high against the dollar. | G5: [0.01166, -0.045078, 0.045879, 0.066219, -0.024982, -0.065276, 0.024268, 0.033273, -0.003228, -0.031656, 0.041612, 0.042376, -0.085986, -0.013278, 0.022194, -0.015344, -0.014185, 0.058692, -0.06073, -0.038472, -0.040678, -0.037289, 0.032682, 0.061973, 0.059942, 0.028826, -0.012083, 0.008807, 0.057151, -0.012636, -0.074995, 0.023487, 0.000374, 0.006776, -0.014882, 0.021985, -0.025838, 0.033625, 0.007844, -0.042056, 0.001968, 0.075948, 0.093572, -0.065885, 0.028537, -0.041628, 0.004171, -0.015631, 0.029607, -0.022143, -0.019503, 0.042335, -0.007857, -0.017647, -0.025504, 0.051457, 0.032655, 0.048858, -0.005133, 0.035595, -0.019947, 0.044812, 0.019297, -0.000278, 0.000988, 0.104439, 0.02356, 0.027931, 0.049329, 0.023005, 0.05449, 0.043029, -0.006387, -0.013097, -0.087729, -0.013848, 0.010651, -0.022438, 0.011174, -0.00271, -0.008383, -0.06722, 0.013826, -0.12394, 0.009291, 0.024355, 0.06053, -0.046977, -0.015593, 0.069678, 0.095373, 0.104904, 0.029348, 0.020234, -0.075201, 0.041495, 0.012571, -0.0286, -0.049781, 0.06418, 0.083693, 0.116603, -0.015073, 0.002576, -0.022808, -0.058453, 0.014261, -0.008747, -0.077801, 0.020998, -0.037108, 0.084524, -0.085124, -0.024337, -0.074404, 0.04995, -0.0017, -0.001924, -0.063186, 0.056525, 0.018742, -0.020778, -0.114183, -0.037478, 0.033675, 0.033634, -0.033676, 0.0, 0.004758, -0.054605, 0.028967, 0.041596, -0.117996, -0.018905, -0.057436, -0.020961, -0.098505, -0.023601, -0.018707, -0.037743, -0.011243, -0.041731, 0.069663, -0.092043, -0.010237, 0.068788, 0.048288, 0.029477, 0.045045, -0.024801, -0.002657, -0.032868, -0.064297, -0.017185, -0.025025, 0.001052, -0.047524, 0.052729, -0.007851, -0.020372, -0.013719, 0.004016, -0.08452, -0.055563, -0.026181, 0.005199, 0.045685, -0.002484, 0.000282, 0.03763, -0.063839, -0.033618, 0.033652, -0.013905, 0.01948, -0.049662, -0.035418, 0.082995, -0.01328, 0.027864, 0.002958, 0.095382, 0.016237, -0.012581, 0.116385, -0.068982, -0.110692, 0.033835, -0.023058, 0.027063, -0.097349, -0.037314, -0.105712, 0.082054, -0.024521, -0.030074, -0.168051, 0.042726, -0.002079, -0.040548, 0.054226, 0.040307, 0.011747, -0.059792, -0.056728, -0.02453, 0.029193, 0.034229, 0.065958, 0.005387, 0.041434, -0.007925, -0.06645, 0.026314, 4.5e-05, -0.011586, 0.051071, -0.008738, -0.018531, 0.002334, 0.096344, -0.014415, 0.009125, -0.0, -0.038556, -0.007143, -0.116241, 0.02376, 0.001491, 0.019246, 0.018153, 0.072684, -0.053585, -0.077295, 0.023441, -0.062653, -0.047262, 0.092164, -0.025025, -0.062096, 0.158013, 0.082233, 0.079285, -0.020674, 0.069573, -0.057856, 0.046898, 0.045126, 0.037668, 0.040798, -0.019251, 0.078258, 0.005124, 0.012284, 0.003385, 0.033115, 0.029506, 0.052861, -0.014158, 0.0048, -0.073127, -0.019282, -0.057968, -0.022594, -0.04742, 0.017942, 0.069864, 0.05258, 0.035696, 0.040778, 0.011961, 0.035558, -0.019948, -0.025275, -0.002721, 0.034306, -0.009934, 0.025149, -0.061497, 0.03215, -0.036708, -0.06489, -0.057958, 0.022006, -0.05226, -0.012589, 0.006918, 0.034028, 0.010144, -0.07104, 0.111345, -0.043653, 0.071207, -0.070872, 0.037237, -0.030551, 0.013688, -0.019339, 0.003105, 0.096441, -0.05834, -0.018672, 0.040315, 0.023548, 0.01855, 0.060555, 0.020461, 0.038869, -0.08989, 0.094791, -0.127003, 0.011066, 0.036082, 0.006766, -0.000175, 0.023678, 0.041795, -0.010548, 0.005947, -0.0, -0.004423, -0.096633, -0.018244, 0.032127, -0.084626, 0.016056, 0.054336, 0.02427, 0.073423, 0.005567, 0.033525, -0.010986, -0.056814, 0.009017, -0.104203, -0.078396, -0.037538, 0.126278, -0.020021, -0.047642, 0.062633, -0.053607, 0.060259, -0.04331, 0.006032, 0.03836, -0.071088, 0.07423, -0.016048, -0.036511, 9.2e-05, -0.073981, 0.080829, 0.080968, 0.062867, 0.0646, 0.019051, 0.014208, 0.003943, 0.045758, -0.023997, -0.068819, 0.009008, 0.023744, 0.067881, -0.021952, -0.004589, 0.060232, 0.123246, -0.09046, -0.023378, -0.039937, -0.088857, 0.000914, 0.003661, 0.004484, -0.008284, 0.021053, -0.042193, 0.008918, -0.055059, -0.106722, -0.150966, 0.093932]
A6: 5 | B6: 6192bccf-9d89-4bdf-b571-47e3e02b311d | C6: CBA.AX | D6: 3 Australian Dividend Stocks With At Least 3% Yield | E6: With Australian credit growth still resilient, income investors are looking harder at local businesses that share profits through dividends. Higher global interest rate expectations have pushed up funding costs, so reliable cash payouts from established Australian dividend stocks can feel even more valuable. This article walks through three higher yielding dividend options from a focused screener and explains why they may deserve a closer look now. The three stocks in this article are just a... | F6: 3 Australian Dividend Stocks With At Least 3% Yield - With Australian credit growth still resilient, income investors are looking harder at local businesses that share profits through dividends. Higher global interest rate expectations have pushed up funding costs, so reliable cash payouts from established Australian dividend stocks can feel even more valuable. This article walks through three higher yielding dividend options from a focused screener and explains why they may deserve a closer look now. The three stocks in this article are just a... | G6: [-0.033398, -0.06279, -0.035794, 0.019417, 0.038975, 0.048319, -0.003688, -0.022353, 0.063222, 0.038204, 0.012999, 0.001172, -0.097216, 0.075997, -0.0003, -0.00179, -0.054892, -0.022133, 0.00314, 0.017766, -0.088347, -0.025548, 0.00551, 0.024832, 0.140462, 0.006124, -0.03393, 0.028531, 0.035762, -0.032797, 0.029336, 0.137494, 0.123737, -0.067748, -0.023733, 0.012263, -0.004666, 0.004278, 0.038314, 0.0256, 0.025714, 0.036501, 0.047901, -0.04613, -0.05459, -0.096765, 0.042904, -0.073374, 0.033903, 0.040374, -0.018402, 0.019302, 0.002976, -0.09142, -0.028839, -0.08282, -0.025024, 0.02538, 0.02701, -0.023369, 0.01654, 0.007606, 0.05696, -0.018498, 0.059522, 0.038679, -0.057804, 0.064672, -0.06199, -0.011219, -0.022834, -0.010549, -0.073946, -0.087633, -0.087294, 0.031744, 0.059974, 0.026554, -0.015915, -0.019208, -0.045571, -0.024149, 0.005349, 0.033407, -0.052269, -0.079067, 0.074379, -0.032687, 0.045162, -0.014693, -0.011429, 0.035333, 0.033186, 0.020033, 0.014854, 0.01113, -0.091109, -0.101596, -0.120284, -0.035603, 0.10646, 0.094692, -0.00985, 0.025594, 0.027317, -0.015588, -0.044961, -0.008552, 0.096738, 0.037279, 0.011717, 0.087717, -0.042879, -0.036077, -0.078595, 0.005879, -0.085958, -0.005871, 0.088067, 0.042463, 0.065902, 0.053821, -0.038762, -0.073755, 0.086091, -0.003615, -0.034206, 0.0, 0.009703, 0.021216, 0.070019, 0.073728, 0.052045, -0.054178, -0.027717, -0.047258, -0.083541, 0.007728, -0.011361, 0.035057, 0.064703, -0.028337, 0.017274, -0.044751, -0.039663, 0.031756, 0.040799, 0.087544, 0.053848, 0.01641, 0.044853, -0.050545, 0.090704, -0.074787, 0.018263, 0.018384, -0.002795, 0.004046, 0.02732, 0.038173, -0.077415, -0.048141, -0.06172, 0.004771, -0.017529, 0.000809, 0.017799, -0.016633, -0.002985, -0.028749, -0.022404, 0.024168, 0.028551, -0.005224, -0.009965, -0.034465, 0.004665, 0.078241, -0.039024, 0.014724, -0.034574, 0.006383, -0.019045, -0.028243, -0.064125, -0.000688, -0.010846, -0.041689, 0.023454, -0.019199, -0.107235, -0.026625, -0.094381, 0.098856, 0.035136, -0.026396, -0.068526, 0.107121, -0.052185, 0.011528, 0.076394, -0.01146, -0.026023, -0.025964, -0.072124, 0.031739, 0.093549, -0.00537, 0.021419, 0.016444, -0.012508, -0.029643, -0.011814, 0.016027, 0.023039, -0.020618, 0.050984, -0.010706, -0.044593, -0.039208, 0.059729, -0.074656, -0.011816, -0.0, -0.008591, -0.075617, -0.006539, -0.013521, -0.030857, -0.025071, 0.038225, 0.007591, 0.016773, 0.014862, -0.040274, 0.107347, 0.016274, 0.002994, -0.017096, -0.020261, 0.081323, -0.034544, 0.092009, -0.116082, 0.055895, -0.018632, -0.053243, 0.071107, 0.014677, 0.071351, -0.091858, -0.024914, 0.024415, -0.049953, -0.071365, 0.04838, -0.041459, 0.025277, -0.030129, 0.01361, -0.047325, 0.023822, -0.002481, 0.08349, -0.017651, -0.002211, 0.012861, 0.004057, -0.035281, 0.008211, 0.008024, 0.060645, 0.023984, 0.027451, -0.031405, 0.012911, -0.054424, 0.088261, -0.033515, 0.044367, -0.054878, 0.006243, 0.012216, 0.054401, -0.021411, 0.126845, -0.001505, 0.012, -0.002952, 0.020292, -0.058679, 0.051607, -0.010668, -0.028921, 0.073891, -0.050505, 0.104447, -0.037335, 0.064165, 0.154246, -0.011543, -0.036576, -0.016681, 0.032215, 0.071552, 0.002008, 0.013224, 0.122084, -0.084288, 0.050927, 0.038767, -0.005652, 0.048191, -0.089701, -0.073369, -0.060396, 0.061385, 0.096097, 0.01883, -0.0, -0.059885, -0.063388, -0.071662, -0.021733, -0.010966, 0.001806, 0.035117, 0.023631, 0.036891, 0.004711, 0.041199, -0.029597, -0.086464, 0.001602, -0.020442, -0.015193, -0.037965, 0.018388, -0.014379, -0.049863, 0.026017, 0.011295, 0.058429, 0.005308, -0.019795, 0.062008, -0.021962, -0.012166, -0.056835, 0.080527, -0.010668, 0.023586, 0.023859, 0.03552, -0.023938, 0.002734, 0.020568, 0.033199, 0.042637, 0.037863, -0.033515, -0.120465, -0.082945, -0.015058, -0.096109, -0.015225, -0.085004, 0.000666, -0.013544, -0.128217, -0.023672, 0.009895, -0.034127, 0.099384, 0.018129, 0.001479, -0.104063, -0.006772, 0.014251, -0.028147, -0.038325, -0.161041, 0.028854, 0.077417]
A7: 6 | B7: c385b2b8-f8e0-4278-99be-f30dbd1d2167 | C7: CBA.AX | D7: 3 Australian Dividend Stocks Paying Over 5% While Cash Income Looks Less Certain | E7: With bond yields across major markets reflecting expectations for tighter central bank policy, income from cash and short-term bonds can feel uncertain again. Reliable dividend income looks more valuable when policy paths shift and inflation stays in focus. Dividend powerhouses with yields above 5% and well covered, growing payouts offer one way to seek steadier cash flow. This article highlights three stocks from that screener. The three dividend stocks covered next are just a sample from... | F7: 3 Australian Dividend Stocks Paying Over 5% While Cash Income Looks Less Certain - With bond yields across major markets reflecting expectations for tighter central bank policy, income from cash and short-term bonds can feel uncertain again. Reliable dividend income looks more valuable when policy paths shift and inflation stays in focus. Dividend powerhouses with yields above 5% and well covered, growing payouts offer one way to seek steadier cash flow. This article highlights three stocks from that screener. The three dividend stocks covered next are just a sample from... | G7: [-0.057789, -0.067497, -0.038848, -0.006074, 0.049677, 0.020223, 0.014186, -0.059408, 0.01436, 0.042265, -0.005234, -0.016453, -0.106396, 0.047942, 0.016012, -0.00426, -0.026763, 0.017775, 0.000381, 0.013634, -0.046898, -0.043421, 0.004105, 0.025199, 0.139629, 0.040418, -0.023361, -0.002571, 0.020517, -0.042867, 0.061013, 0.080699, 0.072357, -0.039605, -0.045642, 0.010168, 0.009997, -4.8e-05, 0.047278, 0.082704, 0.016979, 0.008351, 0.038544, -0.049847, -0.044101, -0.103143, 0.02416, -0.031182, 0.030648, 0.026158, -0.012523, -0.001473, -0.000913, 0.005809, -0.043978, -0.052525, -0.006718, -0.000299, 0.008393, -0.020836, 0.012688, -0.002832, 0.051301, -0.011281, 0.023451, 0.021341, -0.061939, 0.061655, -0.067781, -0.026301, -0.046574, -0.027186, -0.062216, -0.095079, -0.103491, 0.015898, 0.085154, 0.02442, -0.014672, -0.051802, -0.022162, 0.021543, 0.003211, 0.006509, -0.035044, -0.085559, 0.048169, -0.034129, 0.019443, -0.025696, 0.002839, 0.02999, 0.019448, 0.03569, 0.035328, 0.023285, -0.068716, -0.07827, -0.06906, -0.02592, 0.122069, 0.107166, 0.013062, 0.062032, 0.045799, -0.01173, -0.050353, -0.006879, 0.049229, -0.003461, 0.019959, 0.083248, -0.003547, -0.024443, -0.043091, 0.003731, -0.085223, 0.020454, 0.096838, 0.064675, 0.087864, 0.058495, 0.004078, -0.06512, 0.102333, 0.024386, 0.017787, 0.0, 0.001994, -5.1e-05, 0.065808, 0.107051, 0.036778, -0.042468, -0.025758, -0.058192, 0.001896, -0.001499, -0.023045, 0.034614, 0.035516, 0.006262, -0.015021, -0.051388, -0.075963, 0.054759, 0.043029, 0.093616, 0.009189, 0.007084, 0.017914, -0.034358, 0.096235, -0.034361, 0.012088, -0.0101, -0.00195, 0.033213, 0.027337, 0.07503, -0.049076, -0.087093, -0.077342, -0.006631, 0.002283, 0.001169, 0.027754, -0.03903, -0.010375, -0.06847, 0.005258, 0.003921, -0.04097, -0.043363, -0.024966, -0.007764, 0.007943, 0.035952, -0.015335, -0.01482, -0.018724, -0.008239, -0.037553, -0.040308, -0.062483, -0.020336, -0.023894, -0.029331, -0.021219, 0.001352, -0.127114, -0.008723, -0.112472, 0.111268, 0.032436, 0.015765, -0.060501, 0.119657, -0.034973, 0.02492, 0.059728, 0.046371, -0.012712, 0.007579, -0.047222, 0.04256, 0.039228, -0.010427, 0.004235, 0.024952, 0.035992, -0.035569, 0.003434, 0.037745, 0.026836, -0.043642, 0.074315, -0.026255, -0.031465, -0.064899, 0.08472, -0.062155, -0.03526, -0.0, -0.002052, -0.006679, -0.027615, -0.013196, -0.065484, 0.000394, 0.053862, 0.006183, 0.004691, 0.056055, -0.045581, 0.112403, -0.025977, -0.024802, -0.002404, -0.01926, 0.064333, -0.060075, 0.07225, -0.094624, 0.084337, -0.041552, -0.061363, 0.103425, 0.03307, 0.078318, -0.131589, -0.039977, 0.031958, 0.000666, -0.012725, -0.031753, -0.016135, -0.025302, -0.020049, 0.012433, -0.063916, 0.024233, -0.029964, 0.079661, -0.043997, -0.018943, 0.042876, 0.006462, -0.027361, -0.027067, -0.00616, 0.057294, 0.041192, 0.033815, -0.020099, 0.036538, -0.03292, 0.099595, -0.06194, 0.062362, -0.053626, 0.034991, -0.036331, 0.0341, -0.033094, 0.092096, -0.003643, -0.025441, 0.017592, 0.01472, -0.079181, 0.040033, -0.000554, -0.014478, 0.067502, -0.038933, 0.132521, -0.040808, 0.08462, 0.1724, -0.005219, -0.034553, -0.015078, 0.105288, 0.032454, -0.029884, 0.040922, 0.077575, -0.12378, 0.069438, 0.029925, -0.028446, 0.059766, -0.088874, -0.044461, -0.077104, 0.016394, 0.056768, 0.033577, -0.0, -0.025527, -0.070194, -0.034646, -0.057568, -0.028021, -0.0212, 0.019247, -0.007769, 0.055982, -0.003377, 0.032101, 0.012563, -0.04556, -0.024229, -0.045145, -0.016047, -0.052995, 0.015026, -0.016144, -0.081697, 0.041519, 0.008948, 0.023312, 0.01031, -0.016526, 0.06601, 0.005115, 0.008435, -0.050238, 0.069294, 0.00343, 0.020149, 0.022777, -0.003936, 0.022554, 0.047384, 0.089271, 0.006344, 0.047465, 0.081789, -0.019996, -0.144097, -0.056617, -0.010449, -0.081477, -0.013347, -0.097098, 0.010297, -0.025274, -0.161412, -0.018316, 0.027139, -0.060505, 0.084407, 0.005605, -0.056244, -0.104534, 0.011109, 0.008219, -0.039767, -0.035579, -0.108341, 0.058339, 0.08328]
A8: 7 | B8: 3197f837-7d31-4fd0-9208-cca4c823c4f2 | C8: CBA.AX | D8: Three of Australia's four major banks forecast another rate hike this year | E8: SYDNEY, Aug 27 (Reuters) - The Commonwealth Bank of Australia and the National Australia Bank on Thursday joined ANZ in forecasting another rate hike this year after a hot inflation print reignited | F8: Three of Australia's four major banks forecast another rate hike this year - SYDNEY, Aug 27 (Reuters) - The Commonwealth Bank of Australia and the National Australia Bank on Thursday joined ANZ in forecasting another rate hike this year after a hot inflation print reignited | G8: [-0.012481, -0.089297, -0.074646, 0.090728, 0.00413, 0.011362, -0.042485, -0.020466, -0.013267, 0.053397, -0.024232, -0.035385, -0.034141, 0.067862, 0.022673, 0.031259, -0.147181, -0.022818, -0.004399, -0.05586, -0.034669, -0.052577, -0.022253, -0.003983, 0.061569, -0.017235, -0.029606, 0.030687, -0.050763, -0.023831, -0.066742, 0.088887, -0.041855, -0.078016, 0.050129, -0.058526, -0.003425, 0.022525, -0.005074, 0.003898, 0.101183, 0.036508, 0.042075, 0.006503, -0.015163, 0.00705, -0.005446, -0.002163, -0.030186, 0.096998, -0.018457, -0.036562, 0.020815, -0.044477, -0.025067, -0.019503, -0.028591, -0.033877, 0.015728, -0.096853, 0.008592, 0.009368, -0.027925, -0.006067, 0.059894, 0.072825, -0.103585, -0.007393, -0.061148, -0.002908, -0.085563, -0.139079, 0.021162, -0.104836, -0.007875, -0.041084, 0.153892, 0.049792, 0.00806, -0.047913, 0.03201, -0.079706, 0.015977, -0.049254, -0.008581, -0.057645, 0.06157, -0.038224, 0.013095, 0.015502, 0.014669, 0.058092, 0.043053, -0.003379, -0.004651, 0.018286, -0.071806, -0.057019, 0.051024, 0.002236, 0.134502, 0.068002, 0.051792, 0.140443, 0.052116, 0.043389, -0.051361, -0.006195, 0.053082, 0.012356, 0.011348, 0.093648, 0.016355, -0.054329, -0.023662, 0.054115, -0.012997, 0.073378, 0.035261, 0.083444, -0.004557, -0.01556, 0.049098, -0.047411, 0.105864, 0.059153, -0.082906, -0.0, -0.04459, 0.030545, 0.05208, -0.05746, 0.043108, -0.038346, -0.040713, 0.010267, -0.032947, -0.036429, -0.013168, 0.043416, 0.065329, 0.042315, -0.066803, -0.069326, 0.070583, 0.006289, 0.01961, 0.11586, -0.026012, 0.036539, -0.005753, 0.007076, -0.000273, -0.001441, 0.097347, 0.010847, -0.011151, -0.006439, 0.022654, 0.013291, -0.075208, -0.058027, 0.016691, -0.022115, 0.059968, 0.021055, 0.018801, -0.03295, 0.032079, -0.032073, 0.002828, -6.2e-05, -0.013797, 0.056735, -0.098866, -0.07747, -0.02468, -0.006015, -0.017341, -0.045379, -0.087895, 0.010185, 0.012933, -0.026293, -0.107196, -0.005251, 0.090934, -0.009861, -0.001225, -0.058138, -0.102678, -0.018638, -0.039532, 0.00866, 0.069443, 0.000832, -0.069702, 0.061821, -0.046568, 0.008132, 0.044403, 0.045084, -0.001183, 0.028219, 0.04048, -0.024395, 0.063584, -0.010956, -0.059086, 0.062314, 0.030957, -0.01316, 0.002154, -0.050211, 0.003763, -0.017579, 0.046342, -0.054251, -0.030817, -0.011359, 0.035577, 0.007409, 0.027087, -0.0, 0.038513, 0.024147, -0.021706, 0.018278, -0.03554, -0.084068, 0.096959, 0.004761, 0.044852, -0.015903, 0.022014, 0.107664, 0.017528, -0.026077, 0.067362, 0.019373, 0.072588, -0.046754, 0.051634, -0.045009, 0.002816, -0.06276, -0.013236, 0.068527, -0.129242, 0.031451, -0.01048, -0.025802, -0.07249, -0.00722, -0.100037, -0.005887, 0.047256, -0.021109, -0.079489, 0.054966, 0.000234, -0.012772, -0.039824, 0.056163, 0.005542, 0.069543, -0.022919, -0.048356, -0.010459, 0.065063, -0.012007, 0.079553, -0.030604, 0.055914, -0.014365, -0.005876, -0.045089, 0.004353, -0.055726, 0.022117, 0.042125, -0.047094, -0.022967, 0.059381, 0.052688, 0.070566, 0.040667, -0.019341, 0.052504, -0.044582, 0.020528, -0.049456, 0.037093, -0.009087, -0.005951, 0.051257, -0.044309, 0.062299, 0.044287, 0.074119, -0.022479, -0.063714, 0.008179, 0.015093, -0.056673, 0.04738, 0.020745, 0.090178, -0.068882, -0.030768, 0.111254, -0.01577, 0.07085, -0.121569, -0.01956, -0.043861, 0.009467, 0.075426, -0.060046, -0.0, -0.040154, -0.069876, -0.005774, -0.003656, 0.015957, -0.003267, 0.00301, 0.074665, 0.08221, -0.00425, 0.09848, 0.020706, -0.043107, 0.011746, 0.045996, 0.05163, -0.009444, -0.036418, -0.022765, -0.092553, -0.055722, 0.08874, -0.012259, -0.013041, 0.034269, 0.014451, -0.013898, 0.084348, 0.008778, -0.010286, -0.049741, 0.023665, 0.026901, -0.048588, -0.023587, -0.023528, 0.098475, 0.014039, 0.065901, -0.018287, 0.013341, -0.085884, -0.055978, 0.00102, -0.048944, -0.056165, -0.058136, -0.058296, -0.009957, -0.061462, -0.029323, 0.043408, -0.015728, 0.080987, 0.029282, -0.106129, -0.103175, -0.047454, -0.000995, -0.014196, 0.050634, -0.123114, -0.031532, -0.009935]
A9: 8 | B9: 8c255177-b931-4783-a1bf-9e2dacfa1b3c | C9: CBA.AX | D9: Commonwealth Bank Stock And 2 More Dividend Shares For Reliable Income | E9: Rising yields in major markets are pushing income investors to think harder about where their cash flow comes from. With bond markets adjusting to tighter policy signals, dependable company dividends can feel more valuable than ever. That is where the Dividend Powerhouses 3%+ Yield screener comes in. This article walks through three high income stocks on that list and what makes their dividend profiles worth a closer look. The three stocks below are just a starting sample, and the full... | F9: Commonwealth Bank Stock And 2 More Dividend Shares For Reliable Income - Rising yields in major markets are pushing income investors to think harder about where their cash flow comes from. With bond markets adjusting to tighter policy signals, dependable company dividends can feel more valuable than ever. That is where the Dividend Powerhouses 3%+ Yield screener comes in. This article walks through three high income stocks on that list and what makes their dividend profiles worth a closer look. The three stocks below are just a starting sample, and the full... | G9: [-0.004529, -0.088327, -0.03772, 0.019162, 0.018223, 0.01208, 0.014884, -0.024524, 0.014824, -0.000428, -0.018432, 0.018914, -0.0798, 0.055464, 0.040882, -0.006228, -0.002003, 0.042121, 0.003666, 0.009708, -0.047172, -0.076137, 0.036173, 0.005862, 0.096305, -0.001359, -0.023781, 0.00557, -0.001382, -0.0691, 0.002063, 0.07754, 0.080843, -0.033729, 0.007586, -0.017102, 0.042711, 0.0592, 0.06813, 0.016906, 0.025465, 0.007664, 0.04784, 0.030521, 0.007643, -0.063344, 0.039899, -0.027337, 0.040985, 0.014297, -0.050866, 0.00537, 0.041791, -0.052264, -0.029743, -0.038775, -0.063049, 0.045826, 0.093519, -0.036714, -0.003311, 0.030946, 0.058381, -0.0033, 0.085644, 0.009215, -0.025081, 0.091884, -0.051982, -0.025431, -0.028614, -0.035247, -0.081366, -0.111993, -0.104262, 0.025818, 0.045064, 0.025598, -0.02613, -0.022196, -0.018517, 0.006548, 0.021709, 0.012863, -0.004606, -0.068554, 0.046796, -0.028772, -0.001632, -0.019072, -0.014589, 0.00245, 0.061374, 0.005108, 0.028322, 0.040976, -0.074128, -0.104445, -0.074403, 0.000517, 0.092284, 0.119734, -0.005679, 0.10129, 0.046889, -0.020167, -0.064529, 0.010292, 0.08174, 0.037341, 0.051029, 0.113491, -0.058085, -0.041687, -0.053233, -0.024125, -0.029333, 0.018046, 0.100735, 0.080306, 0.091249, -0.010274, -0.028385, -0.046852, 0.084757, 0.008887, -0.041933, 0.0, -0.012168, 0.035764, 0.065847, 0.085491, 0.00582, -0.020191, -0.041646, -0.038427, -0.076389, 0.005141, -0.05672, 0.053396, 0.053577, 0.009853, 0.00458, -0.030604, -0.038561, 0.056082, 0.044244, 0.042178, -0.027739, 0.027874, 0.027928, -0.04493, 0.080676, -0.094956, -0.010328, 0.005525, 0.023172, 0.036468, 0.050089, 0.012159, -0.054213, -0.037938, -0.071686, -0.012377, -0.048514, -0.015765, 0.048301, -0.034355, -0.021512, -0.052949, 0.036801, 0.0266, -0.038888, -0.009613, -0.025262, -0.0225, -0.014878, 0.035473, -0.021639, -0.006, -0.091515, -0.019695, -0.040213, -0.025322, -0.03439, -0.011092, -0.002817, -0.00183, -0.017928, -0.003483, -0.137087, -0.000604, -0.071849, 0.085072, -0.016167, 0.045813, -0.078667, 0.127031, -0.017927, 0.026309, 0.043924, -0.012915, -0.021677, 0.026149, -0.03615, 0.028537, 0.070771, -0.003309, 0.039857, 0.001859, 0.023904, -0.008027, -0.014211, 0.015628, -0.021452, -0.011928, 0.053143, -0.010207, -0.015406, -0.073737, 0.092637, -0.040573, -0.032598, -0.0, -0.026613, -0.012378, 0.006217, -0.047479, -0.074155, -0.068773, 0.063253, -0.059191, -0.021617, 0.042865, -0.003411, 0.028059, 0.011261, 0.063988, -0.066075, -0.020844, 0.04816, -0.042628, 0.1088, -0.073522, 0.069332, -0.014595, -0.018991, 0.098499, -0.037155, 0.079467, -0.14488, -0.034714, 0.051874, 0.005879, -0.056719, -0.014562, -0.024233, -0.028371, -0.037775, 0.027835, -0.071294, -0.03415, 0.016213, 0.093502, -0.007764, 0.001179, -0.00864, -0.05295, 0.031381, 0.046958, 0.07113, 0.056544, 0.079115, 0.007428, -0.01303, 0.04492, -0.037546, 0.136016, -0.043332, 0.030177, -0.044606, 0.016257, -0.007054, 0.012323, -0.028253, 0.084676, -0.00858, -0.009576, 0.019923, 0.027827, -0.0851, 0.051541, 0.000928, -0.040617, 0.054757, -0.067783, 0.135692, -0.037695, 0.014172, 0.12176, -0.005345, -0.074949, 0.002311, 0.068505, 0.042108, 0.011378, 0.001376, 0.084193, -0.092431, 0.051161, 0.045452, -0.039669, 0.04115, -0.085509, -0.047999, -0.032542, 0.060841, 0.10181, 0.020558, -0.0, -0.021126, -0.07759, -0.053878, -0.059245, 0.036207, -0.082662, 0.019591, 0.005212, 0.040888, 0.003107, 0.010643, -0.013468, -0.075324, -0.059212, 0.022025, 0.027008, -0.033228, -0.033216, 0.005207, -0.095689, 0.064721, -0.003049, 0.083104, 0.000514, -0.070823, 0.044436, 0.022357, -0.025397, -0.010078, 0.048202, -0.017247, 0.005113, 0.016081, 0.00803, 0.012433, 0.037507, 0.024692, -0.024871, 0.087465, 0.072746, -0.033831, -0.113158, -0.069675, 0.045738, -0.014795, -0.041902, -0.053653, 0.017604, -0.034, -0.186873, -0.042654, 0.014995, -0.039922, 0.100883, 0.014552, -0.025616, -0.121687, 0.010744, -0.007823, -0.025065, -0.020446, -0.092016, 0.051763, 0.042317]
A10: 9 | B10: 413c847a-f31f-48e9-8aa3-215b13213f26 | C10: CBA.AX | D10: Commonwealth Bank unveils payout platform ahead of cheque exit | E10: PaidIt combines recipient verification, communications and payment delivery within one system. | F10: Commonwealth Bank unveils payout platform ahead of cheque exit - PaidIt combines recipient verification, communications and payment delivery within one system. | G10: [0.003039, 0.048538, -0.059951, -0.032072, 0.021904, 0.00507, 0.077272, -0.042013, 0.00436, 0.018521, 0.008259, -0.035445, -0.020477, -0.030273, 0.050149, -0.056632, -0.012615, 0.002583, 0.02737, 0.01361, -0.069013, -0.061577, -0.026105, 0.007186, 0.017522, -0.046949, -0.035053, 0.009776, -0.064786, -0.037038, 0.009514, 0.037567, -0.050402, -0.013724, -0.002315, 0.041878, -0.005673, 0.005766, -0.137871, -0.09111, 0.019019, -0.04543, -0.047175, 0.028821, 0.067832, 0.060526, -0.027839, 0.049259, -0.070811, 0.004708, 0.062417, -0.043993, 0.033604, 0.10229, -0.074849, 0.019303, 0.058452, 0.013633, -0.00793, -0.117637, -0.006319, 0.021799, -0.095868, 0.019443, 0.050439, 0.060723, -0.019642, 0.028235, -0.002422, -0.064052, -0.03663, -0.087194, 0.035479, -0.01948, 0.004408, 0.097474, 0.063014, -0.009476, -0.005301, 0.033495, 0.032608, 0.078002, -0.047615, 0.004736, 0.031484, -0.007102, -0.025048, 0.011717, 0.018453, -0.104228, -0.042005, 0.043246, 0.106976, -0.068994, 0.058966, -0.083061, 0.013162, -0.043273, 0.066555, -0.005726, 0.10384, 0.061884, 0.029854, -0.001092, 0.073161, 0.069053, 0.003892, 0.015145, 0.153194, -0.047851, -0.024987, -0.02687, 0.076382, 0.002874, 0.061226, 0.120404, -0.094396, 0.087347, 0.097589, -0.025455, 0.021076, -0.001035, -0.073686, -0.124663, 0.005216, 0.012246, 0.027541, 0.0, -0.062279, -0.033208, 0.067412, 0.043127, 0.088416, -0.044801, -0.05452, 0.008989, -0.043747, 0.034044, -0.023896, -0.028276, 0.032761, 0.086224, -0.018633, -0.020775, 0.016351, 0.066151, 0.099192, 0.107618, -0.01892, -0.025774, 0.013264, -0.019929, 0.060981, 0.030106, -0.041889, -0.015041, 0.020449, -0.013093, -0.001393, -0.008656, -0.050846, 0.058432, -0.101906, -0.005682, -0.000671, -0.076294, 0.081126, -0.080318, -0.021546, -0.057455, 0.002535, 0.023516, -0.047986, -0.009434, -0.005089, -0.062365, 0.093436, 0.025644, -0.005862, 0.013876, -0.084318, -0.028866, 0.001621, -0.035558, 0.050704, 0.043371, -0.005599, -0.047496, -0.028172, -0.002565, -0.07198, -0.054288, 0.004234, 0.026336, -0.061189, -0.052616, -0.016315, 0.036913, -0.062812, 0.107168, 0.070581, 0.014653, -0.015231, 0.016041, -0.016679, -0.002245, 0.104737, 0.099705, 0.036349, 0.046712, -0.05835, 0.005888, 0.066205, -0.002324, 0.006801, -0.095952, -0.000874, -0.043414, 0.000633, -0.006933, -0.010451, 0.083232, 0.087538, -0.0, -0.037081, -0.029996, -0.036283, 0.076076, -0.069415, -0.002282, 0.005954, -0.036479, 0.092258, 0.071094, -0.041877, 0.002949, 0.082882, -0.015515, 0.035248, -0.045813, -0.010137, -0.05177, 0.059639, 0.041263, 0.087236, 0.002428, 0.015877, -0.016855, 0.064924, 0.010171, 0.009083, -0.106705, -0.017107, -0.005261, 0.036537, -0.022528, -0.015218, -0.046678, -0.029242, -0.04883, -0.057106, 0.065078, 0.021956, 0.073488, -0.029865, -0.049438, -0.061491, 0.021561, 0.006026, -0.059757, -0.048315, 0.082295, 0.081569, 0.017819, 0.017452, 0.012208, -0.009909, 0.08011, -0.015169, 0.107127, 0.060818, 0.043415, -0.026563, -0.015185, 0.012639, -0.045839, 0.021721, -0.040536, 0.071637, 0.034938, -0.01697, 0.043934, 0.020407, -0.019311, -0.016912, -0.032586, 0.042016, -0.038809, 0.055019, 0.078575, -0.024702, -0.096722, -0.037866, 0.043778, -0.043553, -0.027449, 0.078503, 0.080323, 0.016865, -0.070829, -0.010886, -0.084274, -0.015931, -0.047004, -0.00235, -0.03892, 0.093375, 0.041956, -0.054079, -0.0, -0.009334, -0.024866, -0.036326, -0.041113, -0.010535, -0.045983, -0.003618, 0.055123, -0.048328, -0.026099, -0.028609, -0.024708, -0.013939, 0.006138, 0.027946, 0.049712, 0.047511, -0.069521, -0.058612, -0.000283, 0.006237, -0.017897, -0.060841, -0.035299, -0.112494, -0.01085, 0.059426, 0.069992, 0.013956, -0.072045, -0.079755, 0.008839, -0.022407, 0.00433, 0.084573, 0.075236, 0.073775, 0.0134, 0.002321, 0.01507, -0.019966, -0.042246, -0.091533, 0.006507, -0.03262, 0.001351, -0.057575, 0.058363, -0.075239, -0.061165, 0.021292, -0.018057, 0.007693, 0.046459, 0.039756, -0.038405, -0.021203, 0.003197, 0.108863, 0.08815, -0.009258, -0.032166, 0.071891, -0.088588]
A11: 10 | B11: 686cdb0c-4e0e-4c16-82e8-cc5fb13cd2ca | C11: CBA.AX | D11: Australian bank investors brace for tough times as mortgage demand plummets | E11: By Christine Chen and Scott Murdoch SYDNEY, Aug 25 (Reuters) - Investors are questioning the rich valuations on Australia's biggest banks as a downturn in lucrative mortgage lending threatens to | F11: Australian bank investors brace for tough times as mortgage demand plummets - By Christine Chen and Scott Murdoch SYDNEY, Aug 25 (Reuters) - Investors are questioning the rich valuations on Australia's biggest banks as a downturn in lucrative mortgage lending threatens to | G11: [0.052726, -0.081897, -0.036968, 0.029312, -0.085031, -0.002879, -0.035874, 0.044571, -0.042926, 0.025475, -0.062607, 0.010172, -0.0446, 0.025229, 0.034985, 0.008114, -0.037028, -0.030835, 0.005956, 0.072647, -0.062635, -0.038834, -0.059913, -0.012119, 0.075357, 0.000967, 0.036313, 0.029956, 0.020128, -0.003434, -0.04865, 0.045097, -0.006596, -0.017475, 0.064961, 0.025881, -0.008346, -0.031173, 0.009937, -0.049398, 0.080566, -0.027419, 0.023986, -0.036022, -0.054992, -0.035897, 0.107157, 0.045079, -0.01668, 0.066605, -0.065557, 0.004005, 0.068107, -0.096222, -0.023443, 0.027864, 0.027886, 0.000599, 0.023047, -0.045323, 0.069265, 0.034469, 0.033502, 0.011377, 0.084644, 0.06631, -0.052825, 0.010431, -0.044406, 0.029597, -0.005163, -0.137047, -0.02021, -0.086881, 0.000494, -0.024045, 0.067445, -0.017881, 0.020899, -0.047949, 0.106549, -0.160451, -0.094481, -0.039238, -0.028311, 0.000136, 0.091852, -0.033647, 0.071603, -0.007952, 0.055256, -0.017529, 0.035328, 0.039685, 0.024943, -0.00095, -0.087112, -0.052553, -0.031993, 0.055766, 0.006431, 0.059345, 0.012162, 0.053177, -0.004912, -0.050763, -0.020588, -0.005488, 0.005091, -0.008583, 0.035606, 0.10337, 0.036154, 0.024719, -0.014949, -0.039329, 0.012188, 0.029272, -0.031712, 0.031482, 0.082812, -0.013747, -0.059437, -0.030512, 0.032683, 0.017726, -0.116206, 0.0, 0.001667, 0.004579, 0.05241, -0.029804, 0.00514, -0.03377, -0.06375, -0.013697, -0.056454, 0.034586, 0.080711, -0.015849, 0.023015, 0.029463, -0.054, -0.015775, 0.016155, 0.035894, -0.005101, 0.050972, 0.020428, 0.000618, 0.02292, -0.003762, 0.005427, -0.1015, 0.026604, 0.021079, -0.004396, 0.003759, -0.003281, -0.069023, -0.041193, -0.068773, -0.053672, 0.014725, 0.002872, -0.01777, 0.014501, 0.01313, -0.04992, -0.019838, 0.010573, 0.01796, 0.006464, 0.039071, -0.043627, -0.036886, -0.110046, 0.043255, -0.004958, -0.052008, -0.079468, 0.031018, 0.000946, -0.051036, -0.061875, -0.022414, -0.038451, -0.032476, -0.020249, -0.128783, -0.08277, -0.05075, -0.065273, 0.087785, 0.071226, 0.054626, -0.079816, 0.082576, -0.062877, -0.010253, -0.037195, -0.015688, -0.043611, -0.03145, 0.037785, 0.063208, 0.114132, 0.071076, 0.046347, 0.029185, 0.042234, 0.011587, -0.00499, 0.026044, -0.007527, -0.06636, 0.045405, -0.086167, -0.052291, 0.003534, 0.084929, -0.034291, -0.000695, -0.0, -0.077807, -0.053454, -0.087463, 0.043321, -0.041116, -0.070184, 0.01002, 0.01207, -0.001147, -0.016249, -0.048154, 0.07377, -0.018459, -0.040328, -0.009076, -0.040173, 0.099318, -0.051435, 0.111816, -0.089454, 0.09598, 0.033669, 0.053979, 0.073661, -0.027997, 0.031222, -0.06786, -0.01342, -0.028117, -0.024761, -0.073689, 0.033489, 0.01605, -0.007621, -0.082578, 0.109116, -0.001509, -0.036343, -0.0952, 0.085828, -0.015047, 0.080157, 0.022644, -0.06472, -0.047674, 0.017559, 0.051152, 0.033024, 0.033622, 0.064544, 0.059273, 0.019945, 0.051146, 0.103408, -0.053709, 0.041521, 0.080456, -0.016951, 0.019337, 0.117393, -0.0412, 0.086853, -0.00924, 0.051041, -0.005184, -0.062931, -0.040736, -0.134455, -0.004791, -0.094851, -0.003833, -0.081688, -0.011515, 0.03715, 0.01445, 0.100673, -0.081712, -0.025184, 0.039456, 0.049856, 0.010927, 0.027904, 0.020331, 0.119786, -0.019862, -0.003376, 0.006982, 0.016289, 0.075605, 0.003599, -0.051249, -0.054835, 0.063869, 0.013109, -0.044347, -0.0, -0.036695, -0.063979, -0.046442, -0.047263, 0.004152, -0.006187, 0.023283, 0.073998, 0.081823, 0.016833, 0.049661, 0.003787, -0.06803, 0.03604, -0.026832, 0.02872, -0.046539, 0.006037, -0.05861, -0.010851, 0.028248, 0.049821, 0.018725, 0.033924, 0.009563, 0.031509, -0.037223, 0.036996, -0.054052, 0.036899, -0.087495, 0.060992, 0.067125, -0.004534, -0.024638, 0.084441, 0.05722, 0.053871, 0.004661, 0.00211, -0.014389, -0.095461, -0.033775, -0.005752, -0.038627, -0.006197, -0.018022, 0.086152, 0.059999, -0.108308, -0.013591, 0.035795, 0.022177, 0.01406, -0.060295, -0.043534, -0.065234, -0.014292, 0.017145, -0.047879, 0.068675, -0.063154, 0.020946, -0.028792]
A12: 11 | B12: 01468167-f750-4b79-b8c8-2edf85711375 | C12: CBA.AX | D12: LGT reports 17% rise in H1 profit as assets reach record level | E12: Net new assets came in at SFr12.3bn, equal to an annualised growth rate of 6.4%. | F12: LGT reports 17% rise in H1 profit as assets reach record level - Net new assets came in at SFr12.3bn, equal to an annualised growth rate of 6.4%. | G12: [0.01093, -0.051179, -0.015799, -0.031489, 0.091158, 0.017852, 0.009322, 0.087909, -0.035465, 0.000765, -0.011281, 0.036838, -0.097592, -0.021925, -0.013414, -0.024584, -0.026689, -0.076768, -0.001885, -0.00785, 0.003269, -0.028321, 0.056583, 0.016524, 0.137591, -0.118243, -0.030675, 0.096621, 0.081288, -0.018459, 0.032146, 0.047112, 0.031309, 0.039278, -0.009714, -0.006366, -0.009213, -0.084851, -0.084731, 0.059338, 0.040624, -0.012017, -0.062889, -0.045136, -0.03014, -0.044725, 0.001439, 0.033209, -0.055971, 0.061083, 0.055382, 0.016334, 0.011309, 0.018979, -0.020544, 0.015492, -0.074366, 0.043752, 0.058077, -0.012358, -0.033705, 0.000774, 0.069809, -0.107261, 0.047985, 0.003339, 0.003276, 0.024088, -0.055094, 0.003533, -0.012534, -0.041172, -0.09022, -0.067209, -0.027278, -0.052006, 0.034279, 0.049512, 0.045073, -0.078147, 0.058631, 0.022322, -0.083687, 0.010323, -0.109963, -0.038028, 0.04522, 0.050615, -0.007178, 0.000866, -0.006854, -0.012274, -0.027339, 0.039708, -0.048585, 0.043608, -0.043449, -0.050751, 0.082773, -0.003274, -0.005408, 0.080598, 0.016566, -0.009316, -0.096607, 0.014492, 0.008341, 0.131069, 0.030807, -0.050566, 0.030159, 0.075742, -0.015988, -0.031034, -0.013627, 0.025563, -0.03829, -0.005909, 0.009786, -0.028768, 0.079193, 0.040047, 0.007323, -0.019793, -0.059899, -0.051207, -0.109925, 0.0, 0.003724, 0.029345, -0.01312, -0.018005, -0.0756, -0.025689, -0.038353, 0.07066, -0.002222, 0.010494, -0.041844, 0.03315, -0.052329, -0.073562, -0.001433, -0.072163, -0.018428, 0.016941, 0.045121, -0.033964, -0.059871, -0.014665, 0.026709, 0.009239, -0.001359, 0.022162, -0.032437, -0.03245, -0.008095, 0.00016, 0.019892, -0.033805, -0.013425, -0.013521, -0.049607, 0.007249, 0.014921, 0.016458, 0.086713, -0.034794, -0.02023, 0.084143, -0.005107, -0.044115, -0.036349, 0.050268, 0.013013, -0.01975, -0.028363, 0.069458, -0.041569, -0.017129, -0.035879, -0.075792, 0.036018, 0.033856, -0.094365, 0.024751, 0.02985, 0.057086, 0.059087, 0.06749, 0.013934, 0.084147, -0.017702, 0.03726, 0.107856, -0.012158, -0.014063, 0.037324, -0.012507, -0.030384, 0.059378, -0.032116, 0.081598, 0.004796, -0.018836, -0.026458, 0.062907, 0.072657, -0.03995, -0.000324, 0.031926, -0.078817, -0.021319, -0.016467, 0.038823, -0.10014, -0.02092, 0.058489, 0.042283, -0.101942, 0.0769, -0.009943, -0.029898, -0.0, 0.017567, 0.06061, -0.004508, -0.057021, -0.053101, 0.030816, 0.056935, -0.017859, -0.060728, 0.087112, 0.11626, 0.0196, -0.111461, -0.024275, 0.017972, -0.085971, 0.105871, -0.001252, -0.042078, -0.004655, 0.056042, 0.018023, -0.02223, 0.131168, -0.010101, 0.028138, 0.010039, 0.068797, 0.017927, -0.027062, -0.022633, -0.006456, 0.047252, -0.011788, -0.005019, -0.059683, 0.060709, -0.036097, 0.03689, -0.039172, 0.058687, -0.042756, -0.002521, -0.022641, -0.029625, -0.027377, 0.03027, -0.005868, 0.117769, 0.046866, 0.010698, 0.009792, -0.010845, -0.042076, -0.045597, 0.071393, 0.042074, 0.029571, -0.129888, 0.050403, 0.067092, 0.088031, -0.041005, 0.118602, -0.050873, -0.050842, 0.010631, -0.104301, 0.073517, -0.030514, 0.054029, 0.067056, 0.086739, -0.065546, -0.065102, -0.000695, 0.014776, -0.068152, 0.01676, -0.118349, -0.050525, 0.042951, -0.006802, -0.025591, -0.014859, -0.060761, -0.017636, 0.012875, 0.01928, 0.037892, -0.085679, -0.057141, -0.065994, 0.026346, -0.015437, -0.0, -0.049617, -0.02173, 0.009784, 0.032875, 0.019915, 0.068927, -0.015782, 0.077161, 0.012358, 0.081126, -0.020583, -0.001273, -0.031901, -0.062752, -0.033466, -0.052171, -0.007068, 0.060932, -0.034611, -0.047984, 0.085716, 0.070241, 0.082783, -0.007065, -0.031836, -0.089914, -0.03183, 0.054586, 0.047737, -0.06867, 0.082745, 0.048529, 0.048135, 0.030404, 0.0804, -0.011493, 0.02478, 0.088748, -0.006354, 0.005977, 0.018809, 0.020478, -0.011532, -0.010049, -0.072172, -0.023348, -0.110613, -0.026401, 0.020543, -0.152194, 0.112778, 0.019734, -0.028122, -0.011621, 0.036551, 0.036448, -0.018719, 0.012663, -0.048859, -0.036995, 0.011178, -0.096649, -0.009861, 0.056938]
A13: 12 | B13: 5471b7ec-a7a3-4b6f-9ed9-1077daa933df | C13: CBA.AX | D13: Fast Money Bets on November RBA Hike in Fight Against Inflation | E13: Speculative investors are increasingly betting the Reserve Bank of Australia will raise interest rates again in November as inflation remains above the central bank’s target. | F13: Fast Money Bets on November RBA Hike in Fight Against Inflation - Speculative investors are increasingly betting the Reserve Bank of Australia will raise interest rates again in November as inflation remains above the central bank’s target. | G13: [-0.071025, -0.079204, -0.120371, 0.079145, -0.018242, 0.006971, -0.036173, 0.008664, 0.002778, 0.006519, -0.047016, 0.053294, -0.037991, 0.00609, 0.050269, 0.016932, 0.016307, -0.014505, -0.007567, 0.019713, -0.046585, -0.07531, -0.058002, 0.02604, 0.097024, -0.0357, 0.06472, -0.001252, -0.055762, -0.028225, 0.019501, 0.023328, 0.043446, -0.063793, 0.033321, -0.018996, -0.028198, -0.010309, -0.005334, 0.054666, 0.061665, -0.014863, -0.00453, 0.001674, -0.000343, -0.007796, 0.044016, 0.084705, -0.020393, 0.043307, 0.013772, -0.024261, -0.030923, -0.052592, -0.018958, 0.011816, -0.001785, 0.004654, 0.117353, -0.042586, 0.044202, -0.011933, 0.004191, -0.025825, 0.001773, -0.059696, -0.048843, 0.042665, 0.030482, 0.007738, 0.041983, 0.000579, -0.02913, -0.14002, 0.00409, -0.0251, 0.018707, -0.006651, 0.035711, -0.042389, 0.022167, -0.075997, 0.030536, -0.104988, -0.008978, 0.050232, 0.123078, -0.046696, 0.014683, -0.039494, 0.086211, 0.001221, 0.030895, -0.026795, 0.002128, -0.02556, -0.007441, -0.11916, -0.000948, 0.040309, 0.074722, 0.004096, -0.039311, 0.073913, 0.050252, -0.018647, -0.043078, 0.027828, 0.013302, 3.9e-05, -0.013339, 0.111014, 0.092219, 0.022506, -0.111602, 0.029962, -0.058504, -0.021054, 0.012036, 0.08821, 0.047855, 0.056156, 0.008042, -0.036787, 0.048462, 0.024335, -0.065045, 0.0, 0.037707, 0.037601, -0.005677, -0.097219, -0.028464, 0.033879, -0.060809, -0.005597, -0.022704, 0.000252, 0.001801, 0.058133, 0.02348, 0.030998, -0.05364, -0.065233, 0.005043, 0.036185, 0.080557, 0.041871, 0.020515, -0.063018, 0.013376, -0.069951, -0.012594, -0.01723, 0.072114, -0.057171, 0.059542, 0.014296, -0.01786, 0.063097, -0.053664, -0.075956, -0.06189, 0.000187, 0.012077, -0.055354, -0.06903, -0.011956, 0.014101, 0.04423, -0.001922, 0.024728, -0.028606, 0.050912, -0.009126, -0.029239, -0.042063, 0.046193, -0.023575, -0.043514, -0.043908, 0.033149, 0.035597, -0.086668, -0.035035, -0.030596, 0.043314, -0.045831, 0.046746, -0.026681, -0.095748, -0.022451, -0.138791, 0.032718, -0.002582, -0.00517, -0.08844, 0.041995, 0.003054, 0.037312, 0.036501, -0.011614, -0.065845, -0.076264, 0.067584, 0.028736, 0.052106, -0.040087, 0.027272, 0.002572, 0.060307, -0.034053, 0.03262, -0.007009, -0.040427, -0.101456, 0.011014, -0.135657, -0.081435, -0.053062, 0.04781, -0.020622, 0.044462, -0.0, 0.025039, -0.058286, 0.050295, 0.132023, 0.042469, -0.074595, 0.022079, -0.015519, 0.090561, -0.011386, -0.092763, 0.070289, 0.035365, 0.087517, 0.112134, -0.092508, 0.039307, -0.01543, 0.046863, -0.04414, -0.031991, -0.026659, -0.02685, 0.085065, -0.000736, -0.066666, -0.007203, 0.00026, -0.064847, -0.008996, -0.046858, 0.032634, -0.022873, -0.041706, -0.093934, 0.054455, 0.028615, 0.024492, -0.02473, 0.027315, 0.055783, 0.000625, -0.014568, -0.039795, 0.002662, 0.006249, 0.055171, 0.118873, 0.041417, 0.095981, 0.009227, -0.077542, -0.006207, 0.072391, -0.006337, -0.018861, 0.004101, -0.001116, -0.008185, 0.068968, 0.025274, 0.056422, 0.04618, 0.032426, 0.024686, 0.000251, 0.000932, -0.048501, 0.102436, 0.038788, 0.050999, 0.037518, -0.042972, 0.092703, 0.033878, 0.034878, -0.018513, 0.006352, 0.062129, 0.030197, -0.01416, 0.003975, 0.011128, -0.005639, 0.006286, 0.051692, 0.021931, -0.042548, -0.000468, -0.036036, -0.055424, -0.073936, 0.146121, 0.037606, -0.07086, -0.0, -0.025233, -0.04898, -0.006152, 0.030836, 0.047348, 0.028804, 0.013325, -0.00299, 0.032388, -0.011438, 0.058125, 0.025495, -0.019323, -0.073913, 0.015084, 0.081033, -0.009137, -0.001107, -0.031372, 0.005443, 0.083685, 0.135217, 0.046903, -0.038795, -0.001636, -0.039462, 0.010736, 0.124971, -0.015822, 0.003362, -0.036969, 0.03039, 0.053682, -0.013788, 0.000354, -0.00352, 0.084115, 0.143978, 0.025746, -0.005276, 0.036275, -0.081654, -0.038761, -0.103284, -0.072362, -0.045735, -0.036644, -0.064014, 0.024976, -0.068386, -0.02152, 0.003597, -0.00215, 0.08617, 0.057648, -0.023861, -0.068769, -0.033452, 0.017424, 0.009379, -0.038838, -0.171085, -0.021411, 0.007146]
... A22: 21 | B22: 69dbc761-0547-45ff-9908-81fbc4ec506d | C22: CBA.AX | D22: Billionaire Sam Altman Says OpenAI Was ‘Pretty Wrong’ About AI Jobs, But Goldman Sachs Warns AI is Still Wiping Out 11,000 Jobs Per Month | E22: null | F22: Billionaire Sam Altman Says OpenAI Was ‘Pretty Wrong’ About AI Jobs, But Goldman Sachs Warns AI is Still Wiping Out 11,000 Jobs Per Month | G22: [-0.000277, -0.08568, -0.000159, 0.029765, 0.029727, -0.092166, 0.002427, -0.025931, -0.01661, -0.016104, -0.0218, 0.129882, -0.000539, -0.015542, -0.019917, 0.075905, -0.022776, 0.003242, -0.018937, -0.070764, -0.024887, -0.032194, 0.005002, -0.088364, 0.039389, -0.01954, 0.034443, -0.044343, -0.043867, 0.033381, 0.026853, 0.03712, 0.054377, 0.004807, 0.02646, 0.05604, -0.047575, -0.023647, 0.010952, -0.059338, 0.065722, -0.070705, -0.035221, -0.086545, 0.048556, -0.001786, -0.01782, -0.065461, 0.023913, 0.011075, -0.063626, -0.053779, 0.021425, -0.019093, 0.02144, -0.021191, -0.016217, -0.103608, 0.012066, 0.025433, 0.080155, -0.027896, -0.005452, -0.01269, 0.077005, 0.03393, -0.01369, -0.070035, -0.071235, 0.02716, 0.089399, -0.015762, -0.064811, -0.019087, -0.037277, -0.002772, 0.082383, -0.000994, 0.081829, -0.016483, -0.006239, -0.023967, -0.061717, -0.00999, -0.015136, 0.046779, -0.009559, -0.037316, 0.054688, 0.027736, 0.033447, -0.085951, 0.078217, 0.00353, 0.059332, -0.02913, -0.039067, 0.043468, -0.082134, 0.014887, -0.019159, -0.000373, 0.009161, -0.003551, -0.072326, 0.045013, 0.082398, 0.072696, -0.019972, 0.049832, 0.00961, -0.027216, 0.128662, 0.027367, 0.028122, 0.022528, -0.0368, 0.094997, -0.034543, 0.138274, 0.035212, 0.096746, -0.02335, 0.052472, -0.024599, 0.053483, -0.015564, 0.0, 0.07248, 0.018826, 0.08751, -0.003855, 0.064778, 0.037094, -0.012419, 0.005353, 0.064187, 0.016772, -0.077426, 0.069095, -0.050078, 0.021069, 0.011105, 0.019453, 0.020761, 0.026589, 0.053626, -0.053692, 0.054496, -0.043178, -0.040445, -0.037385, -0.00976, -0.020805, 0.017834, -0.047038, 0.105424, 0.036204, -0.057522, 0.108622, -0.024854, 0.004058, -0.006966, 0.037447, -0.033694, 0.005554, -0.004987, -0.024496, -0.065622, 0.109776, 0.052692, -0.016678, -0.023393, 0.007193, 0.023586, -0.006473, 0.046651, 0.046939, -0.051903, 0.039466, 0.024637, -0.046879, 0.033856, -0.060969, 0.054905, 0.028464, 0.019585, 0.051179, -0.011468, 0.010056, -0.048591, 0.081436, -0.060014, 0.125913, 0.021553, 0.098432, -0.060214, 0.071628, 0.012231, 0.043649, -0.048173, 0.011702, -0.119233, -0.051571, 0.045296, -0.053214, 0.022414, -0.024646, 0.030846, 0.046843, 0.043647, -0.027442, 0.003353, 0.046955, -0.03367, 0.003982, 0.071345, 0.097591, -0.05727, -0.017917, -0.035002, 0.07576, -0.125576, -0.0, -0.167175, -0.044263, -0.002518, 0.002293, -0.050591, -0.002243, 0.016229, 0.053764, -0.002957, 0.054097, 0.005092, -0.004904, 0.046955, 0.026817, -0.029563, -0.075719, 0.005754, -0.040397, -0.080381, 0.010294, 0.01279, 0.065937, -0.034448, 0.006714, 0.068724, 0.069918, -0.062961, 0.019126, -0.047348, -0.009696, 0.023166, -0.009791, -0.094286, 0.053642, 0.053673, 0.029991, 0.004451, -0.023761, 0.014027, 0.038928, 0.02689, -0.084797, -0.073032, -0.037705, -0.003399, -0.035655, -0.041466, -0.015177, -0.037623, -0.132362, -0.039595, -0.003384, -0.058388, 0.003181, -0.080578, -0.012457, 0.016746, -0.042738, -0.048882, -0.009657, -0.014888, 0.019539, 0.050314, 0.021515, -0.097579, -0.049219, 0.076982, 0.031939, -0.00279, -0.149317, -0.024718, -0.087518, -0.018866, 0.02607, -0.049219, 0.080996, -0.062546, -0.028286, -0.000351, -0.004093, 0.062194, -0.107682, 0.058697, 0.052262, 0.000773, 0.046409, 0.071999, -0.022879, -0.017738, 0.067161, -0.075241, -0.059274, -0.058055, 0.060083, -0.023906, -0.0, 0.021194, -0.044726, 0.110956, -0.021955, -0.07074, -0.060188, -0.016902, 0.068276, 0.01903, 0.028851, 0.035154, -0.018928, -0.110218, -0.01216, -0.013825, 0.089442, 0.024488, -0.007211, 0.012035, -0.028113, 0.062239, 0.047695, 0.06194, -0.030064, -0.011306, -0.095577, -0.075105, 0.069935, -0.043767, 0.018364, -0.023513, -0.034836, 0.040667, -0.020399, 0.018301, 0.021924, 0.091503, -0.014759, -0.013458, 0.007936, -0.011578, 0.015576, -0.040229, -0.025302, 0.031595, -0.014476, -0.101428, -0.018774, 0.008066, -0.030508, 0.012574, -0.002903, 0.034544, 0.081428, 0.082169, -0.063884, -0.038381, -0.041538, -0.112467, 0.026177, 0.073947, -0.073821, -0.025583, 0.003418]

Sheet Questions
A1: Question ID | B1: Question | C1: Embedding (all-MiniLM-L6-v2, normalized)
A2: Q1 | B2: How is CBA using AI to improve software engineering productivity? | C2: [-0.00142, 0.030997, -0.029219, -0.016555, -0.007393, -0.002945, -0.023806, 0.058989, 0.006764, -0.035817, -0.122948, -0.002114, 0.055334, -0.038145, 0.013813, 0.133706, 0.062989, -0.064052, -0.028822, -0.107158, -0.022115, 0.037941, -0.004136, 0.005567, -0.021541, 0.03503, 0.026912, -0.08838, 0.035691, -0.005563, -0.020355, 0.094073, 0.063316, -0.011868, -0.043541, 0.050735, -0.007571, 0.000774, 0.120352, -0.007324, -0.090783, 0.019846, -0.017634, -0.022061, 0.069221, -0.023232, -0.000986, -0.030342, 0.059194, -0.017813, -0.075953, 0.002761, 0.014751, -0.028328, 0.047192, 0.037357, 0.014987, 0.004344, 0.04181, 0.039312, -0.030131, -0.004157, 0.053396, 0.016459, 0.127241, -0.052867, -0.088593, -0.019722, -0.017626, -0.032343, 0.005044, 0.022812, -0.047283, -0.054357, 0.045785, -0.00519, -0.061123, 0.059586, 0.074887, -0.087575, -0.013282, -0.017371, 0.002845, 0.085466, 0.00195, 0.005425, 0.037484, -0.056105, 0.000937, 0.075196, 0.076633, 0.012573, 0.009327, -0.008338, 0.02373, 0.00012, 0.035157, -0.069022, -0.065848, 0.040883, 0.023442, 0.027363, -0.025622, -0.071334, -0.107796, 0.027408, 0.161278, 0.050551, 0.039449, -0.025414, -0.02259, 0.026124, -0.048699, -0.055013, -0.001, 0.032686, -0.008386, 0.080183, 0.027729, 0.025007, 0.015846, -0.008278, 0.006963, 0.031596, 0.030199, -0.000211, -0.096139, -0.0, 0.012318, 0.024356, -0.034513, 0.052218, 9.6e-05, -0.103324, -0.031412, 0.021669, 0.039288, -0.061122, -0.038284, 0.067779, -0.030061, -0.007995, 0.118215, -0.017568, -0.103456, 0.055599, -0.021597, 0.021158, 0.027889, -0.128111, 0.058324, -0.014197, 0.051734, 0.066672, 0.10846, -0.036689, 0.04277, 0.012931, 0.006168, 0.06511, -0.074874, 0.051714, -0.013296, 0.047675, -0.0016, 0.050403, 0.022322, 0.132234, -0.057139, 0.023433, 0.013144, -0.034045, 0.023307, -0.012426, -0.005128, -0.075109, -0.004194, 0.018299, 0.014512, -0.005306, 0.039443, -0.029964, 0.037808, -0.043574, 0.010181, 0.006156, 0.05429, 0.016914, -0.01488, 0.079052, -0.049297, 0.069292, -0.050285, 0.037268, -0.036594, 0.092702, 0.077075, -0.060513, 0.01498, 0.005731, 0.017805, -0.063054, -0.021776, -0.060999, -0.072574, -0.088595, 0.049556, 0.015893, -0.023114, 0.000877, 0.0485, -0.105563, 0.072995, -0.052452, 0.008288, 0.023432, -0.049638, 0.029865, -0.041065, 0.012779, 0.003232, 0.079458, 0.009684, 0.0, -0.051059, -0.012403, -0.024971, -0.005463, -0.010213, -0.042161, -0.001796, -0.036352, -0.006346, 0.011361, -0.072351, -0.030137, -0.066539, 0.074479, 0.027079, -0.043835, -0.001484, -0.054793, -0.051949, -0.045205, 0.005563, 0.00717, -0.027577, -0.051169, -0.0015, 0.036569, -0.132743, 0.05774, 0.038951, -0.023556, 0.033896, 0.003401, -0.107128, 0.053264, -0.005025, 0.032593, -0.014494, -0.049819, -0.006649, 0.011562, -0.010474, -0.040349, -0.075648, 0.005924, 0.021668, 0.054598, 0.016423, 0.027314, -0.016166, 0.022755, 0.129662, 0.002939, -0.023687, -0.072585, -0.068912, -0.020963, 0.024162, -0.047004, -0.022916, 0.016563, 0.01223, 0.025887, 0.075701, -0.014048, -0.023164, 0.023421, 0.029618, 0.070459, -0.05887, 0.008803, 0.06712, -0.030563, -0.048346, 0.073562, -0.013674, 0.039148, 0.014515, -0.071075, -0.065888, -0.03979, -0.069301, -0.018882, 0.034339, -0.047073, -0.061769, 0.076965, -0.000366, -0.0829, -0.038781, 0.089311, -0.107272, 0.005771, -0.005279, 0.017789, -0.078189, -0.0, -0.063876, -0.060537, 0.036939, -0.033579, 0.000561, -0.045996, -0.114442, 0.102932, 0.022578, -0.086168, 0.030919, -0.002229, -0.083814, 0.099449, 0.110899, 0.081818, 0.041354, 0.052693, -0.021995, -0.073386, 0.100403, -0.001687, -0.005133, -0.032635, 0.032586, -0.082838, -0.033469, 0.064423, -0.032569, 0.026532, 0.024262, 0.087276, 0.021461, 0.010232, 0.064323, -0.042979, 0.082824, 0.005169, -0.039146, -0.037847, -0.020344, 0.076441, -0.019726, -0.033745, 0.059826, -0.097541, -0.071628, -0.011975, 0.054988, -0.056437, 0.028788, -0.062613, -0.016374, 0.061925, 0.098283, 0.032496, 0.021325, -0.0415, -0.018268, -0.002637, -0.037709, 0.019967, 0.082768, -0.009469]
A3: Q2 | B3: What technology leadership changes has CBA made to support its AI strategy? | C3: [-0.032768, 0.012862, 0.004916, -0.060403, 0.020949, 0.040934, -0.058324, 0.014494, -0.035164, -0.003594, -0.062333, 0.039363, 0.054489, -0.007582, 0.009892, 0.0564, 0.04146, -0.076965, -0.025214, -0.087964, -0.093218, 0.015436, 0.04445, -0.031311, -0.055082, 0.031778, 0.026198, -0.115094, -0.04845, -0.085089, -0.028435, 0.054937, 0.031171, 0.008301, -0.065164, 0.009648, 0.025911, 0.002978, 0.115391, -0.002781, -0.035009, -0.032887, -0.041439, -0.039274, 0.093276, 0.018134, 0.018551, -0.066564, 0.00911, -0.021086, -0.04471, -0.052814, 0.020482, 0.025073, -0.001345, -0.007307, 0.000731, 0.077262, 0.124866, 0.06024, 0.010129, -0.011353, 0.041085, 0.044034, 0.083643, -0.001608, -0.088242, -0.014896, -0.039382, -0.054758, 0.043874, -0.007136, -0.039954, -0.050094, 0.049245, 0.009674, 0.015707, 0.08994, 0.098225, -0.071447, 0.012875, 0.011432, -0.022446, 0.067913, 0.000427, 0.008822, -0.08567, -0.082063, -0.004493, 0.013504, 0.061322, 0.009057, 0.019798, 0.026159, -0.037778, -0.001064, -0.033513, -0.073973, 0.005533, 0.015911, 0.053666, 0.066287, -0.007779, -0.024905, -0.072169, 0.013704, 0.138417, 0.012452, 0.052417, 0.02172, 0.012348, 0.023515, -0.050883, -0.104228, -0.040551, -0.064382, -0.063143, 0.10741, 0.03866, 0.001506, 0.023215, -0.026287, 0.014326, -0.011676, 0.0228, 0.055117, -0.105813, -0.0, -0.001869, 0.050181, -0.003623, 0.071804, 0.018866, -0.055717, 0.014651, -0.001605, 0.010021, -0.072179, -0.010897, 0.102495, -0.062178, -0.046914, 0.11313, -0.111572, -0.091237, 0.028416, 0.03628, -0.028317, 0.015639, 0.006461, 0.044255, -0.038076, 0.109439, 0.049235, 0.023841, -0.012767, 0.011423, 0.022283, -0.007728, 0.060431, -0.113385, 0.005452, -0.016715, 0.021965, -0.039003, -0.045821, 0.011571, 0.084462, -0.070897, 0.052653, -0.05456, -0.022148, 0.013969, -0.026015, -0.016976, -0.039982, -0.003425, 0.005775, -0.079768, 0.016929, 0.016816, -0.072292, 0.114585, -0.042906, 0.044971, 0.041543, 0.069683, -0.023034, 0.055551, 0.069287, -0.115741, 0.091618, -0.032268, 0.052128, -0.029036, -0.012802, 0.016503, -0.006432, 0.027812, 0.02115, -0.006953, 0.029481, -0.068738, -0.030807, -0.091209, -0.037879, 0.015126, -0.024706, -0.036504, -0.000306, 0.100503, -0.030558, 0.048359, -0.04903, 0.011479, -0.000437, -0.012624, 0.009686, -0.059744, -0.004802, 0.004772, 0.126901, 0.008885, 0.0, -0.047146, -0.000518, 0.001095, -0.038956, 0.060397, -0.069312, 0.018503, -0.021643, 0.060023, -0.004533, 0.05915, -0.004795, -0.04875, 0.074902, -0.002405, -0.013602, 0.019955, -0.104301, -0.005429, -0.057809, 0.006238, 0.03494, -0.062968, 0.050722, -0.001338, 0.045791, -0.069007, 0.025766, 0.065371, -0.063554, 0.005082, -0.03604, -0.031425, 0.1606, -0.000321, 0.037261, 0.010969, -0.056971, -0.037782, 0.028841, 0.015613, -0.011588, -0.003381, 0.037083, 0.031175, 0.05068, -0.031836, 0.025088, -0.054879, 0.017836, 0.063282, -3.4e-05, -0.028685, -0.025593, -0.044388, 0.052178, 0.080998, -0.009811, -0.028119, 0.016156, 0.071616, 0.021696, 0.07105, -0.035193, -0.071687, 0.087823, 0.055684, 0.076013, -0.026184, 0.00335, 0.089508, -0.079882, -0.041752, 0.037929, -0.048551, 0.004775, -0.058717, -0.041921, -0.06962, -0.008004, -0.05061, 0.006009, 0.016715, -0.011886, 0.016694, 0.139651, 0.003135, -0.085372, -0.053879, 0.053779, -0.063234, -0.086789, 0.002049, 0.087987, -0.079557, -0.0, -0.068881, -0.033138, 0.026545, -0.002111, 0.078692, -0.024669, -0.076216, -0.000112, 0.064732, -0.069465, -0.015597, 0.010229, -0.008246, 0.068588, 0.113435, 0.034342, -0.025737, -0.004451, 0.008885, -0.047544, 0.045865, 0.038294, -0.006655, -0.069611, 0.026788, -0.024519, -0.11753, 0.054561, -0.003881, 0.07552, -0.037164, 0.069437, 0.01318, -0.056087, 0.014933, -0.035378, 0.045177, -0.027506, 0.009783, -0.026645, 0.005216, 0.076711, -0.035201, 0.000978, 0.029694, -0.026984, -0.069858, -0.010821, 0.045534, -0.098791, 0.025685, -0.001626, 0.003027, 0.068637, 0.115414, 0.040222, 0.01904, -0.042758, -0.02719, -0.001295, 0.014024, -0.065707, 0.053463, 0.042948]
A4: Q3 | B4: How is CBA modernising its payment services? | C4: [-0.028458, 0.049505, -0.0517, -0.045503, -0.093112, 0.026766, -0.034272, -0.001016, -0.000674, -0.057106, -0.062035, 0.017244, 0.026087, -0.006552, 0.003697, -0.009174, 0.09344, -0.077728, 0.000825, 0.008683, -0.117572, 0.026279, -0.053473, 0.031322, 0.0154, -0.009648, 0.030198, -0.042319, 0.024202, -0.034861, -0.007758, 0.117217, 0.038826, -0.001824, -0.070657, 0.05224, 0.058522, -0.022612, 0.017456, 0.008731, -0.003663, -0.022995, -0.055134, -0.025048, 0.056588, -0.005526, 0.061958, 0.028192, -0.020482, 0.008583, 0.005765, -0.055131, 0.031551, 0.080508, -0.044861, -0.019729, 0.031495, 0.030006, 0.04966, 0.012092, -0.033827, 0.046137, -0.007394, 0.079645, 0.128457, -0.019426, -0.050948, -0.011773, -0.023621, -0.109675, -0.034758, -0.097741, -0.006853, -0.011731, -0.002384, 0.008098, -0.012519, 0.109655, -0.006198, -0.054491, 0.044902, 0.000744, 0.051598, 0.050264, -0.010547, 0.015507, -0.060412, -0.084628, -0.014493, -0.006295, 0.104017, 0.101221, 0.022164, -0.073029, -0.021176, -0.041585, 0.003888, -0.062914, 0.046093, -0.000131, 0.095826, 0.077377, 0.043456, -0.022774, -0.031394, -0.010272, 0.050681, 0.099951, 0.058548, 0.032279, -0.036287, 0.010819, -0.022893, -0.055054, -0.074501, -0.003224, -0.051184, 0.023063, 0.06805, 0.019601, 0.039659, 0.107553, -0.087251, -0.118976, -0.028056, 0.035456, -0.028519, -0.0, 0.012798, 0.019853, -0.016111, -0.012858, -0.048957, -0.031649, -0.02665, 0.056273, 0.021883, -0.020329, 0.069291, 0.08638, 0.03164, -0.006961, 0.033119, -0.002013, -0.160199, 0.008783, 0.110944, 0.099076, 0.000276, -0.025379, 0.067811, -0.00667, 0.076399, 0.022205, 0.043441, 0.016007, 0.058674, -0.02002, 0.074491, 0.018808, -0.023504, 0.025526, -0.045123, 0.059005, 0.060509, -0.01111, -0.011968, -0.038966, -0.053268, 0.013869, -0.032655, 0.021236, -0.001242, 0.086334, -0.031582, -0.018737, -0.009262, 0.054493, 0.019944, -0.02207, -0.095256, 0.033764, -0.012411, -0.061817, 0.047151, -0.055558, 0.00404, -0.124198, 0.014136, -0.098279, -0.073831, 0.031592, -0.075068, -0.014, -0.08391, -0.009969, -0.002518, -0.062116, -0.029031, 0.039069, 0.077679, 0.013823, -0.032195, -0.058725, -0.050417, 0.035011, 0.059881, 0.051204, -0.00847, 0.009887, 0.06264, 0.030524, 0.082422, 0.022858, 0.068849, -0.045515, -0.04876, -0.061375, -0.0396, -0.003325, 0.025664, 0.087071, 0.129653, 0.0, -0.010331, 0.020611, -0.031187, 0.062987, -0.029793, -0.079363, -0.034252, 0.006495, 0.0757, 0.014817, -0.057627, 0.014188, -0.017118, 0.056435, 0.013622, -0.046724, 0.011629, -0.043736, -0.010639, -0.060276, 0.011104, 0.022895, 0.016189, -0.008975, -0.001038, 0.018845, -0.079853, -0.052623, 0.036746, -0.001207, -0.026849, -0.008148, -0.050755, 0.055199, -0.077856, 0.01482, -0.067759, 0.044747, 0.035446, -0.025384, 0.008226, -0.035073, -0.092665, 0.002278, 0.056145, -0.024543, 0.015391, -0.018735, 0.00796, -0.004905, 0.062289, 0.002105, 0.004022, 0.009575, -0.049614, 0.07871, 0.106305, -0.024935, -0.03436, -0.017319, 0.064589, 0.104773, 0.060661, 0.040525, 0.00554, 0.026956, 0.062599, -0.026954, -0.000912, 0.013374, 0.063095, -0.04787, -0.0279, 0.031284, 0.024456, 0.017899, 0.041018, -0.065815, -0.07682, 0.00308, -0.050794, -0.009761, 0.088555, 0.017758, 0.004332, -0.006152, 0.018215, -0.138117, -0.0129, 0.061119, -0.11337, -0.032089, -0.000147, 0.024454, 0.000473, -0.0, -0.079072, -0.052374, -0.074301, 0.013929, 0.011188, -0.084894, -0.063347, 0.08801, -0.010746, -0.042484, 0.043246, 0.031432, -0.055611, 0.018002, 0.071804, 0.084551, -0.001868, -0.070155, -0.08351, 0.025757, -0.027065, 0.010331, 0.009028, -0.040207, -0.007238, -0.022083, 0.005793, 0.106017, 0.058989, -0.017591, -0.03287, 0.09375, 0.050669, -0.052016, -0.042781, -0.057768, 0.0551, 0.035838, -0.032168, -0.039337, -0.041813, -0.038195, -0.076802, -0.012459, 0.04088, -0.062323, -0.105163, 0.074962, 0.049473, -0.084272, 0.009617, -0.008291, 0.08077, 0.055323, 0.053391, -0.075362, 0.026666, 0.00486, 0.037238, -0.009194, -0.069627, -0.04894, 0.103498, -0.024624]
A5: Q4 | B5: What are the risks associated with AI-powered shopping and payment agents? | C5: [-0.028698, 0.01707, -0.037848, -0.004819, 0.000439, 0.036705, 0.058973, 0.016095, -0.015614, -0.008393, 0.045763, 0.025807, 0.070898, -0.023574, 0.038817, -0.007939, 0.075284, -0.069647, -0.031637, 0.045496, 0.004007, -0.032727, -0.024803, -0.006378, -0.061798, -0.00854, 0.032802, -0.062292, -0.038843, -0.010654, 0.018077, -0.019682, 0.092634, 0.009691, 0.019457, -0.023512, 0.012484, -0.05908, 0.031317, -0.054301, 0.026441, -0.101744, -0.04774, -0.039098, 0.056898, -0.016543, 0.009666, 0.000532, -0.046122, 0.037102, -0.090541, -0.059179, 0.052287, 0.027816, -0.115571, -0.064975, 0.052025, -0.042867, 0.017938, -0.007858, 0.053793, -0.05382, 0.036479, 0.026358, 0.070151, 0.054931, -0.048085, -0.037571, -0.037425, -0.016196, 0.064649, -0.122145, -0.016891, 0.017483, 0.043341, -0.011726, 0.008586, -0.069052, 0.072012, -0.064799, -0.016976, -0.015449, -0.008684, 0.06486, -0.057485, 0.043226, 0.009704, -0.039589, 0.042548, -0.053609, 0.017532, -0.024809, 0.052915, -0.060682, 0.117288, 0.017889, -0.064467, -0.071, -0.027805, -0.030978, 0.02307, 0.056213, 0.008764, 0.01973, -0.047672, 0.016468, 0.038787, -0.0249, 0.044705, 0.005951, -0.071103, -0.021449, 0.101824, -0.050794, 0.064605, 0.060795, -0.052367, 0.096989, 0.051228, 0.026548, -0.03979, 0.022388, 0.027115, 0.026959, 0.017448, 0.037962, -0.087865, -0.0, -0.067437, 0.012377, -0.020107, -0.043827, 0.067124, -0.040866, 0.030662, 0.046601, -0.015174, 0.082947, 0.032812, 0.034255, -0.010652, 0.070809, 0.035303, 0.025372, -0.016446, 0.031221, 0.039756, 0.002837, 0.046838, -0.092118, 0.054283, 0.031215, 0.029711, 0.010071, -0.037602, 0.029614, 0.154085, -0.016328, -0.039415, 0.024929, 0.011392, 0.05112, -0.093423, 0.086154, -0.105341, 0.024917, -0.038905, 0.039044, -0.081312, 0.074156, 0.063196, 0.026678, 0.004704, 0.009607, 0.05437, -0.088144, -0.056514, 0.025772, -0.117793, 0.075805, 0.010556, -0.019023, 0.008212, -0.044361, 0.040227, -0.059509, -0.001653, -0.090153, -0.036306, -0.048824, -0.015962, 0.027545, -0.040331, 0.025839, 0.050847, -0.024889, -0.008523, 0.046939, -0.011973, 0.017037, 0.043519, -0.041327, -0.065573, 0.008205, -0.079357, -0.013087, 0.025087, -0.068075, -0.065674, -0.047486, 0.091596, 0.102462, -0.01025, 0.029262, -0.026943, -0.053766, -0.027259, 0.00113, 0.021447, 0.029643, -0.041945, 0.044162, 0.029435, 0.0, -0.090738, -0.031746, -0.106487, 0.045201, -0.044411, -0.015562, -0.084558, -0.018793, 0.112859, -0.019651, -0.052228, 0.045467, 0.003574, -0.023318, 0.055056, -0.041483, 0.063938, -0.021812, 0.055304, -0.079929, 0.088916, 0.058379, -0.034344, -0.019626, -0.004559, 0.036695, -0.05395, -0.037245, 0.012189, 0.012723, 0.028496, 0.025449, -0.024298, 0.107873, 0.000449, 0.05534, -0.045504, 0.040504, 0.014932, -0.015441, 0.064537, 0.002004, -0.039956, 0.000986, 0.00399, -0.072574, -0.026742, 0.023373, 0.079193, -0.018982, -0.062327, 0.02772, -0.000611, -0.041469, -0.131508, 0.056712, 0.117946, 0.010221, -0.009493, 0.027863, -0.061955, 0.050226, 0.030173, 0.006403, -0.061699, -0.01273, 0.022116, 0.033426, 0.132614, -0.052405, 0.092675, -0.032831, 0.020534, 0.051247, -0.059224, 0.024643, 0.004437, 0.039111, -0.020701, -0.09419, -0.036513, -0.039667, 0.088411, -0.005015, -0.017557, 0.026371, -0.033026, -0.067309, -0.037847, -0.027797, -0.071009, 0.023783, -0.050988, 0.032192, -0.103723, -0.0, 0.029003, -0.027503, 0.085961, 0.043531, 0.084483, -0.058014, -0.02026, 0.049841, -0.060736, 0.038155, 0.043629, -0.027049, 0.001707, 0.034815, 0.031695, 0.066801, 0.015186, 0.01578, -0.057922, -0.03321, 0.012573, 0.005563, -0.026299, -0.045436, -0.037637, -0.023652, 0.046202, 0.05037, -0.06314, 0.114426, -0.057661, 0.038774, 0.036728, 0.026991, 0.008087, -0.011456, 0.009466, -0.048498, -0.09456, -0.017218, 0.000893, 0.014339, -0.035606, -0.035668, 0.07574, -0.058243, -0.095051, -0.078197, 0.140879, 0.022445, -0.058618, 0.015222, 0.058364, 0.065868, 0.106219, -0.051784, 0.045989, -0.048488, 0.047454, 0.06675, 0.006642, -0.078101, 0.042701, -0.078641]
A6: Q4 | B6: What are the risks associated with AI-powered shopping and payment agents? | C6: [-0.028698, 0.01707, -0.037848, -0.004819, 0.000439, 0.036705, 0.058973, 0.016095, -0.015614, -0.008393, 0.045763, 0.025807, 0.070898, -0.023574, 0.038817, -0.007939, 0.075284, -0.069647, -0.031637, 0.045496, 0.004007, -0.032727, -0.024803, -0.006378, -0.061798, -0.00854, 0.032802, -0.062292, -0.038843, -0.010654, 0.018077, -0.019682, 0.092634, 0.009691, 0.019457, -0.023512, 0.012484, -0.05908, 0.031317, -0.054301, 0.026441, -0.101744, -0.04774, -0.039098, 0.056898, -0.016543, 0.009666, 0.000532, -0.046122, 0.037102, -0.090541, -0.059179, 0.052287, 0.027816, -0.115571, -0.064975, 0.052025, -0.042867, 0.017938, -0.007858, 0.053793, -0.05382, 0.036479, 0.026358, 0.070151, 0.054931, -0.048085, -0.037571, -0.037425, -0.016196, 0.064649, -0.122145, -0.016891, 0.017483, 0.043341, -0.011726, 0.008586, -0.069052, 0.072012, -0.064799, -0.016976, -0.015449, -0.008684, 0.06486, -0.057485, 0.043226, 0.009704, -0.039589, 0.042548, -0.053609, 0.017532, -0.024809, 0.052915, -0.060682, 0.117288, 0.017889, -0.064467, -0.071, -0.027805, -0.030978, 0.02307, 0.056213, 0.008764, 0.01973, -0.047672, 0.016468, 0.038787, -0.0249, 0.044705, 0.005951, -0.071103, -0.021449, 0.101824, -0.050794, 0.064605, 0.060795, -0.052367, 0.096989, 0.051228, 0.026548, -0.03979, 0.022388, 0.027115, 0.026959, 0.017448, 0.037962, -0.087865, -0.0, -0.067437, 0.012377, -0.020107, -0.043827, 0.067124, -0.040866, 0.030662, 0.046601, -0.015174, 0.082947, 0.032812, 0.034255, -0.010652, 0.070809, 0.035303, 0.025372, -0.016446, 0.031221, 0.039756, 0.002837, 0.046838, -0.092118, 0.054283, 0.031215, 0.029711, 0.010071, -0.037602, 0.029614, 0.154085, -0.016328, -0.039415, 0.024929, 0.011392, 0.05112, -0.093423, 0.086154, -0.105341, 0.024917, -0.038905, 0.039044, -0.081312, 0.074156, 0.063196, 0.026678, 0.004704, 0.009607, 0.05437, -0.088144, -0.056514, 0.025772, -0.117793, 0.075805, 0.010556, -0.019023, 0.008212, -0.044361, 0.040227, -0.059509, -0.001653, -0.090153, -0.036306, -0.048824, -0.015962, 0.027545, -0.040331, 0.025839, 0.050847, -0.024889, -0.008523, 0.046939, -0.011973, 0.017037, 0.043519, -0.041327, -0.065573, 0.008205, -0.079357, -0.013087, 0.025087, -0.068075, -0.065674, -0.047486, 0.091596, 0.102462, -0.01025, 0.029262, -0.026943, -0.053766, -0.027259, 0.00113, 0.021447, 0.029643, -0.041945, 0.044162, 0.029435, 0.0, -0.090738, -0.031746, -0.106487, 0.045201, -0.044411, -0.015562, -0.084558, -0.018793, 0.112859, -0.019651, -0.052228, 0.045467, 0.003574, -0.023318, 0.055056, -0.041483, 0.063938, -0.021812, 0.055304, -0.079929, 0.088916, 0.058379, -0.034344, -0.019626, -0.004559, 0.036695, -0.05395, -0.037245, 0.012189, 0.012723, 0.028496, 0.025449, -0.024298, 0.107873, 0.000449, 0.05534, -0.045504, 0.040504, 0.014932, -0.015441, 0.064537, 0.002004, -0.039956, 0.000986, 0.00399, -0.072574, -0.026742, 0.023373, 0.079193, -0.018982, -0.062327, 0.02772, -0.000611, -0.041469, -0.131508, 0.056712, 0.117946, 0.010221, -0.009493, 0.027863, -0.061955, 0.050226, 0.030173, 0.006403, -0.061699, -0.01273, 0.022116, 0.033426, 0.132614, -0.052405, 0.092675, -0.032831, 0.020534, 0.051247, -0.059224, 0.024643, 0.004437, 0.039111, -0.020701, -0.09419, -0.036513, -0.039667, 0.088411, -0.005015, -0.017557, 0.026371, -0.033026, -0.067309, -0.037847, -0.027797, -0.071009, 0.023783, -0.050988, 0.032192, -0.103723, -0.0, 0.029003, -0.027503, 0.085961, 0.043531, 0.084483, -0.058014, -0.02026, 0.049841, -0.060736, 0.038155, 0.043629, -0.027049, 0.001707, 0.034815, 0.031695, 0.066801, 0.015186, 0.01578, -0.057922, -0.03321, 0.012573, 0.005563, -0.026299, -0.045436, -0.037637, -0.023652, 0.046202, 0.05037, -0.06314, 0.114426, -0.057661, 0.038774, 0.036728, 0.026991, 0.008087, -0.011456, 0.009466, -0.048498, -0.09456, -0.017218, 0.000893, 0.014339, -0.035606, -0.035668, 0.07574, -0.058243, -0.095051, -0.078197, 0.140879, 0.022445, -0.058618, 0.015222, 0.058364, 0.065868, 0.106219, -0.051784, 0.045989, -0.048488, 0.047454, 0.06675, 0.006642, -0.078101, 0.042701, -0.078641]
A7: Q5 | B7: What challenges are Australian banks facing in mortgage lending? | C7: [0.019415, -0.046219, -0.065814, 0.007192, -0.019104, 0.056565, -0.07647, -0.018395, -0.071637, 0.009514, 0.022514, -0.042263, -0.048161, 0.009394, 0.020563, 0.004301, -0.055428, -0.024424, 0.007363, 0.065919, -0.004499, -0.021561, -0.069759, -0.017338, 0.023441, -0.017637, 0.039513, -0.028265, -0.034931, -0.047212, -0.004799, 0.023228, 0.007259, -0.032901, 0.049908, 0.016708, 0.029539, -0.036095, -0.043582, -0.091648, 0.045897, -0.064387, 0.0152, -0.040225, 0.002059, -0.05232, 0.086765, -0.004358, -0.05962, 0.044202, -0.076144, -0.03599, 0.024081, -0.028673, -0.00292, -0.058577, 0.001727, -0.005125, 0.006538, -0.036827, 0.059249, 0.027235, -0.059823, 0.047698, 0.067904, 0.048809, -0.063185, -0.011951, -0.00946, 0.041493, -0.048425, -0.156503, 0.011552, -0.052041, 0.071888, -0.006165, 0.055116, 0.00639, 0.02616, -0.020934, 0.055362, -0.134921, -0.057052, 0.007679, 0.024867, -0.035271, 0.031252, -0.009602, -0.00024, -0.017137, 0.070401, -0.015972, 0.07478, -0.006825, 0.03653, -0.036368, -0.051914, -0.065593, 0.004779, 0.004632, 0.043157, 0.063334, 0.022417, 0.088841, -0.016619, 0.013798, 0.019622, -0.002339, 8.5e-05, -0.014968, 0.022073, 0.063249, 0.066684, -0.035595, -0.003949, -0.060337, 0.032554, 0.000996, 0.047149, 0.035419, 0.016072, 0.063122, -0.007342, -0.024951, 0.011959, 0.081814, -0.160848, -0.0, 0.013161, 0.02994, -0.010081, -0.05435, 0.005434, 0.002668, -0.078988, 0.027604, -0.012091, 0.078847, 0.08142, -0.026971, 0.005987, -0.043116, 0.027027, -0.007708, -0.074216, 0.062439, -0.028757, 0.124164, 0.009057, 0.03514, 0.028679, 0.024783, 0.042345, -0.132034, 0.019711, -0.030482, 0.026572, -0.003149, -0.006648, -0.038462, -0.014568, 0.037787, -0.054776, 0.085105, -0.026017, -0.067968, -0.050798, 0.04271, -0.033482, -0.014437, 0.043104, 0.029379, 0.062489, 0.000871, -0.00336, -0.036487, -0.135383, 0.081055, -0.068053, -0.012667, -0.127821, 0.014378, 0.044377, 0.011215, -0.02588, -0.075852, -0.005844, -0.000308, -0.023298, -0.137622, -0.086026, -0.062175, -0.021668, 0.040687, 0.069507, 0.003379, -0.066646, 0.019359, -0.084654, -0.062596, 0.006781, 0.021804, -0.034228, -0.002497, -0.008194, 0.009824, 0.038497, 0.019222, 0.013321, 0.034679, 0.018519, 0.047087, -0.016065, 0.045288, 0.020534, -0.062159, 0.026777, -0.131233, -0.061201, -0.001473, 0.082989, -0.000805, 0.081977, 0.0, -0.06276, -0.048927, -0.099918, 0.074807, -0.064016, -0.049822, 0.060223, 0.016827, 0.06206, -0.082429, -0.062232, 0.052029, 0.010716, 0.005921, -0.046609, -0.052225, 0.047526, 0.003477, 0.117884, -0.06403, 0.073997, 0.103778, 0.051038, 0.039014, -0.0463, 0.043001, -0.08608, -0.054421, -0.051959, -0.041144, -0.014948, 0.070933, -0.021954, 0.028688, -0.09386, 0.079399, 8.4e-05, -0.015085, -0.034737, 0.114847, 0.047694, 0.036618, 0.028741, -0.027113, -0.008266, 0.022469, 0.039428, -0.009948, 0.011768, 0.051602, 0.006196, 0.000542, 0.026462, 0.056221, 0.002513, 0.021222, 0.135872, -0.046444, 0.05773, 0.114299, 0.015413, 0.093394, 0.030541, 0.025069, 0.027665, -0.048014, -0.048527, -0.035381, -0.002813, -0.026409, 0.034136, -0.053514, 0.004324, 0.078012, 0.015319, 0.090143, -0.053006, -0.042122, 0.009308, -0.001999, -0.035784, 0.043154, 0.043238, 0.086645, -0.029799, -0.004959, 0.086549, -0.024418, 0.111743, -0.069313, -0.085958, -0.015748, 0.042261, 0.045588, -0.007582, -0.0, -0.028023, -0.032913, -0.058384, -0.058366, 0.02847, -0.001064, 0.02484, 0.037353, 0.020766, 0.044568, 0.048932, 0.057725, -0.056695, 0.015148, -0.009543, 0.047301, 0.023371, 0.010347, -0.053135, 0.007119, -0.031653, 0.084646, -0.043227, 0.009429, -0.017669, 0.002866, 0.036233, 0.109818, 0.019454, 0.050768, -0.10906, 0.068992, 0.063896, -0.026505, -0.154339, 0.069714, 0.039662, 0.034267, -0.010191, -0.067998, -0.014274, -0.028374, -0.004231, -0.034473, -0.016294, -0.007144, -0.040167, 0.089841, 0.019262, -0.057891, -0.019627, 0.035165, 0.041046, 0.049745, 0.025485, -0.05206, -0.036172, -0.00516, 0.074479, -0.015013, 0.064766, -0.048903, 0.038844, -0.044212]
A8: Q6 | B8: What are the latest expectations for Australian interest rates? | C8: [0.041851, -0.064243, -0.065782, 0.017886, 0.01519, -0.006999, -0.079316, 0.041902, -0.007634, 0.08073, 0.019146, 0.032895, -0.082336, 0.072835, 0.013468, 0.039056, -0.06914, -0.087348, 0.004939, 0.057548, -0.03622, -0.009011, -0.006145, -0.073647, 0.110233, 0.031492, 0.024509, -0.049613, -0.041125, 0.011046, -0.049301, -0.000902, 0.054784, -0.071015, 0.048589, -0.005981, 0.015528, -0.030879, -0.014326, -0.025937, 0.024951, -0.019769, 0.022601, -0.025419, -0.034103, -0.036104, 0.038456, -0.007661, -0.059122, 0.109345, -0.020019, -0.001324, 0.005292, -0.079626, 0.02743, -0.017486, -0.054649, -0.006699, 0.035534, -0.058112, -0.005185, 0.032281, -0.052018, 0.001713, 0.025938, 0.002076, -0.038874, -0.001126, -0.008017, 0.003263, -0.096394, -0.095746, -0.041685, -0.11366, -0.0062, -0.064184, 0.089054, 0.048513, 0.016488, -0.042702, 0.026333, -0.074815, -0.025212, -0.12862, 0.026735, -0.019208, 0.07941, 0.02972, 0.008384, 0.000108, 0.044863, 0.010164, -0.028767, -0.000119, 0.01378, 0.031335, -0.082592, -0.057223, -0.038551, 0.018315, 0.107259, 0.055233, 0.002512, 0.09198, -0.013188, -0.006775, 0.011292, 0.018015, 0.064219, -0.02149, -0.050449, 0.049916, -0.054342, -0.048226, -0.064933, -0.007674, 0.005755, 0.02637, 0.064042, 0.061662, 0.094367, 0.029772, -0.013353, 0.009751, 0.058802, 0.045393, -0.08804, -0.0, 0.006415, 0.010515, 0.018438, -0.062109, -0.014298, -0.009789, -0.010444, 0.043405, 0.004296, -0.026941, 0.007697, 0.027425, -0.011978, -0.042385, -0.009887, -0.078373, -0.066538, 0.07197, 0.054919, 0.0884, -0.023044, 0.052233, 0.037514, 0.006085, 0.004845, -0.062407, 0.062177, -0.010833, 0.041238, -0.007311, 0.053847, 0.061678, -0.06433, -0.07299, -0.076778, 0.072162, 0.013523, 0.048131, -0.005591, -0.004981, 0.029879, 0.030814, 0.014853, 0.025405, 0.036982, -0.02958, 0.013289, -0.079193, -0.026614, 0.022251, -0.05738, -0.055948, -0.09009, 0.057993, 0.025594, 0.020821, -0.058983, -0.019891, -0.056438, -0.018085, 0.004592, -0.027905, -0.078114, -0.066058, -0.12647, 0.065086, 0.09422, -0.030053, -0.072248, 0.079478, -0.038012, -0.018968, -0.014048, 0.0084, -0.04842, 0.010903, 0.031903, -0.014804, 0.079257, 0.009367, -0.023245, 0.003799, 0.009421, -0.04536, -0.031547, 0.021899, 0.006482, -0.028913, 0.069169, -0.078309, -0.029339, -0.058344, 0.059904, 0.05393, 0.045981, 0.0, 0.01247, -0.005408, -0.019551, 0.150233, -0.089295, -0.051654, 0.092781, 0.051742, 0.060014, -0.027223, -0.05575, 0.125829, 0.067986, 0.05497, 0.024049, -0.021999, 0.08931, 0.00587, 0.112441, -0.0351, -0.014155, 0.048052, -0.002971, 0.051707, 0.000495, 0.045515, -0.031115, -0.08211, -0.104104, -0.101409, -0.08705, 0.017745, -0.004164, 0.029721, -0.08971, 0.014555, -0.001606, -0.007836, -0.048439, 0.096636, 0.078062, 0.050833, -0.010569, -0.018808, -0.021594, -0.015485, 0.035797, 0.136971, 0.013268, 0.044634, -0.015597, 0.009701, -0.062235, 0.026988, -0.057475, -0.006233, 0.054326, -0.026223, -0.053, 0.075138, 0.002412, 0.139028, -0.010411, 4e-06, 0.029539, -0.043796, -0.006202, -0.055693, 0.087018, -0.036118, 0.07928, -0.051239, -0.088647, 0.041218, 0.026324, 0.093801, 0.043655, -0.046647, 0.041659, 0.018877, -0.038645, 0.078824, -0.005891, 0.005019, -0.054526, -0.002456, 0.070257, -0.074369, 0.016044, -0.052179, -0.086966, -0.010564, 0.041815, 0.068569, -0.048659, -0.0, -0.02995, 0.014295, -0.084445, -0.00176, 0.004367, 0.011194, 0.002129, 0.028764, 0.013208, -0.008427, 0.127545, -0.00679, -0.037554, -0.034865, 0.033367, 0.008528, -0.02958, 0.052272, -0.035205, -0.048205, -0.030259, 0.116698, 0.031192, -0.072174, -0.02462, 0.035733, 0.003416, 0.097955, -0.061407, 0.057089, -0.107613, 0.03057, 0.053475, -0.060013, -0.074826, 0.035765, 0.059969, 0.021349, 0.05975, -0.021479, 0.06427, -0.069352, -0.061033, -0.035699, -0.032037, 0.007571, 0.01075, -0.016577, 0.027328, -0.059838, 0.007817, 0.013962, -0.029294, 0.022689, 0.04012, -0.00908, -0.064645, -0.004515, -0.036556, -0.016689, 0.024021, -0.076919, -0.058577, 0.02032]
A9: Q6 | B9: What are the latest expectations for Australian interest rates? | C9: [0.041851, -0.064243, -0.065782, 0.017886, 0.01519, -0.006999, -0.079316, 0.041902, -0.007634, 0.08073, 0.019146, 0.032895, -0.082336, 0.072835, 0.013468, 0.039056, -0.06914, -0.087348, 0.004939, 0.057548, -0.03622, -0.009011, -0.006145, -0.073647, 0.110233, 0.031492, 0.024509, -0.049613, -0.041125, 0.011046, -0.049301, -0.000902, 0.054784, -0.071015, 0.048589, -0.005981, 0.015528, -0.030879, -0.014326, -0.025937, 0.024951, -0.019769, 0.022601, -0.025419, -0.034103, -0.036104, 0.038456, -0.007661, -0.059122, 0.109345, -0.020019, -0.001324, 0.005292, -0.079626, 0.02743, -0.017486, -0.054649, -0.006699, 0.035534, -0.058112, -0.005185, 0.032281, -0.052018, 0.001713, 0.025938, 0.002076, -0.038874, -0.001126, -0.008017, 0.003263, -0.096394, -0.095746, -0.041685, -0.11366, -0.0062, -0.064184, 0.089054, 0.048513, 0.016488, -0.042702, 0.026333, -0.074815, -0.025212, -0.12862, 0.026735, -0.019208, 0.07941, 0.02972, 0.008384, 0.000108, 0.044863, 0.010164, -0.028767, -0.000119, 0.01378, 0.031335, -0.082592, -0.057223, -0.038551, 0.018315, 0.107259, 0.055233, 0.002512, 0.09198, -0.013188, -0.006775, 0.011292, 0.018015, 0.064219, -0.02149, -0.050449, 0.049916, -0.054342, -0.048226, -0.064933, -0.007674, 0.005755, 0.02637, 0.064042, 0.061662, 0.094367, 0.029772, -0.013353, 0.009751, 0.058802, 0.045393, -0.08804, -0.0, 0.006415, 0.010515, 0.018438, -0.062109, -0.014298, -0.009789, -0.010444, 0.043405, 0.004296, -0.026941, 0.007697, 0.027425, -0.011978, -0.042385, -0.009887, -0.078373, -0.066538, 0.07197, 0.054919, 0.0884, -0.023044, 0.052233, 0.037514, 0.006085, 0.004845, -0.062407, 0.062177, -0.010833, 0.041238, -0.007311, 0.053847, 0.061678, -0.06433, -0.07299, -0.076778, 0.072162, 0.013523, 0.048131, -0.005591, -0.004981, 0.029879, 0.030814, 0.014853, 0.025405, 0.036982, -0.02958, 0.013289, -0.079193, -0.026614, 0.022251, -0.05738, -0.055948, -0.09009, 0.057993, 0.025594, 0.020821, -0.058983, -0.019891, -0.056438, -0.018085, 0.004592, -0.027905, -0.078114, -0.066058, -0.12647, 0.065086, 0.09422, -0.030053, -0.072248, 0.079478, -0.038012, -0.018968, -0.014048, 0.0084, -0.04842, 0.010903, 0.031903, -0.014804, 0.079257, 0.009367, -0.023245, 0.003799, 0.009421, -0.04536, -0.031547, 0.021899, 0.006482, -0.028913, 0.069169, -0.078309, -0.029339, -0.058344, 0.059904, 0.05393, 0.045981, 0.0, 0.01247, -0.005408, -0.019551, 0.150233, -0.089295, -0.051654, 0.092781, 0.051742, 0.060014, -0.027223, -0.05575, 0.125829, 0.067986, 0.05497, 0.024049, -0.021999, 0.08931, 0.00587, 0.112441, -0.0351, -0.014155, 0.048052, -0.002971, 0.051707, 0.000495, 0.045515, -0.031115, -0.08211, -0.104104, -0.101409, -0.08705, 0.017745, -0.004164, 0.029721, -0.08971, 0.014555, -0.001606, -0.007836, -0.048439, 0.096636, 0.078062, 0.050833, -0.010569, -0.018808, -0.021594, -0.015485, 0.035797, 0.136971, 0.013268, 0.044634, -0.015597, 0.009701, -0.062235, 0.026988, -0.057475, -0.006233, 0.054326, -0.026223, -0.053, 0.075138, 0.002412, 0.139028, -0.010411, 4e-06, 0.029539, -0.043796, -0.006202, -0.055693, 0.087018, -0.036118, 0.07928, -0.051239, -0.088647, 0.041218, 0.026324, 0.093801, 0.043655, -0.046647, 0.041659, 0.018877, -0.038645, 0.078824, -0.005891, 0.005019, -0.054526, -0.002456, 0.070257, -0.074369, 0.016044, -0.052179, -0.086966, -0.010564, 0.041815, 0.068569, -0.048659, -0.0, -0.02995, 0.014295, -0.084445, -0.00176, 0.004367, 0.011194, 0.002129, 0.028764, 0.013208, -0.008427, 0.127545, -0.00679, -0.037554, -0.034865, 0.033367, 0.008528, -0.02958, 0.052272, -0.035205, -0.048205, -0.030259, 0.116698, 0.031192, -0.072174, -0.02462, 0.035733, 0.003416, 0.097955, -0.061407, 0.057089, -0.107613, 0.03057, 0.053475, -0.060013, -0.074826, 0.035765, 0.059969, 0.021349, 0.05975, -0.021479, 0.06427, -0.069352, -0.061033, -0.035699, -0.032037, 0.007571, 0.01075, -0.016577, 0.027328, -0.059838, 0.007817, 0.013962, -0.029294, 0.022689, 0.04012, -0.00908, -0.064645, -0.004515, -0.036556, -0.016689, 0.024021, -0.076919, -0.058577, 0.02032]
A10: Q7 | B10: What is CBA doing to expand investment opportunities for retail customers? | C10: [0.025654, 0.024019, -0.034065, -0.028773, -0.042246, 0.059559, 0.015746, 0.012557, -0.006247, -0.067588, 0.01317, 0.031538, 0.001681, -0.026768, 0.073808, 0.038509, 0.090275, -0.063887, -0.037216, -0.022519, -0.072962, 0.013918, -0.02418, 0.055312, -0.09266, -0.014284, 0.060779, -0.015799, -0.006902, -0.033645, -0.00629, 0.118365, 0.102176, 0.006123, 0.009447, 0.019028, 0.035058, 0.025648, 0.058286, 0.003117, -0.012223, -0.027047, -0.100145, 0.032287, 0.0717, -0.087969, 0.040475, 0.030898, 0.034744, -0.000926, 0.038231, 0.011762, 0.02676, 0.017986, -0.062961, 0.015439, -0.062126, 0.016142, 0.092502, 0.06475, -0.033882, 0.001106, 0.045385, 0.067185, 0.081584, -0.068993, -0.134785, 0.012183, -0.079733, -0.104615, 0.005946, -0.100056, -0.072474, -0.034547, 0.022684, 0.026733, -0.009194, 0.072232, 0.06892, -0.012437, 0.021352, 0.008684, -0.024937, 0.017895, -0.056087, -0.010737, 0.01454, -0.082828, -0.022727, 0.052824, 0.064482, 0.024584, -0.050396, -0.034078, -0.095399, -0.045326, -0.034806, -0.086081, 0.04726, 0.020754, 0.077428, 0.000506, 0.048645, -0.047925, -0.119483, -0.080902, 0.03171, 0.057417, 0.047036, 0.043564, -0.038084, 0.015824, -0.015991, -0.017618, -0.014346, -0.003161, -0.041262, 0.045515, 0.071793, 0.018553, 0.016036, 0.084068, -0.012587, -0.057127, -0.037825, -0.024675, -0.068251, -0.0, -0.051425, 0.054187, -0.014264, 0.043288, -0.007097, -0.032388, 0.003331, -0.039226, -0.01144, -0.008616, 0.017137, 0.13839, 0.020942, 0.014892, 0.048504, 0.036109, -0.127813, 0.079648, 0.085826, -0.041712, -0.00697, -0.009844, 0.04413, 0.036582, 0.035372, 0.018043, 0.055449, -0.009822, 0.089273, 0.014133, 0.110081, 0.061445, -0.027164, -0.004708, -0.049326, 0.066567, 0.030198, -0.047094, -0.006244, 0.002931, -0.099586, -0.012238, -0.013368, 0.007498, -0.007096, 0.024672, -0.044183, -0.015243, -0.047462, 0.090983, -0.023932, -0.05612, -0.043007, 0.031226, 0.020215, -0.043866, 0.000429, -0.11169, 0.027259, -0.04216, 0.010195, 0.009515, -0.096815, 0.038736, -0.102525, -0.019117, -0.006023, -0.020428, 0.014475, -0.019954, 0.017995, 0.039325, 0.080694, -0.017629, -0.00994, -0.073648, -0.132898, 0.06798, 0.089986, 0.055242, 0.049471, -0.020763, 0.096791, -0.027186, 0.021788, -0.026988, 0.070627, -0.038319, -0.05884, -0.048916, -0.060682, 0.062567, -0.043927, 0.141849, 0.096831, 0.0, 0.035524, 0.024448, 0.042869, -0.0044, 0.00322, -0.039172, -0.012876, -0.061544, 0.010545, -0.038498, -0.098259, 0.01828, 0.023365, 0.085502, -0.046814, -0.046637, 0.054394, -0.00187, 0.01481, -0.059022, 0.053699, -0.057172, -0.049085, 0.02069, 0.008027, 0.007547, -0.101186, 0.018816, -0.016491, -0.044546, -0.053487, 0.026176, -0.009114, 0.074423, -0.060444, -0.003996, -0.009989, -0.000259, -0.014174, -0.000563, 0.012188, -0.028629, 0.010141, -0.00953, -0.010101, 0.005873, 0.12269, 0.014698, 0.071924, 0.002843, 0.013665, 0.019825, 0.008905, -0.006733, -0.036231, 0.076944, 0.072296, -0.029561, -0.044461, 0.027852, 0.096318, 0.112817, 0.048933, -0.006669, -0.001511, -0.030961, 0.054921, -0.0386, 0.001923, -0.074856, 0.105399, -0.008201, -0.008563, -0.039807, -0.080371, 0.008709, 0.016048, -0.088247, -0.068847, -0.006249, -0.107175, -0.021185, 0.06799, 0.024183, 0.024281, 0.008719, -0.013226, -0.074992, -0.028994, 0.044042, -0.123236, 0.01657, -0.00757, 0.006825, -0.034755, -0.0, -0.073861, -0.049541, -0.019478, -0.033516, 0.050499, -0.078572, -0.024264, 0.069933, 0.05424, -0.048838, 0.008013, 0.008796, -0.073324, 0.088802, 0.077305, 0.0779, 0.052408, -0.011539, -0.013119, 0.032581, 0.014246, 0.020145, 0.065063, -0.055242, -0.005328, 0.001881, -0.074702, 0.078146, 0.004464, -0.015758, 0.010838, 0.040577, 0.067829, -0.055377, -0.031013, -0.028907, 0.042809, 0.045894, -0.025497, -0.034604, -0.07391, -0.053905, -0.007297, -0.025283, -0.007324, -0.045441, -0.120572, 0.042922, 0.039226, -0.015553, 0.022335, -0.05466, 0.026758, -0.0215, 0.026436, -0.003234, -0.026204, 0.014136, -0.012962, -0.012647, -0.06203, -0.077221, 0.020527, 0.037632]
A11: Q8 | B11: How is AI affecting employment at Commonwealth Bank? | C11: [0.02477, -0.008563, -0.002138, 0.022444, 0.044938, 0.046775, 0.055493, -0.043085, -0.020578, -0.005761, -0.024309, 0.051332, -0.057956, -0.0107, 0.011445, 0.04914, -0.02057, -0.02902, -0.060139, -0.05033, 0.009973, -0.079812, -0.081262, -0.065134, -0.038668, -0.014324, 0.064502, 0.000721, 0.005075, -0.0379, -0.057749, 0.042347, 0.05788, -0.010037, 0.044062, -0.031473, 0.010249, 0.080995, 0.059104, -0.082869, 0.044001, -0.088792, -0.009659, -0.056807, 0.111278, 0.061933, 0.041955, 0.012235, -0.051877, 0.077021, -0.074805, -0.018039, 0.087682, -0.027609, -0.051543, -0.022817, 0.037848, 0.011268, 0.055987, -0.024024, 0.020797, 0.002822, 0.017026, 0.040968, 0.165113, 0.001091, -0.086399, -0.024397, -0.053853, -0.056909, 0.019753, -0.131297, -0.090152, -0.032021, 0.004491, 0.02209, -0.024006, 0.0333, 0.106723, -0.031177, 0.024842, -0.055324, -0.010653, 0.04962, -0.012548, -0.026473, 0.055696, -0.079174, 0.017776, 0.012593, 0.074263, -0.068578, 0.057471, -0.013805, 0.11885, -0.04533, -0.034357, 0.015273, 0.035308, 0.022493, 0.058838, 0.061692, -0.042336, 0.106958, -0.020907, 0.04982, 0.06404, -0.01881, 0.083338, -0.021775, -0.054543, 0.062698, 0.018075, -0.034061, 0.028297, 0.022337, -0.004872, 0.129362, -0.015691, 0.08172, 0.001577, 0.031642, -0.048487, 0.024072, -0.043719, 0.034575, -0.11674, -0.0, -0.062329, -0.004152, 0.008287, -0.039794, 0.062935, -0.110645, -0.04311, -0.006607, -0.000419, 0.041755, -0.071938, 0.037582, 0.050791, 0.003868, 0.02336, 0.029093, 0.017236, 0.05358, 0.021346, 0.094617, 0.03523, -0.062566, -0.031154, -0.001704, 0.017122, 0.005927, -0.018547, -0.019198, 0.067296, 0.009966, 0.017152, 0.031494, -0.071959, 0.05007, -0.019014, 0.038742, -0.049008, -0.00068, 0.024073, 0.047214, -0.021338, 0.019214, 0.110339, -0.008072, -0.029236, 0.045604, -0.006911, -0.05326, -0.016939, 0.124668, -0.036313, 0.014972, -0.079001, -0.056272, 0.052495, -0.022953, -0.037965, 0.002626, 0.037377, -0.027468, 0.032741, -0.055646, -0.110187, 0.052454, -0.027572, 0.080972, 0.053837, -0.00321, 0.036856, -0.013256, -0.007494, 0.059784, 0.012072, -0.017096, -0.098603, 0.051019, -0.054692, 0.001661, -0.004471, 0.015081, 0.000982, 0.039057, 0.015846, -0.074363, 0.017366, -0.024186, 0.006623, -0.064402, 0.037697, -0.040425, 0.001027, -0.026207, -0.030657, 0.124193, -0.02506, 0.0, -0.08752, -0.0273, -0.048769, 0.00705, -0.066536, -0.005848, 0.084678, -0.012819, 0.026385, 0.043945, -0.031461, -0.017749, -0.008437, 0.058904, -0.009452, 0.000804, 0.053858, 0.034148, 0.043455, -0.022987, 0.027074, 0.049793, 0.032356, 0.01817, 0.002825, 0.081175, -0.091948, -0.059037, -0.003575, -0.036566, -0.035605, 0.046568, -0.090186, 0.093254, -0.035102, -0.025945, -0.007429, -0.077104, 0.019336, 0.033376, -0.005139, -0.016061, -0.076438, -0.027752, 0.022148, -0.005632, 0.068615, 0.057031, 0.081295, -0.04595, 0.049399, 0.033018, -0.012585, 0.041824, -0.086729, 0.010988, 0.113063, -0.034616, -0.08128, 0.053472, -0.014279, 0.033671, 0.030622, -0.034661, 0.004595, 0.012334, 0.019615, 0.032767, 0.068379, -0.114734, 0.034279, -0.065033, -0.010855, 0.053028, -0.03073, 0.019804, 0.023024, -0.083422, -0.058232, -0.023676, -0.075668, -0.020821, -0.000561, 0.045255, -0.038348, 0.022323, 0.037266, -0.057904, -0.026099, -0.004026, -0.048054, -0.054236, -0.018409, 0.024911, -0.083944, -0.0, 0.002102, -0.033742, 0.042945, -0.007577, 0.01487, -0.068663, -0.037188, 0.022319, -0.01334, -0.023974, 0.002006, -0.034, -0.047548, -0.034997, 0.086649, 0.073444, 0.005747, -0.052233, -0.022182, -0.040368, 0.060951, 0.044702, -0.023925, -0.014745, -0.054326, -0.041487, 0.073201, 0.074185, -0.009245, 0.037361, -0.095469, 0.101008, 0.058359, -0.035358, -0.047827, -0.011362, 0.094096, -0.067565, -0.056935, -0.060106, -0.011293, 0.012917, -0.026605, -0.031558, 0.08456, -0.053513, -0.068414, -0.024917, 0.02919, -0.103441, 0.018895, 0.027605, 0.056451, 0.133963, 0.105403, -0.051301, -0.037382, -0.061769, -0.012991, 0.047519, 0.052002, -0.028364, 0.062173, -0.110042]
A12: Q9 | B12: What is CBA's latest dividend payout ratio? | C12: [-0.033144, -0.011279, -0.099342, 0.010818, -0.029386, 0.020072, -0.036055, 0.013872, 0.020006, -0.022177, -0.018113, 0.006081, -0.028319, 0.023887, -0.03497, 0.037987, 0.055973, -0.048632, 0.013259, -0.021411, -0.069522, 0.0279, 0.003825, 0.028189, 0.123177, -0.024226, -0.001834, -0.063945, 0.005196, -0.023495, 0.026657, 0.144076, 0.11711, -0.046467, -0.081021, -0.022245, 0.020141, -0.05314, 0.097303, 0.032361, -0.013065, 0.042404, -0.020027, -0.016651, -0.034542, -0.03846, 0.001523, 0.018838, 0.063395, 0.092738, 0.019427, 0.022651, -0.020332, 0.107858, 0.025738, 0.006647, -0.073752, 0.024142, 0.079476, 0.049363, -0.036911, 0.020291, 0.02293, 0.056124, 0.096313, -0.043009, -0.024252, -0.044704, -0.052026, -0.09221, -0.015525, 0.00997, -0.056462, -0.146472, 0.006748, 0.104037, 0.028722, 0.072241, 0.000277, -0.067343, -0.055645, 0.031705, 0.015706, -0.014833, -0.01265, -0.043685, 0.057093, 0.023097, 0.046118, 0.029871, 0.019358, 0.064363, 0.009472, -0.05678, -0.083136, 0.005623, -0.062844, -0.061963, -0.028409, -0.023989, 0.081342, 0.115204, -0.032744, -0.088528, -0.015117, -0.007756, 0.063886, 0.062394, 0.076099, 0.034838, 0.00231, 0.043387, 0.003968, -0.047547, -0.0543, -0.044058, -0.032843, 0.008276, 0.13537, 0.013505, 0.090627, 0.074897, -0.07099, -0.020311, 0.002922, -0.051855, -0.054663, -0.0, 0.087881, 0.025791, 0.051642, 0.037931, -0.00245, -0.053844, 0.011986, 0.009161, 0.023054, -0.012657, -0.096594, 0.031816, 0.013232, -0.072233, 0.015906, -0.074772, -0.106326, 0.04761, 0.068619, 0.026509, 0.006641, 0.005699, 0.013893, -0.006077, 0.093001, 0.008629, -0.030912, -0.021861, 0.011602, 0.02173, 0.030042, 0.08394, -0.067211, -0.066663, -0.078499, -0.001265, -0.014557, 0.093063, 0.014549, -0.00494, -0.042733, -0.019826, -0.066705, -0.03667, -0.028212, -0.036731, 0.00643, -0.027657, 0.024411, 0.016708, -0.057049, -0.036756, 0.007146, -0.010917, 0.032469, -0.034134, 0.030027, -0.032678, -0.004432, 0.050726, 0.008619, 0.092504, -0.088328, -0.011421, -0.134383, 0.001484, -0.078487, -0.007808, -0.072123, 0.037164, 0.013572, 0.020719, 0.050572, 0.0251, -0.031516, -0.089682, -0.008105, 0.012205, 0.081671, 0.067336, -0.027521, 0.040068, 0.068207, -0.04114, -0.002482, -0.006099, 0.054869, 0.030017, -0.018494, -0.042143, -0.002917, -0.096958, 0.072691, -0.020717, 0.05963, 0.0, 0.020808, 0.027888, 0.00348, -0.006174, -0.007822, -0.080738, 0.06271, 0.109827, 0.03929, 0.050761, -0.00382, 0.046699, 0.025245, 0.104448, -0.013557, -0.020078, 0.008972, -0.03684, -0.011535, -0.061075, 0.05475, -0.045954, -0.021693, 0.06173, 0.026963, 0.000761, -0.013602, 0.004264, 0.017282, 0.007024, -0.052387, -0.05834, -0.080279, 0.028192, -0.001776, -0.024955, -0.082283, 0.036426, 0.045172, 0.019839, 0.027946, -0.025387, -0.020049, 0.040338, 0.063076, -0.005974, 0.081059, 0.009424, 0.05427, 0.044557, 0.00912, 0.036311, -0.025338, 0.076153, 0.029236, 0.071544, -0.043663, 0.018476, -0.018558, -0.004273, 0.074132, 0.122504, -0.004484, 0.014845, -0.034045, 0.076986, -0.027423, 0.0809, -0.001049, 0.018848, 0.112336, -0.031752, 0.087979, -0.01519, -0.012322, 0.063329, 0.03311, -0.030725, -0.033496, 0.052501, -0.032207, 0.005967, 0.031457, 0.042991, -0.026215, 0.011799, 0.066592, -0.056156, -0.008021, 0.022042, -0.126647, -0.072653, 0.038185, 0.075946, 0.038321, -0.0, -0.076325, -0.032306, -0.08853, -0.054022, 0.085419, -0.002901, -0.0079, -0.032889, -0.014797, -0.045113, 0.060993, 0.013308, -0.077085, 0.016832, -0.027245, -0.002899, -0.019482, -0.011864, -0.004932, -0.041954, 0.017768, 0.002514, 0.05696, -0.043919, -0.044407, 0.00709, -0.095663, 0.023408, -0.04646, -0.046815, 0.033935, 0.086469, -0.046362, -0.104522, 0.006175, -0.009899, 0.021548, 0.052932, 0.031754, 0.016624, -0.024083, -0.102282, -0.057906, -0.025085, -0.002043, -0.001311, -0.116314, 0.008689, -0.017273, -0.157762, 0.035377, 0.008546, -0.028814, 0.030088, 0.061717, -0.039411, -0.071393, 0.015604, -0.049764, -0.057335, -0.044506, -0.084736, 0.033884, 0.028785]
... A19: H4 | B19: How is CBA generating A$400 million in value from its AI initiatives? | C19: [0.013275, 0.009012, -0.046796, -0.020073, -0.044902, 0.056053, -0.015964, 0.070823, 0.040899, 0.017405, -0.048942, -0.046528, 0.058586, -0.056027, -0.022422, 0.138769, 0.082762, -0.065646, -0.061385, -0.026664, -0.026969, 0.025237, -0.010889, -0.00979, 0.016575, 0.044449, 0.053226, -0.066474, 0.045521, 0.006832, 0.010596, 0.107613, 0.047607, -0.000439, 0.016918, 0.068151, 0.009408, 0.030497, 0.102857, -0.004754, 0.029917, -0.013686, -0.020172, -0.058618, 0.040775, 0.02217, 0.034745, 0.027443, 0.037127, 0.034867, 0.001274, 0.015711, 0.020013, 0.018421, -0.025297, -0.008359, -0.007881, 0.016055, 0.046423, 0.09276, -0.025344, 0.012895, 0.052991, 0.014804, 0.111182, -0.02871, -0.0738, -0.060905, -0.051474, -0.131774, 0.099556, -0.034995, -0.044115, -0.037748, 0.050025, 0.029874, 0.010316, 0.099243, 0.100377, -0.046792, 0.024804, 0.013805, -0.010731, 0.011424, -0.010952, 0.028662, 0.031233, -0.027501, 0.055939, 0.083378, 0.054259, -0.058347, 0.02387, -0.045208, -0.037807, 0.032619, -0.021799, -0.073075, 0.049851, 0.022864, 0.034051, 0.014178, -0.01848, -0.071823, -0.092087, -0.062338, 0.091853, 0.023008, 0.05671, 0.050334, -0.009423, -0.018036, 0.019562, -0.043805, -0.008092, 0.013507, -0.056853, 0.046483, 0.066865, -0.026341, 0.030256, -0.000239, -0.009019, -0.00293, -0.02584, -0.027593, -0.115629, -0.0, -0.014963, 0.066814, 0.025353, -0.03207, -0.068832, -0.072961, -0.018169, 0.01798, 0.025479, 0.001042, -0.056313, 0.129531, 0.049496, 0.045588, 0.052511, -0.078923, -0.120799, 0.00452, 0.042633, 0.003861, 0.047518, -0.065605, 0.103044, 0.020758, 0.04357, 0.045994, 0.022308, -0.02163, 0.036463, 0.009035, 0.014831, 0.092609, -0.030536, -0.055655, -0.058816, 0.049803, 0.027631, 0.005915, -0.014364, 0.088943, -0.051094, 0.046671, 0.00164, -0.004917, -0.042463, 0.037817, -0.004643, -0.039699, 0.009864, -0.005711, -0.007547, -0.002812, -0.060229, -0.041592, 0.011599, -0.094368, -0.006168, -0.036324, 0.018415, -0.016531, -0.004222, 0.054676, -0.057174, 0.123454, -0.108052, 0.078575, 0.005393, 0.044684, 0.048692, -0.061086, 0.053487, -0.040069, 0.006683, -0.066925, -0.080068, -0.075835, -0.028227, 0.023394, 0.090401, 0.06867, -0.044945, 0.004281, 0.071888, -0.047179, 0.118785, -0.033384, 5.4e-05, 0.015877, -0.042482, -0.050205, -0.019239, -0.006474, -0.027653, 0.077012, 0.011576, 0.0, -0.043245, 0.040073, 0.013589, -0.03815, 0.038717, -0.06402, -0.010321, -0.013591, 0.021869, 0.058065, -0.082593, -0.049885, -0.013257, 0.10542, -0.010441, -0.085562, 0.022392, -0.077974, -0.007672, -0.066327, 0.02314, 0.05479, 0.009118, 0.008433, -0.023088, 0.016694, -0.089055, 0.009845, 0.065846, 0.001436, 0.006283, -0.023137, -0.082975, 0.079343, -0.086108, 0.042531, 0.06379, -0.077809, -0.027409, -0.022453, 0.002342, -0.027576, -0.104464, 0.047885, -0.020201, 0.048514, 0.01464, 0.031205, 0.046734, -0.022124, 0.070221, -0.009379, -0.027006, 0.011987, -0.092323, 0.014267, 0.064364, -0.014242, -0.039445, -0.008152, 0.052508, 0.064051, -0.00148, 0.035495, -0.051649, 0.043084, 0.056249, -0.000987, -0.043319, -0.081965, 0.068339, -0.066614, -0.010372, 0.003873, -0.028939, 0.091592, -0.022285, -0.016935, 0.044395, -0.051164, -0.062362, -0.022776, 0.052957, -0.026735, 0.033457, 0.050609, -0.023557, -0.129378, -0.059132, 0.137852, -0.102495, -0.020112, 0.013144, 0.047619, -0.038709, -0.0, -0.056977, -0.015599, -0.009845, 0.012038, 0.020801, -0.07681, -0.085178, 0.048126, 0.015785, -0.058227, 0.013747, -0.038196, -0.084871, 0.050899, 0.028335, 0.010455, -0.046652, 0.016821, -0.005521, -0.025244, 0.027613, -0.021317, -0.000194, -0.072737, 0.017889, -0.040193, -0.070191, 0.078212, -0.027257, 0.040226, -0.008679, 0.060115, -0.002157, -0.015909, 0.029218, -0.060838, 0.022702, 0.003464, -0.007384, -0.086699, -0.012304, 0.020283, -0.055621, -0.050129, 0.016455, -0.026689, -0.147439, -0.033095, 0.100782, -0.116404, 0.035145, -0.042044, 0.023037, 0.069528, 0.084956, -0.023061, -0.019266, -0.011124, 0.004046, -0.020154, -0.030994, -0.092995, 0.038837, -0.04107]

Sheet Example-Question-Article
A1: Question ID | B1: Question | C1: Test Purpose | D1: CSV Row | E1: Article ID | F1: Article Title | G1: Relevance Label | H1: Review Status
A2: Q1 | B2: How is CBA using AI to improve software engineering productivity? | C2: Direct semantic matching | D2: 3 | E2: d1b0bef8-6caa-4a64-88c9-3a0aa08b588b | F2: Interview: CBA AI chief on scaling A$400m in AI value with humans in loop | G2: Relevant | H2: Provisional — verify
A3: Q2 | B3: What technology leadership changes has CBA made to support its AI strategy? | C3: Specific fact retrieval | D3: 18 | E3: b68a2d6d-73de-419c-b598-7ce0a1052836 | F3: Commonwealth Bank of Australia appoints new CIO, CTO to boost technology, AI strategy | G3: Relevant | H3: Provisional — verify
A4: Q3 | B4: How is CBA modernising its payment services? | C4: Paraphrase / semantic retrieval | D4: 9 | E4: 413c847a-f31f-48e9-8aa3-215b13213f26 | F4: Commonwealth Bank unveils payout platform ahead of cheque exit | G4: Relevant | H4: Provisional — verify
A5: Q4 | B5: What are the risks associated with AI-powered shopping and payment agents? | C5: Multiple relevant articles | D5: 1 | E5: 99d3c240-a69d-471e-9754-bd53d542c01f | F5: Banks warn AI shopping agents could increase risk of scams, fraud and data privacy breaches | G5: Relevant | H5: Provisional — verify
A6: Q4 | B6: What are the risks associated with AI-powered shopping and payment agents? | C6: Multiple relevant articles | D6: 2 | E6: b1b83951-4c53-41ff-a55f-9a52d2b6570d | F6: Banks warn AI shopping agents outpace fraud protections | G6: Relevant | H6: Provisional — verify
A7: Q5 | B7: What challenges are Australian banks facing in mortgage lending? | C7: Industry-context retrieval | D7: 10 | E7: 686cdb0c-4e0e-4c16-82e8-cc5fb13cd2ca | F7: Australian bank investors brace for tough times as mortgage demand plummets | G7: Relevant | H7: Provisional — verify
A8: Q6 | B8: What are the latest expectations for Australian interest rates? | C8: Multiple related articles | D8: 7 | E8: 3197f837-7d31-4fd0-9208-cca4c823c4f2 | F8: Three of Australia's four major banks forecast another rate hike this year | G8: Relevant | H8: Provisional — verify
A9: Q6 | B9: What are the latest expectations for Australian interest rates? | C9: Multiple related articles | D9: 12 | E9: 5471b7ec-a7a3-4b6f-9ed9-1077daa933df | F9: Fast Money Bets on November RBA Hike in Fight Against Inflation | G9: Relevant | H9: Provisional — verify
A10: Q7 | B10: What is CBA doing to expand investment opportunities for retail customers? | C10: Indirect semantic matching | D10: 15 | E10: c4a7e0e3-afd4-4f96-a328-a4fc62d9dce2 | F10: CommSec Eyes More U.S. IPOs After 28,000 SpaceX Applications | G10: Relevant | H10: Provisional — verify
A11: Q8 | B11: How is AI affecting employment at Commonwealth Bank? | C11: Headline-only evidence | D11: 14 | E11: 6b7cca15-b540-451a-8034-b1fc4704f805 | F11: AI Is Replacing Customer Service Jobs at CBA, Microsoft, Uber | G11: Relevant | H11: Provisional — verify
A12: Q9 | B12: What is CBA's latest dividend payout ratio? | C12: Answer absent / unsupported specific fact | G12: No confirmed evidence | H12: Provisional — verify
A13: Q10 | B13: What was CBA's exact net profit for FY2025? | C13: Answer absent / unsupported specific fact | G13: No confirmed evidence | H13: Provisional — verify

Sheet Question-Article-Match
A1: Question ID | B1: Question | C1: CSV Row | D1: Article ID | E1: Article Title | F1: Match Reason
A2: Q1 | B2: How is CBA using AI to improve software engineering productivity? | C2: 3 | D2: d1b0bef8-6caa-4a64-88c9-3a0aa08b588b | E2: Interview: CBA AI chief on scaling A$400m in AI value with humans in loop | F2: direct match
A3: Q1 | B3: How is CBA using AI to improve software engineering productivity? | C3: 18 | D3: b68a2d6d-73de-419c-b598-7ce0a1052836 | E3: Commonwealth Bank of Australia appoints new CIO, CTO to boost technology, AI strategy | F3: indirect match
A4: Q1 | B4: How is CBA using AI to improve software engineering productivity? | C4: 14 | D4: 6b7cca15-b540-451a-8034-b1fc4704f805 | E4: AI Is Replacing Customer Service Jobs at CBA, Microsoft, Uber | F4: indirect match
A5: Q2 | B5: What technology leadership changes has CBA made to support its AI strategy? | C5: 18 | D5: b68a2d6d-73de-419c-b598-7ce0a1052836 | E5: Commonwealth Bank of Australia appoints new CIO, CTO to boost technology, AI strategy | F5: direct match
A6: Q2 | B6: What technology leadership changes has CBA made to support its AI strategy? | C6: 3 | D6: d1b0bef8-6caa-4a64-88c9-3a0aa08b588b | E6: Interview: CBA AI chief on scaling A$400m in AI value with humans in loop | F6: indirect match
A7: Q3 | B7: How is CBA modernising its payment services? | C7: 9 | D7: 413c847a-f31f-48e9-8aa3-215b13213f26 | E7: Commonwealth Bank unveils payout platform ahead of cheque exit | F7: indirect match
A8: Q3 | B8: How is CBA modernising its payment services? | C8: 1 | D8: 99d3c240-a69d-471e-9754-bd53d542c01f | E8: Banks warn AI shopping agents could increase risk of scams, fraud and data privacy breaches | F8: indirect match
A9: Q3 | B9: How is CBA modernising its payment services? | C9: 2 | D9: b1b83951-4c53-41ff-a55f-9a52d2b6570d | E9: Banks warn AI shopping agents outpace fraud protections | F9: indirect match
A10: Q4 | B10: What are the risks associated with AI-powered shopping and payment agents? | C10: 1 | D10: 99d3c240-a69d-471e-9754-bd53d542c01f | E10: Banks warn AI shopping agents could increase risk of scams, fraud and data privacy breaches | F10: direct match
A11: Q4 | B11: What are the risks associated with AI-powered shopping and payment agents? | C11: 2 | D11: b1b83951-4c53-41ff-a55f-9a52d2b6570d | E11: Banks warn AI shopping agents outpace fraud protections | F11: direct match
A12: Q5 | B12: What challenges are Australian banks facing in mortgage lending? | C12: 10 | D12: 686cdb0c-4e0e-4c16-82e8-cc5fb13cd2ca | E12: Australian bank investors brace for tough times as mortgage demand plummets | F12: direct match
A13: Q5 | B13: What challenges are Australian banks facing in mortgage lending? | C13: 7 | D13: 3197f837-7d31-4fd0-9208-cca4c823c4f2 | E13: Three of Australia's four major banks forecast another rate hike this year | F13: indirect match
... A32: Q10 | B32: What was CBA's exact net profit for FY2025? | C32: 19 | D32: f6a03202-fdda-4b58-97b6-a48e3659827b | E32: Did Profit Uptick and RBA Countdown Just Shift Commonwealth Bank's (ASX:CBA) Investment Narrative? | F32: indirect match
A33: Q11 | B33: Has CBA faced any recent regulatory action or penalties from ASIC, APRA or AUSTRAC? | C33: None | D33: None | E33: None | F33: no match
A34: Q12 | B34: What are CBA's climate commitments, such as net-zero targets or limits on fossil-fuel lending? | C34: None | D34: None | E34: None | F34: no match
A35: H1 | B35: What new payout platform has CBA introduced to replace cheque-based payments? | C35: 9 | D35: 413c847a-f31f-48e9-8aa3-215b13213f26 | E35: Commonwealth Bank unveils payout platform ahead of cheque exit | F35: direct match
A36: H2 | B36: How has CBA supported archTIS with a A$4 million financing facility? | C36: 16 | D36: a8b21a0e-aa2c-42e8-8cfb-c7479fd1d8e3 | E36: archTIS extends A$4 million CBA facility to support contract execution and growth | F36: direct match
A37: H3 | B37: What changes has CBA made to its CIO and CTO positions? | C37: 18 | D37: b68a2d6d-73de-419c-b598-7ce0a1052836 | E37: Commonwealth Bank of Australia appoints new CIO, CTO to boost technology, AI strategy | F37: direct match
A38: H3 | B38: What changes has CBA made to its CIO and CTO positions? | C38: 3 | D38: d1b0bef8-6caa-4a64-88c9-3a0aa08b588b | E38: Interview: CBA AI chief on scaling A$400m in AI value with humans in loop | F38: indirect match
A39: H4 | B39: How is CBA generating A$400 million in value from its AI initiatives? | C39: 3 | D39: d1b0bef8-6caa-4a64-88c9-3a0aa08b588b | E39: Interview: CBA AI chief on scaling A$400m in AI value with humans in loop | F39: direct match
A40: H4 | B40: How is CBA generating A$400 million in value from its AI initiatives? | C40: 18 | D40: b68a2d6d-73de-419c-b598-7ce0a1052836 | E40: Commonwealth Bank of Australia appoints new CIO, CTO to boost technology, AI strategy | F40: indirect match
A41: H4 | B41: How is CBA generating A$400 million in value from its AI initiatives? | C41: 14 | D41: 6b7cca15-b540-451a-8034-b1fc4704f805 | E41: AI Is Replacing Customer Service Jobs at CBA, Microsoft, Uber | F41: indirect match

Sheet Error Analysis
A1: Question ID | B1: Question | C1: Rank | D1: Article ID | E1: Article Title | F1: Cosine Similarity | G1: Ground Truth | H1: Below Threshold
A2: Q7 | B2: What is CBA doing to expand investment opportunities for retail customers? | C2: 1 | D2: f6a03202-fdda-4b58-97b6-a48e3659827b | E2: Did Profit Uptick and RBA Countdown Just Shift Commonwealth Bank's (ASX:CBA) Investment Narrative? | F2: 0.5138 | G2: =IF(COUNTIFS('Question-Article-Match'!$A:$A,A2,'Question-Article-Match'!$C:$C,C2,'Question-Article-Match'!$F:$F,"direct match")>0,"direct match",IF(COUNTIFS('Question-Article-Match'!$A:$A,A2,'Question-Article-Match'!$C:$C,C2,'Question-Article-Match'!$F:$F,"indirect match")>0,"indirect match","no match")) -> no match | H2: =IF($F2<0.4,TRUE,FALSE) -> FALSE
A3: Q7 | B3: What is CBA doing to expand investment opportunities for retail customers? | C3: 2 | D3: a8b21a0e-aa2c-42e8-8cfb-c7479fd1d8e3 | E3: archTIS extends A$4 million CBA facility to support contract execution and growth | F3: 0.4786 | G3: =IF(COUNTIFS('Question-Article-Match'!$A:$A,A3,'Question-Article-Match'!$C:$C,C3,'Question-Article-Match'!$F:$F,"direct match")>0,"direct match",IF(COUNTIFS('Question-Article-Match'!$A:$A,A3,'Question-Article-Match'!$C:$C,C3,'Question-Article-Match'!$F:$F,"indirect match")>0,"indirect match","no match")) -> no match | H3: =IF($F3<0.4,TRUE,FALSE) -> FALSE
A4: Q7 | B4: What is CBA doing to expand investment opportunities for retail customers? | C4: 3 | D4: 6b7cca15-b540-451a-8034-b1fc4704f805 | E4: AI Is Replacing Customer Service Jobs at CBA, Microsoft, Uber | F4: 0.4653 | G4: =IF(COUNTIFS('Question-Article-Match'!$A:$A,A4,'Question-Article-Match'!$C:$C,C4,'Question-Article-Match'!$F:$F,"direct match")>0,"direct match",IF(COUNTIFS('Question-Article-Match'!$A:$A,A4,'Question-Article-Match'!$C:$C,C4,'Question-Article-Match'!$F:$F,"indirect match")>0,"indirect match","no match")) -> no match | H4: =IF($F4<0.4,TRUE,FALSE) -> FALSE
A5: Q7 | B5: What is CBA doing to expand investment opportunities for retail customers? | C5: 4 | D5: b1b83951-4c53-41ff-a55f-9a52d2b6570d | E5: Banks warn AI shopping agents outpace fraud protections | F5: 0.353 | G5: =IF(COUNTIFS('Question-Article-Match'!$A:$A,A5,'Question-Article-Match'!$C:$C,C5,'Question-Article-Match'!$F:$F,"direct match")>0,"direct match",IF(COUNTIFS('Question-Article-Match'!$A:$A,A5,'Question-Article-Match'!$C:$C,C5,'Question-Article-Match'!$F:$F,"indirect match")>0,"indirect match","no match")) -> no match | H5: =IF($F5<0.4,TRUE,FALSE) -> TRUE
A6: Q7 | B6: What is CBA doing to expand investment opportunities for retail customers? | C6: 5 | D6: d1b0bef8-6caa-4a64-88c9-3a0aa08b588b | E6: Interview: CBA AI chief on scaling A$400m in AI value with humans in loop | F6: 0.337 | G6: =IF(COUNTIFS('Question-Article-Match'!$A:$A,A6,'Question-Article-Match'!$C:$C,C6,'Question-Article-Match'!$F:$F,"direct match")>0,"direct match",IF(COUNTIFS('Question-Article-Match'!$A:$A,A6,'Question-Article-Match'!$C:$C,C6,'Question-Article-Match'!$F:$F,"indirect match")>0,"indirect match","no match")) -> no match | H6: =IF($F6<0.4,TRUE,FALSE) -> TRUE
A7: Q7 | B7: What is CBA doing to expand investment opportunities for retail customers? | C7: 6 | D7: b68a2d6d-73de-419c-b598-7ce0a1052836 | E7: Commonwealth Bank of Australia appoints new CIO, CTO to boost technology, AI strategy | F7: 0.3249 | G7: =IF(COUNTIFS('Question-Article-Match'!$A:$A,A7,'Question-Article-Match'!$C:$C,C7,'Question-Article-Match'!$F:$F,"direct match")>0,"direct match",IF(COUNTIFS('Question-Article-Match'!$A:$A,A7,'Question-Article-Match'!$C:$C,C7,'Question-Article-Match'!$F:$F,"indirect match")>0,"indirect match","no match")) -> no match | H7: =IF($F7<0.4,TRUE,FALSE) -> TRUE
A8: Q7 | B8: What is CBA doing to expand investment opportunities for retail customers? | C8: 7 | D8: 5471b7ec-a7a3-4b6f-9ed9-1077daa933df | E8: Fast Money Bets on November RBA Hike in Fight Against Inflation | F8: 0.2963 | G8: =IF(COUNTIFS('Question-Article-Match'!$A:$A,A8,'Question-Article-Match'!$C:$C,C8,'Question-Article-Match'!$F:$F,"direct match")>0,"direct match",IF(COUNTIFS('Question-Article-Match'!$A:$A,A8,'Question-Article-Match'!$C:$C,C8,'Question-Article-Match'!$F:$F,"indirect match")>0,"indirect match","no match")) -> no match | H8: =IF($F8<0.4,TRUE,FALSE) -> TRUE
A9: Q7 | B9: What is CBA doing to expand investment opportunities for retail customers? | C9: 8 | D9: 99d3c240-a69d-471e-9754-bd53d542c01f | E9: Banks warn AI shopping agents could increase risk of scams, fraud and data privacy breaches | F9: 0.2844 | G9: =IF(COUNTIFS('Question-Article-Match'!$A:$A,A9,'Question-Article-Match'!$C:$C,C9,'Question-Article-Match'!$F:$F,"direct match")>0,"direct match",IF(COUNTIFS('Question-Article-Match'!$A:$A,A9,'Question-Article-Match'!$C:$C,C9,'Question-Article-Match'!$F:$F,"indirect match")>0,"indirect match","no match")) -> no match | H9: =IF($F9<0.4,TRUE,FALSE) -> TRUE
A10: Q7 | B10: What is CBA doing to expand investment opportunities for retail customers? | C10: 9 | D10: 6192bccf-9d89-4bdf-b571-47e3e02b311d | E10: 3 Australian Dividend Stocks With At Least 3% Yield | F10: 0.2716 | G10: =IF(COUNTIFS('Question-Article-Match'!$A:$A,A10,'Question-Article-Match'!$C:$C,C10,'Question-Article-Match'!$F:$F,"direct match")>0,"direct match",IF(COUNTIFS('Question-Article-Match'!$A:$A,A10,'Question-Article-Match'!$C:$C,C10,'Question-Article-Match'!$F:$F,"indirect match")>0,"indirect match","no match")) -> no match | H10: =IF($F10<0.4,TRUE,FALSE) -> TRUE
A11: Q7 | B11: What is CBA doing to expand investment opportunities for retail customers? | C11: 10 | D11: 8c255177-b931-4783-a1bf-9e2dacfa1b3c | E11: Commonwealth Bank Stock And 2 More Dividend Shares For Reliable Income | F11: 0.264 | G11: =IF(COUNTIFS('Question-Article-Match'!$A:$A,A11,'Question-Article-Match'!$C:$C,C11,'Question-Article-Match'!$F:$F,"direct match")>0,"direct match",IF(COUNTIFS('Question-Article-Match'!$A:$A,A11,'Question-Article-Match'!$C:$C,C11,'Question-Article-Match'!$F:$F,"indirect match")>0,"indirect match","no match")) -> no match | H11: =IF($F11<0.4,TRUE,FALSE) -> TRUE
A12: Q3 | B12: How is CBA modernising its payment services? | C12: 1 | D12: a8b21a0e-aa2c-42e8-8cfb-c7479fd1d8e3 | E12: archTIS extends A$4 million CBA facility to support contract execution and growth | F12: 0.4989 | G12: =IF(COUNTIFS('Question-Article-Match'!$A:$A,A12,'Question-Article-Match'!$C:$C,C12,'Question-Article-Match'!$F:$F,"direct match")>0,"direct match",IF(COUNTIFS('Question-Article-Match'!$A:$A,A12,'Question-Article-Match'!$C:$C,C12,'Question-Article-Match'!$F:$F,"indirect match")>0,"indirect match","no match")) -> indirect match | H12: =IF($F12<0.4,TRUE,FALSE) -> FALSE
A13: Q3 | B13: How is CBA modernising its payment services? | C13: 2 | D13: f6a03202-fdda-4b58-97b6-a48e3659827b | E13: Did Profit Uptick and RBA Countdown Just Shift Commonwealth Bank's (ASX:CBA) Investment Narrative? | F13: 0.4433 | G13: =IF(COUNTIFS('Question-Article-Match'!$A:$A,A13,'Question-Article-Match'!$C:$C,C13,'Question-Article-Match'!$F:$F,"direct match")>0,"direct match",IF(COUNTIFS('Question-Article-Match'!$A:$A,A13,'Question-Article-Match'!$C:$C,C13,'Question-Article-Match'!$F:$F,"indirect match")>0,"indirect match","no match")) -> indirect match | H13: =IF($F13<0.4,TRUE,FALSE) -> FALSE
... A41: Q11 | B41: Has CBA faced any recent regulatory action or penalties from ASIC, APRA or AUSTRAC? | C41: 10 | D41: 99d3c240-a69d-471e-9754-bd53d542c01f | E41: Banks warn AI shopping agents could increase risk of scams, fraud and data privacy breaches | F41: 0.2419 | G41: =IF(COUNTIFS('Question-Article-Match'!$A:$A,A41,'Question-Article-Match'!$C:$C,C41,'Question-Article-Match'!$F:$F,"direct match")>0,"direct match",IF(COUNTIFS('Question-Article-Match'!$A:$A,A41,'Question-Article-Match'!$C:$C,C41,'Question-Article-Match'!$F:$F,"indirect match")>0,"indirect match","no match")) -> no match | H41: =IF($F41<0.4,TRUE,FALSE) -> TRUE

Sheet Similarity
A1: Question ID | B1: Question | C1: CSV Row | D1: Article ID | E1: Article Title | F1: Cosine Similarity | G1: Ground Truth | H1: Relevant (GT) | I1: Predicted @ Threshold | J1: Outcome
A2: Q1 | B2: How is CBA using AI to improve software engineering productivity? | C2: 1 | D2: 99d3c240-a69d-471e-9754-bd53d542c01f | E2: Banks warn AI shopping agents could increase risk of scams, fraud and data privacy breaches | F2: 0.3027 | G2: =IF(COUNTIFS('Question-Article-Match'!$A:$A,A2,'Question-Article-Match'!$C:$C,C2,'Question-Article-Match'!$F:$F,"direct match")>0,"direct match",IF(COUNTIFS('Question-Article-Match'!$A:$A,A2,'Question-Article-Match'!$C:$C,C2,'Question-Article-Match'!$F:$F,"indirect match")>0,"indirect match","no match")) -> no match | H2: =IF(G2="no match",0,1) -> 0 | I2: =IF(F2>=$N$2,1,0) -> 0 | J2: =IF(AND(H2=1,I2=1),"TP",IF(AND(H2=0,I2=1),"FP",IF(H2=1,"FN","TN"))) -> TN | L2: Threshold (edit me) | N2: 0.35
A3: Q1 | B3: How is CBA using AI to improve software engineering productivity? | C3: 2 | D3: b1b83951-4c53-41ff-a55f-9a52d2b6570d | E3: Banks warn AI shopping agents outpace fraud protections | F3: 0.2825 | G3: =IF(COUNTIFS('Question-Article-Match'!$A:$A,A3,'Question-Article-Match'!$C:$C,C3,'Question-Article-Match'!$F:$F,"direct match")>0,"direct match",IF(COUNTIFS('Question-Article-Match'!$A:$A,A3,'Question-Article-Match'!$C:$C,C3,'Question-Article-Match'!$F:$F,"indirect match")>0,"indirect match","no match")) -> no match | H3: =IF(G3="no match",0,1) -> 0 | I3: =IF(F3>=$N$2,1,0) -> 0 | J3: =IF(AND(H3=1,I3=1),"TP",IF(AND(H3=0,I3=1),"FP",IF(H3=1,"FN","TN"))) -> TN
A4: Q1 | B4: How is CBA using AI to improve software engineering productivity? | C4: 3 | D4: d1b0bef8-6caa-4a64-88c9-3a0aa08b588b | E4: Interview: CBA AI chief on scaling A$400m in AI value with humans in loop | F4: 0.6111 | G4: =IF(COUNTIFS('Question-Article-Match'!$A:$A,A4,'Question-Article-Match'!$C:$C,C4,'Question-Article-Match'!$F:$F,"direct match")>0,"direct match",IF(COUNTIFS('Question-Article-Match'!$A:$A,A4,'Question-Article-Match'!$C:$C,C4,'Question-Article-Match'!$F:$F,"indirect match")>0,"indirect match","no match")) -> direct match | H4: =IF(G4="no match",0,1) -> 1 | I4: =IF(F4>=$N$2,1,0) -> 1 | J4: =IF(AND(H4=1,I4=1),"TP",IF(AND(H4=0,I4=1),"FP",IF(H4=1,"FN","TN"))) -> TP | L4: Threshold | M4: TP | N4: FP | O4: FN | P4: Precision | Q4: Recall | R4: F1 | S4: Direct recall | T4: Indirect recall
A5: Q1 | B5: How is CBA using AI to improve software engineering productivity? | C5: 4 | D5: c23b800e-0d81-4f22-b84c-948dcb872f02 | E5: Asian Stocks Choppy as Investors Weigh Pause in Bond Selloff | F5: 0.065 | G5: =IF(COUNTIFS('Question-Article-Match'!$A:$A,A5,'Question-Article-Match'!$C:$C,C5,'Question-Article-Match'!$F:$F,"direct match")>0,"direct match",IF(COUNTIFS('Question-Article-Match'!$A:$A,A5,'Question-Article-Match'!$C:$C,C5,'Question-Article-Match'!$F:$F,"indirect match")>0,"indirect match","no match")) -> no match | H5: =IF(G5="no match",0,1) -> 0 | I5: =IF(F5>=$N$2,1,0) -> 0 | J5: =IF(AND(H5=1,I5=1),"TP",IF(AND(H5=0,I5=1),"FP",IF(H5=1,"FN","TN"))) -> TN | L5: 0.2 | M5: =COUNTIFS($H$2:$H$337,1,$F$2:$F$337,">="&L5) -> 38 | N5: =COUNTIFS($H$2:$H$337,0,$F$2:$F$337,">="&L5) -> 163 | O5: =COUNTIFS($H$2:$H$337,1,$F$2:$F$337,"<"&L5) -> 0 | P5: =IF(M5+N5=0,0,M5/(M5+N5)) -> 0.18905473 | Q5: =IF(M5+O5=0,0,M5/(M5+O5)) -> 1 | R5: =IF(P5+Q5=0,0,2*P5*Q5/(P5+Q5)) -> 0.31799163 | S5: =COUNTIFS($G$2:$G$337,"direct match",$F$2:$F$337,">="&L5)/MAX(1,COUNTIF($G$2:$G$337,"direct match")) -> 1 | T5: =COUNTIFS($G$2:$G$337,"indirect match",$F$2:$F$337,">="&L5)/MAX(1,COUNTIF($G$2:$G$337,"indirect match")) -> 1
A6: Q1 | B6: How is CBA using AI to improve software engineering productivity? | C6: 5 | D6: 6192bccf-9d89-4bdf-b571-47e3e02b311d | E6: 3 Australian Dividend Stocks With At Least 3% Yield | F6: 0.1112 | G6: =IF(COUNTIFS('Question-Article-Match'!$A:$A,A6,'Question-Article-Match'!$C:$C,C6,'Question-Article-Match'!$F:$F,"direct match")>0,"direct match",IF(COUNTIFS('Question-Article-Match'!$A:$A,A6,'Question-Article-Match'!$C:$C,C6,'Question-Article-Match'!$F:$F,"indirect match")>0,"indirect match","no match")) -> no match | H6: =IF(G6="no match",0,1) -> 0 | I6: =IF(F6>=$N$2,1,0) -> 0 | J6: =IF(AND(H6=1,I6=1),"TP",IF(AND(H6=0,I6=1),"FP",IF(H6=1,"FN","TN"))) -> TN | L6: 0.25 | M6: =COUNTIFS($H$2:$H$337,1,$F$2:$F$337,">="&L6) -> 37 | N6: =COUNTIFS($H$2:$H$337,0,$F$2:$F$337,">="&L6) -> 110 | O6: =COUNTIFS($H$2:$H$337,1,$F$2:$F$337,"<"&L6) -> 1 | P6: =IF(M6+N6=0,0,M6/(M6+N6)) -> 0.25170068 | Q6: =IF(M6+O6=0,0,M6/(M6+O6)) -> 0.97368421 | R6: =IF(P6+Q6=0,0,2*P6*Q6/(P6+Q6)) -> 0.4 | S6: =COUNTIFS($G$2:$G$337,"direct match",$F$2:$F$337,">="&L6)/MAX(1,COUNTIF($G$2:$G$337,"direct match")) -> 1 | T6: =COUNTIFS($G$2:$G$337,"indirect match",$F$2:$F$337,">="&L6)/MAX(1,COUNTIF($G$2:$G$337,"indirect match")) -> 0.96153846
A7: Q1 | B7: How is CBA using AI to improve software engineering productivity? | C7: 6 | D7: c385b2b8-f8e0-4278-99be-f30dbd1d2167 | E7: 3 Australian Dividend Stocks Paying Over 5% While Cash Income Looks Less Certain | F7: 0.0768 | G7: =IF(COUNTIFS('Question-Article-Match'!$A:$A,A7,'Question-Article-Match'!$C:$C,C7,'Question-Article-Match'!$F:$F,"direct match")>0,"direct match",IF(COUNTIFS('Question-Article-Match'!$A:$A,A7,'Question-Article-Match'!$C:$C,C7,'Question-Article-Match'!$F:$F,"indirect match")>0,"indirect match","no match")) -> no match | H7: =IF(G7="no match",0,1) -> 0 | I7: =IF(F7>=$N$2,1,0) -> 0 | J7: =IF(AND(H7=1,I7=1),"TP",IF(AND(H7=0,I7=1),"FP",IF(H7=1,"FN","TN"))) -> TN | L7: 0.3 | M7: =COUNTIFS($H$2:$H$337,1,$F$2:$F$337,">="&L7) -> 37 | N7: =COUNTIFS($H$2:$H$337,0,$F$2:$F$337,">="&L7) -> 78 | O7: =COUNTIFS($H$2:$H$337,1,$F$2:$F$337,"<"&L7) -> 1 | P7: =IF(M7+N7=0,0,M7/(M7+N7)) -> 0.32173913 | Q7: =IF(M7+O7=0,0,M7/(M7+O7)) -> 0.97368421 | R7: =IF(P7+Q7=0,0,2*P7*Q7/(P7+Q7)) -> 0.48366013 | S7: =COUNTIFS($G$2:$G$337,"direct match",$F$2:$F$337,">="&L7)/MAX(1,COUNTIF($G$2:$G$337,"direct match")) -> 1 | T7: =COUNTIFS($G$2:$G$337,"indirect match",$F$2:$F$337,">="&L7)/MAX(1,COUNTIF($G$2:$G$337,"indirect match")) -> 0.96153846
A8: Q1 | B8: How is CBA using AI to improve software engineering productivity? | C8: 7 | D8: 3197f837-7d31-4fd0-9208-cca4c823c4f2 | E8: Three of Australia's four major banks forecast another rate hike this year | F8: 0.0345 | G8: =IF(COUNTIFS('Question-Article-Match'!$A:$A,A8,'Question-Article-Match'!$C:$C,C8,'Question-Article-Match'!$F:$F,"direct match")>0,"direct match",IF(COUNTIFS('Question-Article-Match'!$A:$A,A8,'Question-Article-Match'!$C:$C,C8,'Question-Article-Match'!$F:$F,"indirect match")>0,"indirect match","no match")) -> no match | H8: =IF(G8="no match",0,1) -> 0 | I8: =IF(F8>=$N$2,1,0) -> 0 | J8: =IF(AND(H8=1,I8=1),"TP",IF(AND(H8=0,I8=1),"FP",IF(H8=1,"FN","TN"))) -> TN | L8: 0.35 | M8: =COUNTIFS($H$2:$H$337,1,$F$2:$F$337,">="&L8) -> 33 | N8: =COUNTIFS($H$2:$H$337,0,$F$2:$F$337,">="&L8) -> 49 | O8: =COUNTIFS($H$2:$H$337,1,$F$2:$F$337,"<"&L8) -> 5 | P8: =IF(M8+N8=0,0,M8/(M8+N8)) -> 0.40243902 | Q8: =IF(M8+O8=0,0,M8/(M8+O8)) -> 0.86842105 | R8: =IF(P8+Q8=0,0,2*P8*Q8/(P8+Q8)) -> 0.55 | S8: =COUNTIFS($G$2:$G$337,"direct match",$F$2:$F$337,">="&L8)/MAX(1,COUNTIF($G$2:$G$337,"direct match")) -> 1 | T8: =COUNTIFS($G$2:$G$337,"indirect match",$F$2:$F$337,">="&L8)/MAX(1,COUNTIF($G$2:$G$337,"indirect match")) -> 0.80769231
A9: Q1 | B9: How is CBA using AI to improve software engineering productivity? | C9: 8 | D9: 8c255177-b931-4783-a1bf-9e2dacfa1b3c | E9: Commonwealth Bank Stock And 2 More Dividend Shares For Reliable Income | F9: 0.1111 | G9: =IF(COUNTIFS('Question-Article-Match'!$A:$A,A9,'Question-Article-Match'!$C:$C,C9,'Question-Article-Match'!$F:$F,"direct match")>0,"direct match",IF(COUNTIFS('Question-Article-Match'!$A:$A,A9,'Question-Article-Match'!$C:$C,C9,'Question-Article-Match'!$F:$F,"indirect match")>0,"indirect match","no match")) -> no match | H9: =IF(G9="no match",0,1) -> 0 | I9: =IF(F9>=$N$2,1,0) -> 0 | J9: =IF(AND(H9=1,I9=1),"TP",IF(AND(H9=0,I9=1),"FP",IF(H9=1,"FN","TN"))) -> TN | L9: 0.4 | M9: =COUNTIFS($H$2:$H$337,1,$F$2:$F$337,">="&L9) -> 30 | N9: =COUNTIFS($H$2:$H$337,0,$F$2:$F$337,">="&L9) -> 23 | O9: =COUNTIFS($H$2:$H$337,1,$F$2:$F$337,"<"&L9) -> 8 | P9: =IF(M9+N9=0,0,M9/(M9+N9)) -> 0.56603774 | Q9: =IF(M9+O9=0,0,M9/(M9+O9)) -> 0.78947368 | R9: =IF(P9+Q9=0,0,2*P9*Q9/(P9+Q9)) -> 0.65934066 | S9: =COUNTIFS($G$2:$G$337,"direct match",$F$2:$F$337,">="&L9)/MAX(1,COUNTIF($G$2:$G$337,"direct match")) -> 1 | T9: =COUNTIFS($G$2:$G$337,"indirect match",$F$2:$F$337,">="&L9)/MAX(1,COUNTIF($G$2:$G$337,"indirect match")) -> 0.69230769
A10: Q1 | B10: How is CBA using AI to improve software engineering productivity? | C10: 9 | D10: 413c847a-f31f-48e9-8aa3-215b13213f26 | E10: Commonwealth Bank unveils payout platform ahead of cheque exit | F10: -0.0179 | G10: =IF(COUNTIFS('Question-Article-Match'!$A:$A,A10,'Question-Article-Match'!$C:$C,C10,'Question-Article-Match'!$F:$F,"direct match")>0,"direct match",IF(COUNTIFS('Question-Article-Match'!$A:$A,A10,'Question-Article-Match'!$C:$C,C10,'Question-Article-Match'!$F:$F,"indirect match")>0,"indirect match","no match")) -> no match | H10: =IF(G10="no match",0,1) -> 0 | I10: =IF(F10>=$N$2,1,0) -> 0 | J10: =IF(AND(H10=1,I10=1),"TP",IF(AND(H10=0,I10=1),"FP",IF(H10=1,"FN","TN"))) -> TN | L10: 0.45 | M10: =COUNTIFS($H$2:$H$337,1,$F$2:$F$337,">="&L10) -> 24 | N10: =COUNTIFS($H$2:$H$337,0,$F$2:$F$337,">="&L10) -> 12 | O10: =COUNTIFS($H$2:$H$337,1,$F$2:$F$337,"<"&L10) -> 14 | P10: =IF(M10+N10=0,0,M10/(M10+N10)) -> 0.66666667 | Q10: =IF(M10+O10=0,0,M10/(M10+O10)) -> 0.63157895 | R10: =IF(P10+Q10=0,0,2*P10*Q10/(P10+Q10)) -> 0.64864865 | S10: =COUNTIFS($G$2:$G$337,"direct match",$F$2:$F$337,">="&L10)/MAX(1,COUNTIF($G$2:$G$337,"direct match")) -> 1 | T10: =COUNTIFS($G$2:$G$337,"indirect match",$F$2:$F$337,">="&L10)/MAX(1,COUNTIF($G$2:$G$337,"indirect match")) -> 0.46153846
A11: Q1 | B11: How is CBA using AI to improve software engineering productivity? | C11: 10 | D11: 686cdb0c-4e0e-4c16-82e8-cc5fb13cd2ca | E11: Australian bank investors brace for tough times as mortgage demand plummets | F11: 0.0277 | G11: =IF(COUNTIFS('Question-Article-Match'!$A:$A,A11,'Question-Article-Match'!$C:$C,C11,'Question-Article-Match'!$F:$F,"direct match")>0,"direct match",IF(COUNTIFS('Question-Article-Match'!$A:$A,A11,'Question-Article-Match'!$C:$C,C11,'Question-Article-Match'!$F:$F,"indirect match")>0,"indirect match","no match")) -> no match | H11: =IF(G11="no match",0,1) -> 0 | I11: =IF(F11>=$N$2,1,0) -> 0 | J11: =IF(AND(H11=1,I11=1),"TP",IF(AND(H11=0,I11=1),"FP",IF(H11=1,"FN","TN"))) -> TN | L11: 0.5 | M11: =COUNTIFS($H$2:$H$337,1,$F$2:$F$337,">="&L11) -> 20 | N11: =COUNTIFS($H$2:$H$337,0,$F$2:$F$337,">="&L11) -> 8 | O11: =COUNTIFS($H$2:$H$337,1,$F$2:$F$337,"<"&L11) -> 18 | P11: =IF(M11+N11=0,0,M11/(M11+N11)) -> 0.71428571 | Q11: =IF(M11+O11=0,0,M11/(M11+O11)) -> 0.52631579 | R11: =IF(P11+Q11=0,0,2*P11*Q11/(P11+Q11)) -> 0.60606061 | S11: =COUNTIFS($G$2:$G$337,"direct match",$F$2:$F$337,">="&L11)/MAX(1,COUNTIF($G$2:$G$337,"direct match")) -> 1 | T11: =COUNTIFS($G$2:$G$337,"indirect match",$F$2:$F$337,">="&L11)/MAX(1,COUNTIF($G$2:$G$337,"indirect match")) -> 0.30769231
A12: Q1 | B12: How is CBA using AI to improve software engineering productivity? | C12: 11 | D12: 01468167-f750-4b79-b8c8-2edf85711375 | E12: LGT reports 17% rise in H1 profit as assets reach record level | F12: 0.1159 | G12: =IF(COUNTIFS('Question-Article-Match'!$A:$A,A12,'Question-Article-Match'!$C:$C,C12,'Question-Article-Match'!$F:$F,"direct match")>0,"direct match",IF(COUNTIFS('Question-Article-Match'!$A:$A,A12,'Question-Article-Match'!$C:$C,C12,'Question-Article-Match'!$F:$F,"indirect match")>0,"indirect match","no match")) -> no match | H12: =IF(G12="no match",0,1) -> 0 | I12: =IF(F12>=$N$2,1,0) -> 0 | J12: =IF(AND(H12=1,I12=1),"TP",IF(AND(H12=0,I12=1),"FP",IF(H12=1,"FN","TN"))) -> TN | L12: 0.55 | M12: =COUNTIFS($H$2:$H$337,1,$F$2:$F$337,">="&L12) -> 14 | N12: =COUNTIFS($H$2:$H$337,0,$F$2:$F$337,">="&L12) -> 5 | O12: =COUNTIFS($H$2:$H$337,1,$F$2:$F$337,"<"&L12) -> 24 | P12: =IF(M12+N12=0,0,M12/(M12+N12)) -> 0.73684211 | Q12: =IF(M12+O12=0,0,M12/(M12+O12)) -> 0.36842105 | R12: =IF(P12+Q12=0,0,2*P12*Q12/(P12+Q12)) -> 0.49122807 | S12: =COUNTIFS($G$2:$G$337,"direct match",$F$2:$F$337,">="&L12)/MAX(1,COUNTIF($G$2:$G$337,"direct match")) -> 0.83333333 | T12: =COUNTIFS($G$2:$G$337,"indirect match",$F$2:$F$337,">="&L12)/MAX(1,COUNTIF($G$2:$G$337,"indirect match")) -> 0.15384615
A13: Q1 | B13: How is CBA using AI to improve software engineering productivity? | C13: 12 | D13: 5471b7ec-a7a3-4b6f-9ed9-1077daa933df | E13: Fast Money Bets on November RBA Hike in Fight Against Inflation | F13: 0.1225 | G13: =IF(COUNTIFS('Question-Article-Match'!$A:$A,A13,'Question-Article-Match'!$C:$C,C13,'Question-Article-Match'!$F:$F,"direct match")>0,"direct match",IF(COUNTIFS('Question-Article-Match'!$A:$A,A13,'Question-Article-Match'!$C:$C,C13,'Question-Article-Match'!$F:$F,"indirect match")>0,"indirect match","no match")) -> no match | H13: =IF(G13="no match",0,1) -> 0 | I13: =IF(F13>=$N$2,1,0) -> 0 | J13: =IF(AND(H13=1,I13=1),"TP",IF(AND(H13=0,I13=1),"FP",IF(H13=1,"FN","TN"))) -> TN | L13: 0.6 | M13: =COUNTIFS($H$2:$H$337,1,$F$2:$F$337,">="&L13) -> 8 | N13: =COUNTIFS($H$2:$H$337,0,$F$2:$F$337,">="&L13) -> 0 | O13: =COUNTIFS($H$2:$H$337,1,$F$2:$F$337,"<"&L13) -> 30 | P13: =IF(M13+N13=0,0,M13/(M13+N13)) -> 1 | Q13: =IF(M13+O13=0,0,M13/(M13+O13)) -> 0.21052632 | R13: =IF(P13+Q13=0,0,2*P13*Q13/(P13+Q13)) -> 0.34782609 | S13: =COUNTIFS($G$2:$G$337,"direct match",$F$2:$F$337,">="&L13)/MAX(1,COUNTIF($G$2:$G$337,"direct match")) -> 0.66666667 | T13: =COUNTIFS($G$2:$G$337,"indirect match",$F$2:$F$337,">="&L13)/MAX(1,COUNTIF($G$2:$G$337,"indirect match")) -> 0
A14: Q1 | B14: How is CBA using AI to improve software engineering productivity? | C14: 13 | D14: 5332bf57-f144-4f09-9a22-0048374de7a6 | E14: Tencent AI Spending Key After Magnificent 7 Rout | F14: 0.2395 | G14: =IF(COUNTIFS('Question-Article-Match'!$A:$A,A14,'Question-Article-Match'!$C:$C,C14,'Question-Article-Match'!$F:$F,"direct match")>0,"direct match",IF(COUNTIFS('Question-Article-Match'!$A:$A,A14,'Question-Article-Match'!$C:$C,C14,'Question-Article-Match'!$F:$F,"indirect match")>0,"indirect match","no match")) -> no match | H14: =IF(G14="no match",0,1) -> 0 | I14: =IF(F14>=$N$2,1,0) -> 0 | J14: =IF(AND(H14=1,I14=1),"TP",IF(AND(H14=0,I14=1),"FP",IF(H14=1,"FN","TN"))) -> TN
A15: Q1 | B15: How is CBA using AI to improve software engineering productivity? | C15: 14 | D15: 6b7cca15-b540-451a-8034-b1fc4704f805 | E15: AI Is Replacing Customer Service Jobs at CBA, Microsoft, Uber | F15: 0.5526 | G15: =IF(COUNTIFS('Question-Article-Match'!$A:$A,A15,'Question-Article-Match'!$C:$C,C15,'Question-Article-Match'!$F:$F,"direct match")>0,"direct match",IF(COUNTIFS('Question-Article-Match'!$A:$A,A15,'Question-Article-Match'!$C:$C,C15,'Question-Article-Match'!$F:$F,"indirect match")>0,"indirect match","no match")) -> indirect match | H15: =IF(G15="no match",0,1) -> 1 | I15: =IF(F15>=$N$2,1,0) -> 1 | J15: =IF(AND(H15=1,I15=1),"TP",IF(AND(H15=0,I15=1),"FP",IF(H15=1,"FN","TN"))) -> TP
A16: Q1 | B16: How is CBA using AI to improve software engineering productivity? | C16: 15 | D16: c4a7e0e3-afd4-4f96-a328-a4fc62d9dce2 | E16: CommSec Eyes More U.S. IPOs After 28,000 SpaceX Applications | F16: 0.134 | G16: =IF(COUNTIFS('Question-Article-Match'!$A:$A,A16,'Question-Article-Match'!$C:$C,C16,'Question-Article-Match'!$F:$F,"direct match")>0,"direct match",IF(COUNTIFS('Question-Article-Match'!$A:$A,A16,'Question-Article-Match'!$C:$C,C16,'Question-Article-Match'!$F:$F,"indirect match")>0,"indirect match","no match")) -> no match | H16: =IF(G16="no match",0,1) -> 0 | I16: =IF(F16>=$N$2,1,0) -> 0 | J16: =IF(AND(H16=1,I16=1),"TP",IF(AND(H16=0,I16=1),"FP",IF(H16=1,"FN","TN"))) -> TN
A17: Q1 | B17: How is CBA using AI to improve software engineering productivity? | C17: 16 | D17: a8b21a0e-aa2c-42e8-8cfb-c7479fd1d8e3 | E17: archTIS extends A$4 million CBA facility to support contract execution and growth | F17: 0.2923 | G17: =IF(COUNTIFS('Question-Article-Match'!$A:$A,A17,'Question-Article-Match'!$C:$C,C17,'Question-Article-Match'!$F:$F,"direct match")>0,"direct match",IF(COUNTIFS('Question-Article-Match'!$A:$A,A17,'Question-Article-Match'!$C:$C,C17,'Question-Article-Match'!$F:$F,"indirect match")>0,"indirect match","no match")) -> no match | H17: =IF(G17="no match",0,1) -> 0 | I17: =IF(F17>=$N$2,1,0) -> 0 | J17: =IF(AND(H17=1,I17=1),"TP",IF(AND(H17=0,I17=1),"FP",IF(H17=1,"FN","TN"))) -> TN
A18: Q1 | B18: How is CBA using AI to improve software engineering productivity? | C18: 17 | D18: 273b4c77-4742-4732-8603-9f737578c99c | E18: Companies rehire workers laid off for AI as automation falls short | F18: 0.3574 | G18: =IF(COUNTIFS('Question-Article-Match'!$A:$A,A18,'Question-Article-Match'!$C:$C,C18,'Question-Article-Match'!$F:$F,"direct match")>0,"direct match",IF(COUNTIFS('Question-Article-Match'!$A:$A,A18,'Question-Article-Match'!$C:$C,C18,'Question-Article-Match'!$F:$F,"indirect match")>0,"indirect match","no match")) -> no match | H18: =IF(G18="no match",0,1) -> 0 | I18: =IF(F18>=$N$2,1,0) -> 1 | J18: =IF(AND(H18=1,I18=1),"TP",IF(AND(H18=0,I18=1),"FP",IF(H18=1,"FN","TN"))) -> FP
A19: Q1 | B19: How is CBA using AI to improve software engineering productivity? | C19: 18 | D19: b68a2d6d-73de-419c-b598-7ce0a1052836 | E19: Commonwealth Bank of Australia appoints new CIO, CTO to boost technology, AI strategy | F19: 0.3646 | G19: =IF(COUNTIFS('Question-Article-Match'!$A:$A,A19,'Question-Article-Match'!$C:$C,C19,'Question-Article-Match'!$F:$F,"direct match")>0,"direct match",IF(COUNTIFS('Question-Article-Match'!$A:$A,A19,'Question-Article-Match'!$C:$C,C19,'Question-Article-Match'!$F:$F,"indirect match")>0,"indirect match","no match")) -> indirect match | H19: =IF(G19="no match",0,1) -> 1 | I19: =IF(F19>=$N$2,1,0) -> 1 | J19: =IF(AND(H19=1,I19=1),"TP",IF(AND(H19=0,I19=1),"FP",IF(H19=1,"FN","TN"))) -> TP
A20: Q1 | B20: How is CBA using AI to improve software engineering productivity? | C20: 19 | D20: f6a03202-fdda-4b58-97b6-a48e3659827b | E20: Did Profit Uptick and RBA Countdown Just Shift Commonwealth Bank's (ASX:CBA) Investment Narrative? | F20: 0.2526 | G20: =IF(COUNTIFS('Question-Article-Match'!$A:$A,A20,'Question-Article-Match'!$C:$C,C20,'Question-Article-Match'!$F:$F,"direct match")>0,"direct match",IF(COUNTIFS('Question-Article-Match'!$A:$A,A20,'Question-Article-Match'!$C:$C,C20,'Question-Article-Match'!$F:$F,"indirect match")>0,"indirect match","no match")) -> no match | H20: =IF(G20="no match",0,1) -> 0 | I20: =IF(F20>=$N$2,1,0) -> 0 | J20: =IF(AND(H20=1,I20=1),"TP",IF(AND(H20=0,I20=1),"FP",IF(H20=1,"FN","TN"))) -> TN
A21: Q1 | B21: How is CBA using AI to improve software engineering productivity? | C21: 20 | D21: 2b3ee594-b9e3-4c7b-9721-471bf15554f4 | E21: USO, UCO Dip As Oil Prices Slide After Trump Declares Iran Deal 'Complete' — Analyst Sees $80 Brent By Year-End | F21: 0.1037 | G21: =IF(COUNTIFS('Question-Article-Match'!$A:$A,A21,'Question-Article-Match'!$C:$C,C21,'Question-Article-Match'!$F:$F,"direct match")>0,"direct match",IF(COUNTIFS('Question-Article-Match'!$A:$A,A21,'Question-Article-Match'!$C:$C,C21,'Question-Article-Match'!$F:$F,"indirect match")>0,"indirect match","no match")) -> no match | H21: =IF(G21="no match",0,1) -> 0 | I21: =IF(F21>=$N$2,1,0) -> 0 | J21: =IF(AND(H21=1,I21=1),"TP",IF(AND(H21=0,I21=1),"FP",IF(H21=1,"FN","TN"))) -> TN
A22: Q1 | B22: How is CBA using AI to improve software engineering productivity? | C22: 21 | D22: 69dbc761-0547-45ff-9908-81fbc4ec506d | E22: Billionaire Sam Altman Says OpenAI Was ‘Pretty Wrong’ About AI Jobs, But Goldman Sachs Warns AI is Still Wiping Out 11,000 Jobs Per Month | F22: 0.3273 | G22: =IF(COUNTIFS('Question-Article-Match'!$A:$A,A22,'Question-Article-Match'!$C:$C,C22,'Question-Article-Match'!$F:$F,"direct match")>0,"direct match",IF(COUNTIFS('Question-Article-Match'!$A:$A,A22,'Question-Article-Match'!$C:$C,C22,'Question-Article-Match'!$F:$F,"indirect match")>0,"indirect match","no match")) -> no match | H22: =IF(G22="no match",0,1) -> 0 | I22: =IF(F22>=$N$2,1,0) -> 0 | J22: =IF(AND(H22=1,I22=1),"TP",IF(AND(H22=0,I22=1),"FP",IF(H22=1,"FN","TN"))) -> TN
A23: Q2 | B23: What technology leadership changes has CBA made to support its AI strategy? | C23: 1 | D23: 99d3c240-a69d-471e-9754-bd53d542c01f | E23: Banks warn AI shopping agents could increase risk of scams, fraud and data privacy breaches | F23: 0.2918 | G23: =IF(COUNTIFS('Question-Article-Match'!$A:$A,A23,'Question-Article-Match'!$C:$C,C23,'Question-Article-Match'!$F:$F,"direct match")>0,"direct match",IF(COUNTIFS('Question-Article-Match'!$A:$A,A23,'Question-Article-Match'!$C:$C,C23,'Question-Article-Match'!$F:$F,"indirect match")>0,"indirect match","no match")) -> no match | H23: =IF(G23="no match",0,1) -> 0 | I23: =IF(F23>=$N$2,1,0) -> 0 | J23: =IF(AND(H23=1,I23=1),"TP",IF(AND(H23=0,I23=1),"FP",IF(H23=1,"FN","TN"))) -> TN
A24: Q2 | B24: What technology leadership changes has CBA made to support its AI strategy? | C24: 2 | D24: b1b83951-4c53-41ff-a55f-9a52d2b6570d | E24: Banks warn AI shopping agents outpace fraud protections | F24: 0.3531 | G24: =IF(COUNTIFS('Question-Article-Match'!$A:$A,A24,'Question-Article-Match'!$C:$C,C24,'Question-Article-Match'!$F:$F,"direct match")>0,"direct match",IF(COUNTIFS('Question-Article-Match'!$A:$A,A24,'Question-Article-Match'!$C:$C,C24,'Question-Article-Match'!$F:$F,"indirect match")>0,"indirect match","no match")) -> no match | H24: =IF(G24="no match",0,1) -> 0 | I24: =IF(F24>=$N$2,1,0) -> 1 | J24: =IF(AND(H24=1,I24=1),"TP",IF(AND(H24=0,I24=1),"FP",IF(H24=1,"FN","TN"))) -> FP
A25: Q2 | B25: What technology leadership changes has CBA made to support its AI strategy? | C25: 3 | D25: d1b0bef8-6caa-4a64-88c9-3a0aa08b588b | E25: Interview: CBA AI chief on scaling A$400m in AI value with humans in loop | F25: 0.5889 | G25: =IF(COUNTIFS('Question-Article-Match'!$A:$A,A25,'Question-Article-Match'!$C:$C,C25,'Question-Article-Match'!$F:$F,"direct match")>0,"direct match",IF(COUNTIFS('Question-Article-Match'!$A:$A,A25,'Question-Article-Match'!$C:$C,C25,'Question-Article-Match'!$F:$F,"indirect match")>0,"indirect match","no match")) -> indirect match | H25: =IF(G25="no match",0,1) -> 1 | I25: =IF(F25>=$N$2,1,0) -> 1 | J25: =IF(AND(H25=1,I25=1),"TP",IF(AND(H25=0,I25=1),"FP",IF(H25=1,"FN","TN"))) -> TP
... A337: H4 | B337: How is CBA generating A$400 million in value from its AI initiatives? | C337: 21 | D337: 69dbc761-0547-45ff-9908-81fbc4ec506d | E337: Billionaire Sam Altman Says OpenAI Was ‘Pretty Wrong’ About AI Jobs, But Goldman Sachs Warns AI is Still Wiping Out 11,000 Jobs Per Month | F337: 0.3404 | G337: =IF(COUNTIFS('Question-Article-Match'!$A:$A,A337,'Question-Article-Match'!$C:$C,C337,'Question-Article-Match'!$F:$F,"direct match")>0,"direct match",IF(COUNTIFS('Question-Article-Match'!$A:$A,A337,'Question-Article-Match'!$C:$C,C337,'Question-Article-Match'!$F:$F,"indirect match")>0,"indirect match","no match")) -> no match | H337: =IF(G337="no match",0,1) -> 0 | I337: =IF(F337>=$N$2,1,0) -> 0 | J337: =IF(AND(H337=1,I337=1),"TP",IF(AND(H337=0,I337=1),"FP",IF(H337=1,"FN","TN"))) -> TN

Sheet Keyword Search Analysis
A1: Question ID | B1: Question | C1: Rank | D1: Article ID | E1: Article Title | F1: Cosine Similarity | G1: Ground Truth | H1: Below Threshold
A2: H1 | B2: What new payout platform has CBA introduced to replace cheque-based payments? | C2: 1 | D2: 413c847a-f31f-48e9-8aa3-215b13213f26 | E2: Commonwealth Bank unveils payout platform ahead of cheque exit | F2: 0.6164 | G2: =IF(COUNTIFS('Question-Article-Match'!$A:$A,A2,'Question-Article-Match'!$C:$C,C2,'Question-Article-Match'!$F:$F,"direct match")>0,"direct match",IF(COUNTIFS('Question-Article-Match'!$A:$A,A2,'Question-Article-Match'!$C:$C,C2,'Question-Article-Match'!$F:$F,"indirect match")>0,"indirect match","no match")) -> no match
A3: H1 | B3: What new payout platform has CBA introduced to replace cheque-based payments? | C3: 2 | D3: a8b21a0e-aa2c-42e8-8cfb-c7479fd1d8e3 | E3: archTIS extends A$4 million CBA facility to support contract execution and growth | F3: 0.3988 | G3: =IF(COUNTIFS('Question-Article-Match'!$A:$A,A3,'Question-Article-Match'!$C:$C,C3,'Question-Article-Match'!$F:$F,"direct match")>0,"direct match",IF(COUNTIFS('Question-Article-Match'!$A:$A,A3,'Question-Article-Match'!$C:$C,C3,'Question-Article-Match'!$F:$F,"indirect match")>0,"indirect match","no match")) -> no match
A4: H1 | B4: What new payout platform has CBA introduced to replace cheque-based payments? | C4: 3 | D4: f6a03202-fdda-4b58-97b6-a48e3659827b | E4: Did Profit Uptick and RBA Countdown Just Shift Commonwealth Bank's (ASX:CBA) Investment Narrative? | F4: 0.3678 | G4: =IF(COUNTIFS('Question-Article-Match'!$A:$A,A4,'Question-Article-Match'!$C:$C,C4,'Question-Article-Match'!$F:$F,"direct match")>0,"direct match",IF(COUNTIFS('Question-Article-Match'!$A:$A,A4,'Question-Article-Match'!$C:$C,C4,'Question-Article-Match'!$F:$F,"indirect match")>0,"indirect match","no match")) -> no match
A5: H1 | B5: What new payout platform has CBA introduced to replace cheque-based payments? | C5: 4 | D5: 6b7cca15-b540-451a-8034-b1fc4704f805 | E5: AI Is Replacing Customer Service Jobs at CBA, Microsoft, Uber | F5: 0.3396 | G5: =IF(COUNTIFS('Question-Article-Match'!$A:$A,A5,'Question-Article-Match'!$C:$C,C5,'Question-Article-Match'!$F:$F,"direct match")>0,"direct match",IF(COUNTIFS('Question-Article-Match'!$A:$A,A5,'Question-Article-Match'!$C:$C,C5,'Question-Article-Match'!$F:$F,"indirect match")>0,"indirect match","no match")) -> no match
A6: H1 | B6: What new payout platform has CBA introduced to replace cheque-based payments? | C6: 5 | D6: b1b83951-4c53-41ff-a55f-9a52d2b6570d | E6: Banks warn AI shopping agents outpace fraud protections | F6: 0.3122 | G6: =IF(COUNTIFS('Question-Article-Match'!$A:$A,A6,'Question-Article-Match'!$C:$C,C6,'Question-Article-Match'!$F:$F,"direct match")>0,"direct match",IF(COUNTIFS('Question-Article-Match'!$A:$A,A6,'Question-Article-Match'!$C:$C,C6,'Question-Article-Match'!$F:$F,"indirect match")>0,"indirect match","no match")) -> no match
A7: H1 | B7: What new payout platform has CBA introduced to replace cheque-based payments? | C7: 6 | D7: 5471b7ec-a7a3-4b6f-9ed9-1077daa933df | E7: Fast Money Bets on November RBA Hike in Fight Against Inflation | F7: 0.3038 | G7: =IF(COUNTIFS('Question-Article-Match'!$A:$A,A7,'Question-Article-Match'!$C:$C,C7,'Question-Article-Match'!$F:$F,"direct match")>0,"direct match",IF(COUNTIFS('Question-Article-Match'!$A:$A,A7,'Question-Article-Match'!$C:$C,C7,'Question-Article-Match'!$F:$F,"indirect match")>0,"indirect match","no match")) -> no match
A8: H1 | B8: What new payout platform has CBA introduced to replace cheque-based payments? | C8: 7 | D8: 99d3c240-a69d-471e-9754-bd53d542c01f | E8: Banks warn AI shopping agents could increase risk of scams, fraud and data privacy breaches | F8: 0.2887 | G8: =IF(COUNTIFS('Question-Article-Match'!$A:$A,A8,'Question-Article-Match'!$C:$C,C8,'Question-Article-Match'!$F:$F,"direct match")>0,"direct match",IF(COUNTIFS('Question-Article-Match'!$A:$A,A8,'Question-Article-Match'!$C:$C,C8,'Question-Article-Match'!$F:$F,"indirect match")>0,"indirect match","no match")) -> no match
A9: H1 | B9: What new payout platform has CBA introduced to replace cheque-based payments? | C9: 8 | D9: b68a2d6d-73de-419c-b598-7ce0a1052836 | E9: Commonwealth Bank of Australia appoints new CIO, CTO to boost technology, AI strategy | F9: 0.2887 | G9: =IF(COUNTIFS('Question-Article-Match'!$A:$A,A9,'Question-Article-Match'!$C:$C,C9,'Question-Article-Match'!$F:$F,"direct match")>0,"direct match",IF(COUNTIFS('Question-Article-Match'!$A:$A,A9,'Question-Article-Match'!$C:$C,C9,'Question-Article-Match'!$F:$F,"indirect match")>0,"indirect match","no match")) -> no match
A10: H1 | B10: What new payout platform has CBA introduced to replace cheque-based payments? | C10: 9 | D10: d1b0bef8-6caa-4a64-88c9-3a0aa08b588b | E10: Interview: CBA AI chief on scaling A$400m in AI value with humans in loop | F10: 0.2762 | G10: =IF(COUNTIFS('Question-Article-Match'!$A:$A,A10,'Question-Article-Match'!$C:$C,C10,'Question-Article-Match'!$F:$F,"direct match")>0,"direct match",IF(COUNTIFS('Question-Article-Match'!$A:$A,A10,'Question-Article-Match'!$C:$C,C10,'Question-Article-Match'!$F:$F,"indirect match")>0,"indirect match","no match")) -> direct match
A11: H1 | B11: What new payout platform has CBA introduced to replace cheque-based payments? | C11: 10 | D11: c385b2b8-f8e0-4278-99be-f30dbd1d2167 | E11: 3 Australian Dividend Stocks Paying Over 5% While Cash Income Looks Less Certain | F11: 0.2701 | G11: =IF(COUNTIFS('Question-Article-Match'!$A:$A,A11,'Question-Article-Match'!$C:$C,C11,'Question-Article-Match'!$F:$F,"direct match")>0,"direct match",IF(COUNTIFS('Question-Article-Match'!$A:$A,A11,'Question-Article-Match'!$C:$C,C11,'Question-Article-Match'!$F:$F,"indirect match")>0,"indirect match","no match")) -> no match
A12: H2 | B12: How has CBA supported archTIS with a A$4 million financing facility? | C12: 1 | D12: a8b21a0e-aa2c-42e8-8cfb-c7479fd1d8e3 | E12: archTIS extends A$4 million CBA facility to support contract execution and growth | F12: 0.7406 | G12: =IF(COUNTIFS('Question-Article-Match'!$A:$A,A12,'Question-Article-Match'!$C:$C,C12,'Question-Article-Match'!$F:$F,"direct match")>0,"direct match",IF(COUNTIFS('Question-Article-Match'!$A:$A,A12,'Question-Article-Match'!$C:$C,C12,'Question-Article-Match'!$F:$F,"indirect match")>0,"indirect match","no match")) -> no match
A13: H2 | B13: How has CBA supported archTIS with a A$4 million financing facility? | C13: 2 | D13: f6a03202-fdda-4b58-97b6-a48e3659827b | E13: Did Profit Uptick and RBA Countdown Just Shift Commonwealth Bank's (ASX:CBA) Investment Narrative? | F13: 0.4257 | G13: =IF(COUNTIFS('Question-Article-Match'!$A:$A,A13,'Question-Article-Match'!$C:$C,C13,'Question-Article-Match'!$F:$F,"direct match")>0,"direct match",IF(COUNTIFS('Question-Article-Match'!$A:$A,A13,'Question-Article-Match'!$C:$C,C13,'Question-Article-Match'!$F:$F,"indirect match")>0,"indirect match","no match")) -> no match
... A41: H4 | B41: How is CBA generating A$400 million in value from its AI initiatives? | C41: 10 | D41: 5471b7ec-a7a3-4b6f-9ed9-1077daa933df | E41: Fast Money Bets on November RBA Hike in Fight Against Inflation | F41: 0.2697 | G41: =IF(COUNTIFS('Question-Article-Match'!$A:$A,A41,'Question-Article-Match'!$C:$C,C41,'Question-Article-Match'!$F:$F,"direct match")>0,"direct match",IF(COUNTIFS('Question-Article-Match'!$A:$A,A41,'Question-Article-Match'!$C:$C,C41,'Question-Article-Match'!$F:$F,"indirect match")>0,"indirect match","no match")) -> no match

Sheet Lexical
A1: Question ID | B1: Question | C1: CSV Row | D1: Article ID | E1: Article Title | F1: Lexical Score (ts_rank_cd) | G1: Rank in Question | H1: Ground Truth
A2: Q1 | B2: How is CBA using AI to improve software engineering productivity? | C2: 3 | D2: d1b0bef8-6caa-4a64-88c9-3a0aa08b588b | E2: Interview: CBA AI chief on scaling A$400m in AI value with humans in loop | F2: 0.8 | G2: 1 | H2: =IF(COUNTIFS('Question-Article-Match'!$A:$A,A2,'Question-Article-Match'!$C:$C,C2,'Question-Article-Match'!$F:$F,"direct match")>0,"direct match",IF(COUNTIFS('Question-Article-Match'!$A:$A,A2,'Question-Article-Match'!$C:$C,C2,'Question-Article-Match'!$F:$F,"indirect match")>0,"indirect match","no match")) -> direct match
A3: Q1 | B3: How is CBA using AI to improve software engineering productivity? | C3: 16 | D3: a8b21a0e-aa2c-42e8-8cfb-c7479fd1d8e3 | E3: archTIS extends A$4 million CBA facility to support contract execution and growth | F3: 0.3 | G3: 2 | H3: =IF(COUNTIFS('Question-Article-Match'!$A:$A,A3,'Question-Article-Match'!$C:$C,C3,'Question-Article-Match'!$F:$F,"direct match")>0,"direct match",IF(COUNTIFS('Question-Article-Match'!$A:$A,A3,'Question-Article-Match'!$C:$C,C3,'Question-Article-Match'!$F:$F,"indirect match")>0,"indirect match","no match")) -> no match
A4: Q1 | B4: How is CBA using AI to improve software engineering productivity? | C4: 21 | D4: 69dbc761-0547-45ff-9908-81fbc4ec506d | E4: Billionaire Sam Altman Says OpenAI Was ‘Pretty Wrong’ About AI Jobs, But Goldman Sachs Warns AI is Still Wiping Out 11,000 Jobs Per Month | F4: 0.2 | G4: 3 | H4: =IF(COUNTIFS('Question-Article-Match'!$A:$A,A4,'Question-Article-Match'!$C:$C,C4,'Question-Article-Match'!$F:$F,"direct match")>0,"direct match",IF(COUNTIFS('Question-Article-Match'!$A:$A,A4,'Question-Article-Match'!$C:$C,C4,'Question-Article-Match'!$F:$F,"indirect match")>0,"indirect match","no match")) -> no match
A5: Q1 | B5: How is CBA using AI to improve software engineering productivity? | C5: 14 | D5: 6b7cca15-b540-451a-8034-b1fc4704f805 | E5: AI Is Replacing Customer Service Jobs at CBA, Microsoft, Uber | F5: 0.2 | G5: 4 | H5: =IF(COUNTIFS('Question-Article-Match'!$A:$A,A5,'Question-Article-Match'!$C:$C,C5,'Question-Article-Match'!$F:$F,"direct match")>0,"direct match",IF(COUNTIFS('Question-Article-Match'!$A:$A,A5,'Question-Article-Match'!$C:$C,C5,'Question-Article-Match'!$F:$F,"indirect match")>0,"indirect match","no match")) -> indirect match
A6: Q1 | B6: How is CBA using AI to improve software engineering productivity? | C6: 1 | D6: 99d3c240-a69d-471e-9754-bd53d542c01f | E6: Banks warn AI shopping agents could increase risk of scams, fraud and data privacy breaches | F6: 0.2 | G6: 5 | H6: =IF(COUNTIFS('Question-Article-Match'!$A:$A,A6,'Question-Article-Match'!$C:$C,C6,'Question-Article-Match'!$F:$F,"direct match")>0,"direct match",IF(COUNTIFS('Question-Article-Match'!$A:$A,A6,'Question-Article-Match'!$C:$C,C6,'Question-Article-Match'!$F:$F,"indirect match")>0,"indirect match","no match")) -> no match
A7: Q1 | B7: How is CBA using AI to improve software engineering productivity? | C7: 2 | D7: b1b83951-4c53-41ff-a55f-9a52d2b6570d | E7: Banks warn AI shopping agents outpace fraud protections | F7: 0.2 | G7: 6 | H7: =IF(COUNTIFS('Question-Article-Match'!$A:$A,A7,'Question-Article-Match'!$C:$C,C7,'Question-Article-Match'!$F:$F,"direct match")>0,"direct match",IF(COUNTIFS('Question-Article-Match'!$A:$A,A7,'Question-Article-Match'!$C:$C,C7,'Question-Article-Match'!$F:$F,"indirect match")>0,"indirect match","no match")) -> no match
A8: Q1 | B8: How is CBA using AI to improve software engineering productivity? | C8: 17 | D8: 273b4c77-4742-4732-8603-9f737578c99c | E8: Companies rehire workers laid off for AI as automation falls short | F8: 0.1 | G8: 7 | H8: =IF(COUNTIFS('Question-Article-Match'!$A:$A,A8,'Question-Article-Match'!$C:$C,C8,'Question-Article-Match'!$F:$F,"direct match")>0,"direct match",IF(COUNTIFS('Question-Article-Match'!$A:$A,A8,'Question-Article-Match'!$C:$C,C8,'Question-Article-Match'!$F:$F,"indirect match")>0,"indirect match","no match")) -> no match
A9: Q1 | B9: How is CBA using AI to improve software engineering productivity? | C9: 13 | D9: 5332bf57-f144-4f09-9a22-0048374de7a6 | E9: Tencent AI Spending Key After Magnificent 7 Rout | F9: 0.1 | G9: 8 | H9: =IF(COUNTIFS('Question-Article-Match'!$A:$A,A9,'Question-Article-Match'!$C:$C,C9,'Question-Article-Match'!$F:$F,"direct match")>0,"direct match",IF(COUNTIFS('Question-Article-Match'!$A:$A,A9,'Question-Article-Match'!$C:$C,C9,'Question-Article-Match'!$F:$F,"indirect match")>0,"indirect match","no match")) -> no match
A10: Q1 | B10: How is CBA using AI to improve software engineering productivity? | C10: 18 | D10: b68a2d6d-73de-419c-b598-7ce0a1052836 | E10: Commonwealth Bank of Australia appoints new CIO, CTO to boost technology, AI strategy | F10: 0.1 | G10: 9 | H10: =IF(COUNTIFS('Question-Article-Match'!$A:$A,A10,'Question-Article-Match'!$C:$C,C10,'Question-Article-Match'!$F:$F,"direct match")>0,"direct match",IF(COUNTIFS('Question-Article-Match'!$A:$A,A10,'Question-Article-Match'!$C:$C,C10,'Question-Article-Match'!$F:$F,"indirect match")>0,"indirect match","no match")) -> indirect match
A11: Q1 | B11: How is CBA using AI to improve software engineering productivity? | C11: 19 | D11: f6a03202-fdda-4b58-97b6-a48e3659827b | E11: Did Profit Uptick and RBA Countdown Just Shift Commonwealth Bank's (ASX:CBA) Investment Narrative? | F11: 0.1 | G11: 10 | H11: =IF(COUNTIFS('Question-Article-Match'!$A:$A,A11,'Question-Article-Match'!$C:$C,C11,'Question-Article-Match'!$F:$F,"direct match")>0,"direct match",IF(COUNTIFS('Question-Article-Match'!$A:$A,A11,'Question-Article-Match'!$C:$C,C11,'Question-Article-Match'!$F:$F,"indirect match")>0,"indirect match","no match")) -> no match
A12: Q1 | B12: How is CBA using AI to improve software engineering productivity? | C12: 11 | D12: 01468167-f750-4b79-b8c8-2edf85711375 | E12: LGT reports 17% rise in H1 profit as assets reach record level | F12: 0 | G12: 11 | H12: =IF(COUNTIFS('Question-Article-Match'!$A:$A,A12,'Question-Article-Match'!$C:$C,C12,'Question-Article-Match'!$F:$F,"direct match")>0,"direct match",IF(COUNTIFS('Question-Article-Match'!$A:$A,A12,'Question-Article-Match'!$C:$C,C12,'Question-Article-Match'!$F:$F,"indirect match")>0,"indirect match","no match")) -> no match
A13: Q1 | B13: How is CBA using AI to improve software engineering productivity? | C13: 20 | D13: 2b3ee594-b9e3-4c7b-9721-471bf15554f4 | E13: USO, UCO Dip As Oil Prices Slide After Trump Declares Iran Deal 'Complete' — Analyst Sees $80 Brent By Year-End | F13: 0 | G13: 12 | H13: =IF(COUNTIFS('Question-Article-Match'!$A:$A,A13,'Question-Article-Match'!$C:$C,C13,'Question-Article-Match'!$F:$F,"direct match")>0,"direct match",IF(COUNTIFS('Question-Article-Match'!$A:$A,A13,'Question-Article-Match'!$C:$C,C13,'Question-Article-Match'!$F:$F,"indirect match")>0,"indirect match","no match")) -> no match
... A337: H4 | B337: How is CBA generating A$400 million in value from its AI initiatives? | C337: 6 | D337: c385b2b8-f8e0-4278-99be-f30dbd1d2167 | E337: 3 Australian Dividend Stocks Paying Over 5% While Cash Income Looks Less Certain | F337: 0 | G337: 21 | H337: =IF(COUNTIFS('Question-Article-Match'!$A:$A,A337,'Question-Article-Match'!$C:$C,C337,'Question-Article-Match'!$F:$F,"direct match")>0,"direct match",IF(COUNTIFS('Question-Article-Match'!$A:$A,A337,'Question-Article-Match'!$C:$C,C337,'Question-Article-Match'!$F:$F,"indirect match")>0,"indirect match","no match")) -> no match

Sheet Retrieval Comparison
A1: Retrieval Comparison - CBA.AX (16 questions x 21 articles)
A3: Method | B3: Precision@5 | C3: Recall@5 | D3: Precision@7 | E3: Recall@7 | F3: Precision@10 | G3: Recall@10 | H3: MRR | I3: Avg # retrieved for no-answer Qs (k=5)
A4: Semantic | B4: =AVERAGEIFS($I$16:$I$63,$A$16:$A$63,$A4,$C$16:$C$63,"Yes") -> 0.59404762 | C4: =AVERAGEIFS($J$16:$J$63,$A$16:$A$63,$A4,$C$16:$C$63,"Yes") -> 0.69982993 | D4: =AVERAGEIFS($M$16:$M$63,$A$16:$A$63,$A4,$C$16:$C$63,"Yes") -> 0.58588435 | E4: =AVERAGEIFS($N$16:$N$63,$A$16:$A$63,$A4,$C$16:$C$63,"Yes") -> 0.7202381 | F4: =AVERAGEIFS($Q$16:$Q$63,$A$16:$A$63,$A4,$C$16:$C$63,"Yes") -> 0.58829365 | G4: =AVERAGEIFS($R$16:$R$63,$A$16:$A$63,$A4,$C$16:$C$63,"Yes") -> 0.75595238 | H4: =AVERAGEIFS($F$16:$F$63,$A$16:$A$63,$A4,$C$16:$C$63,"Yes") -> 0.80952143 | I4: =AVERAGEIFS($G$16:$G$63,$A$16:$A$63,$A4,$C$16:$C$63,"No") -> 1
A5: Lexical | B5: =AVERAGEIFS($I$16:$I$63,$A$16:$A$63,$A5,$C$16:$C$63,"Yes") -> 0.37142857 | C5: =AVERAGEIFS($J$16:$J$63,$A$16:$A$63,$A5,$C$16:$C$63,"Yes") -> 0.7372449 | D5: =AVERAGEIFS($M$16:$M$63,$A$16:$A$63,$A5,$C$16:$C$63,"Yes") -> 0.29285714 | E5: =AVERAGEIFS($N$16:$N$63,$A$16:$A$63,$A5,$C$16:$C$63,"Yes") -> 0.74744898 | F5: =AVERAGEIFS($Q$16:$Q$63,$A$16:$A$63,$A5,$C$16:$C$63,"Yes") -> 0.28117914 | G5: =AVERAGEIFS($R$16:$R$63,$A$16:$A$63,$A5,$C$16:$C$63,"Yes") -> 0.83078231 | H5: =AVERAGEIFS($F$16:$F$63,$A$16:$A$63,$A5,$C$16:$C$63,"Yes") -> 0.75 | I5: =AVERAGEIFS($G$16:$G$63,$A$16:$A$63,$A5,$C$16:$C$63,"No") -> 4.5
A6: Hybrid RRF | B6: =AVERAGEIFS($I$16:$I$63,$A$16:$A$63,$A6,$C$16:$C$63,"Yes") -> 0.4 | C6: =AVERAGEIFS($J$16:$J$63,$A$16:$A$63,$A6,$C$16:$C$63,"Yes") -> 0.75935374 | D6: =AVERAGEIFS($M$16:$M$63,$A$16:$A$63,$A6,$C$16:$C$63,"Yes") -> 0.32346939 | E6: =AVERAGEIFS($N$16:$N$63,$A$16:$A$63,$A6,$C$16:$C$63,"Yes") -> 0.79336735 | F6: =AVERAGEIFS($Q$16:$Q$63,$A$16:$A$63,$A6,$C$16:$C$63,"Yes") -> 0.29444444 | G6: =AVERAGEIFS($R$16:$R$63,$A$16:$A$63,$A6,$C$16:$C$63,"Yes") -> 0.88690476 | H6: =AVERAGEIFS($F$16:$F$63,$A$16:$A$63,$A6,$C$16:$C$63,"Yes") -> 0.78809286 | I6: =AVERAGEIFS($G$16:$G$63,$A$16:$A$63,$A6,$C$16:$C$63,"No") -> 4.5
A8: Method notes:
A9: Semantic: cosine similarity (Similarity tab), keep >= 0.4, rank by similarity. Ranked lists in the detail table are precomputed in Python.
A10: Lexical: ts_rank_cd from the user's query (Lexical tab), keep score > 0, rank as returned by SQL (score desc, id). The 0.40 threshold is NOT applied: ts_rank_cd is on a different scale.
A11: Hybrid RRF: union of the Semantic and Lexical lists above; score = sum of 1/(60 + rank) over the lists an article appears in; rank by score.
A12: Precision@k = hits / articles actually retrieved in top k (threshold can return fewer than k); Recall@k = hits / relevant; MRR uses the full retrieved list.
A13: Averages are macro, over the 14 answerable questions. Q11 and Q12 have no relevant article; last column = how many articles each method still returns for them.
A15: Method | B15: Question ID | C15: Answerable | D15: # Relevant | E15: Ranked List (CSV rows) | F15: Reciprocal Rank | G15: Retrieved@5 | H15: Hits@5 | I15: Precision@5 | J15: Recall@5 | K15: Retrieved@7 | L15: Hits@7 | M15: Precision@7 | N15: Recall@7 | O15: Retrieved@10 | P15: Hits@10 | Q15: Precision@10 | R15: Recall@10
A16: Semantic | B16: Q1 | C16: Yes | D16: 3 | E16: 3, 14 | F16: 1 | G16: 2 | H16: 2 | I16: =IF(G16=0,0,H16/G16) -> 1 | J16: =IF(D16=0,"",H16/D16) -> 0.66666667 | K16: 2 | L16: 2 | M16: =IF(K16=0,0,L16/K16) -> 1 | N16: =IF(D16=0,"",L16/D16) -> 0.66666667 | O16: 2 | P16: 2 | Q16: =IF(O16=0,0,P16/O16) -> 1 | R16: =IF(D16=0,"",P16/D16) -> 0.66666667
A17: Semantic | B17: Q2 | C17: Yes | D17: 2 | E17: 3, 14, 18 | F17: 1 | G17: 3 | H17: 2 | I17: =IF(G17=0,0,H17/G17) -> 0.66666667 | J17: =IF(D17=0,"",H17/D17) -> 1 | K17: 3 | L17: 2 | M17: =IF(K17=0,0,L17/K17) -> 0.66666667 | N17: =IF(D17=0,"",L17/D17) -> 1 | O17: 3 | P17: 2 | Q17: =IF(O17=0,0,P17/O17) -> 0.66666667 | R17: =IF(D17=0,"",P17/D17) -> 1
A18: Semantic | B18: Q3 | C18: Yes | D18: 3 | E18: 16, 19, 14 | F18: 0 | G18: 3 | H18: 0 | I18: =IF(G18=0,0,H18/G18) -> 0 | J18: =IF(D18=0,"",H18/D18) -> 0 | K18: 3 | L18: 0 | M18: =IF(K18=0,0,L18/K18) -> 0 | N18: =IF(D18=0,"",L18/D18) -> 0 | O18: 3 | P18: 0 | Q18: =IF(O18=0,0,P18/O18) -> 0 | R18: =IF(D18=0,"",P18/D18) -> 0
A19: Semantic | B19: Q4 | C19: Yes | D19: 2 | E19: 1, 2, 3, 14 | F19: 1 | G19: 4 | H19: 2 | I19: =IF(G19=0,0,H19/G19) -> 0.5 | J19: =IF(D19=0,"",H19/D19) -> 1 | K19: 4 | L19: 2 | M19: =IF(K19=0,0,L19/K19) -> 0.5 | N19: =IF(D19=0,"",L19/D19) -> 1 | O19: 4 | P19: 2 | Q19: =IF(O19=0,0,P19/O19) -> 0.5 | R19: =IF(D19=0,"",P19/D19) -> 1
A20: Semantic | B20: Q5 | C20: Yes | D20: 4 | E20: 10, 7, 16, 12 | F20: 1 | G20: 4 | H20: 3 | I20: =IF(G20=0,0,H20/G20) -> 0.75 | J20: =IF(D20=0,"",H20/D20) -> 0.75 | K20: 4 | L20: 3 | M20: =IF(K20=0,0,L20/K20) -> 0.75 | N20: =IF(D20=0,"",L20/D20) -> 0.75 | O20: 4 | P20: 3 | Q20: =IF(O20=0,0,P20/O20) -> 0.75 | R20: =IF(D20=0,"",P20/D20) -> 0.75
A21: Semantic | B21: Q6 | C21: Yes | D21: 7 | E21: 7, 12, 10, 5, 6, 8, 19, 16 | F21: 1 | G21: 5 | H21: 5 | I21: =IF(G21=0,0,H21/G21) -> 1 | J21: =IF(D21=0,"",H21/D21) -> 0.71428571 | K21: 7 | L21: 7 | M21: =IF(K21=0,0,L21/K21) -> 1 | N21: =IF(D21=0,"",L21/D21) -> 1 | O21: 8 | P21: 7 | Q21: =IF(O21=0,0,P21/O21) -> 0.875 | R21: =IF(D21=0,"",P21/D21) -> 1
A22: Semantic | B22: Q7 | C22: Yes | D22: 1 | E22: 19, 16, 14 | F22: 0 | G22: 3 | H22: 0 | I22: =IF(G22=0,0,H22/G22) -> 0 | J22: =IF(D22=0,"",H22/D22) -> 0 | K22: 3 | L22: 0 | M22: =IF(K22=0,0,L22/K22) -> 0 | N22: =IF(D22=0,"",L22/D22) -> 0 | O22: 3 | P22: 0 | Q22: =IF(O22=0,0,P22/O22) -> 0 | R22: =IF(D22=0,"",P22/D22) -> 0
A23: Semantic | B23: Q8 | C23: Yes | D23: 4 | E23: 18, 2, 14, 1, 3, 19, 16, 17, 21 | F23: 0.3333 | G23: 5 | H23: 2 | I23: =IF(G23=0,0,H23/G23) -> 0.4 | J23: =IF(D23=0,"",H23/D23) -> 0.5 | K23: 7 | L23: 2 | M23: =IF(K23=0,0,L23/K23) -> 0.28571429 | N23: =IF(D23=0,"",L23/D23) -> 0.5 | O23: 9 | P23: 4 | Q23: =IF(O23=0,0,P23/O23) -> 0.44444444 | R23: =IF(D23=0,"",P23/D23) -> 1
A24: Semantic | B24: Q9 | C24: Yes | D24: 4 | E24: 5, 6, 8, 19 | F24: 1 | G24: 4 | H24: 4 | I24: =IF(G24=0,0,H24/G24) -> 1 | J24: =IF(D24=0,"",H24/D24) -> 1 | K24: 4 | L24: 4 | M24: =IF(K24=0,0,L24/K24) -> 1 | N24: =IF(D24=0,"",L24/D24) -> 1 | O24: 4 | P24: 4 | Q24: =IF(O24=0,0,P24/O24) -> 1 | R24: =IF(D24=0,"",P24/D24) -> 1
A25: Semantic | B25: Q10 | C25: Yes | D25: 1 | E25: 19, 11 | F25: 1 | G25: 2 | H25: 1 | I25: =IF(G25=0,0,H25/G25) -> 0.5 | J25: =IF(D25=0,"",H25/D25) -> 1 | K25: 2 | L25: 1 | M25: =IF(K25=0,0,L25/K25) -> 0.5 | N25: =IF(D25=0,"",L25/D25) -> 1 | O25: 2 | P25: 1 | Q25: =IF(O25=0,0,P25/O25) -> 0.5 | R25: =IF(D25=0,"",P25/D25) -> 1
A26: Semantic | B26: Q11 | C26: No | D26: 0 | E26: 16, 19 | F26: 0 | G26: 2 | H26: 0 | I26: =IF(G26=0,0,H26/G26) -> 0 | J26: =IF(D26=0,"",H26/D26) | K26: 2 | L26: 0 | M26: =IF(K26=0,0,L26/K26) -> 0 | N26: =IF(D26=0,"",L26/D26) | O26: 2 | P26: 0 | Q26: =IF(O26=0,0,P26/O26) -> 0 | R26: =IF(D26=0,"",P26/D26)
A27: Semantic | B27: Q12 | C27: No | D27: 0 | E27: (none) | F27: 0 | G27: 0 | H27: 0 | I27: =IF(G27=0,0,H27/G27) -> 0 | J27: =IF(D27=0,"",H27/D27) | K27: 0 | L27: 0 | M27: =IF(K27=0,0,L27/K27) -> 0 | N27: =IF(D27=0,"",L27/D27) | O27: 0 | P27: 0 | Q27: =IF(O27=0,0,P27/O27) -> 0 | R27: =IF(D27=0,"",P27/D27)
... A63: Hybrid RRF | B63: H4 | C63: Yes | D63: 3 | E63: 3, 16, 14, 19, 21, 1, 2, 17, 13, 18, 15 | F63: 1 | G63: 5 | H63: 2 | I63: =IF(G63=0,0,H63/G63) -> 0.4 | J63: =IF(D63=0,"",H63/D63) -> 0.66666667 | K63: 7 | L63: 2 | M63: =IF(K63=0,0,L63/K63) -> 0.28571429 | N63: =IF(D63=0,"",L63/D63) -> 0.66666667 | O63: 10 | P63: 3 | Q63: =IF(O63=0,0,P63/O63) -> 0.3 | R63: =IF(D63=0,"",P63/D63) -> 1

Sheet Answer Quality
A1: End-to-end answer quality - 4 CBA questions x 3 retrieval methods (k=5, semantic threshold 0.40)
A3: Method | B3: Avg Retrieval Recall | C3: Avg Groundedness % | D3: Avg Completeness vs Gold % | E3: Avg Completeness vs Retrieved % | F3: Q12 (answer absent): declined?
A4: Semantic | B4: =AVERAGEIFS($I$16:$I$27,$D$16:$D$27,$A4,$G$16:$G$27,">0") -> 0.57142857 | C4: =AVERAGEIFS($J$16:$J$27,$D$16:$D$27,$A4,$G$16:$G$27,">0") -> 90 | D4: =AVERAGEIFS($L$16:$L$27,$D$16:$D$27,$A4,$G$16:$G$27,">0") -> 65 | E4: =AVERAGEIFS($M$16:$M$27,$D$16:$D$27,$A4,$G$16:$G$27,">0") -> 95 | F4: =INDEX($N$16:$N$27,MATCH(1,INDEX(($A$16:$A$27="Q12")*($D$16:$D$27=$A4),0),0)) -> Yes
A5: Lexical | B5: =AVERAGEIFS($I$16:$I$27,$D$16:$D$27,$A5,$G$16:$G$27,">0") -> 0.74603175 | C5: =AVERAGEIFS($J$16:$J$27,$D$16:$D$27,$A5,$G$16:$G$27,">0") -> 83.333333 | D5: =AVERAGEIFS($L$16:$L$27,$D$16:$D$27,$A5,$G$16:$G$27,">0") -> 95 | E5: =AVERAGEIFS($M$16:$M$27,$D$16:$D$27,$A5,$G$16:$G$27,">0") -> 93.333333 | F5: =INDEX($N$16:$N$27,MATCH(1,INDEX(($A$16:$A$27="Q12")*($D$16:$D$27=$A5),0),0)) -> Yes
A6: Hybrid RRF | B6: =AVERAGEIFS($I$16:$I$27,$D$16:$D$27,$A6,$G$16:$G$27,">0") -> 0.68253968 | C6: =AVERAGEIFS($J$16:$J$27,$D$16:$D$27,$A6,$G$16:$G$27,">0") -> 93.333333 | D6: =AVERAGEIFS($L$16:$L$27,$D$16:$D$27,$A6,$G$16:$G$27,">0") -> 95 | E6: =AVERAGEIFS($M$16:$M$27,$D$16:$D$27,$A6,$G$16:$G$27,">0") -> 96.666667 | F6: =INDEX($N$16:$N$27,MATCH(1,INDEX(($A$16:$A$27="Q12")*($D$16:$D$27=$A6),0),0)) -> Yes
A8: Method:
A9: Questions: H1 = direct answer; Q6 = broad, many relevant articles; Q3 = retrieval methods differ; Q12 = answer absent. Averages cover the 3 answerable questions (H1, Q6, Q3).
A10: Retrieved lists = top 5 from the Retrieval Comparison tab. Evidence text fetched read-only from ticker_news in the exact shape search_internal_news_tool produces.
A11: Answers: production agent/shared/synthesize.py::synthesize_insight (ANALYSIS_MODEL) with question=..., no ReAct draft_answer, no external Yahoo tool. Empty evidence returns production's fixed decline message.
A12: Judges (JUDGE_MODEL, agent/eval/judge.py): groundedness vs RETRIEVED evidence; completeness vs GOLD evidence (human-labelled articles = expected answer facts) and vs retrieved evidence (what production monitoring sees); answer_found for Q12.
A13: Single run per cell - LLM generation and judging are non-deterministic, so differences of ~5-15 points between cells are within noise.
A15: Question ID | B15: Question Type | C15: Question | D15: Method | E15: Retrieved (CSV rows) | F15: Gold (CSV rows) | G15: # Gold | H15: Relevant Retrieved | I15: Retrieval Recall | J15: Groundedness % | K15: Grounded | L15: Completeness vs Gold % | M15: Completeness vs Retrieved % (monitoring view) | N15: Declined Correctly (answer-absent) | O15: Answer | P15: Unsupported Claims | Q15: Omitted Gold Points
A16: H1 | B16: Direct answer | C16: What new payout platform has CBA introduced to replace cheque-based payments? | D16: Semantic | E16: 9 | F16: 9 | G16: 1 | H16: 1 | I16: =IF(G16=0,"n/a",H16/G16) -> 1 | J16: 75 | K16: No | L16: 100 | M16: 100 | N16: n/a | O16: Based on the evidence, Commonwealth Bank has introduced **PaidIt**, a new payout platform launched ahead of the phase-out of cheques. According to the reporting from Retail Banker International, PaidIt combines three functions within a single system: - **Recipient verification** – confirming the identity/details of the person being paid - **Communications** – notifying recipients about the payment - **Payment delivery** – actually transferring the funds This platform is positioned as CBA's replacement mechanism for cheque-based payments as cheques are wound down. Note: the evidence provided is limited to this single announcement, so I don't have further details on rollout timing, target customers (retail vs. business), or how PaidIt compares to existing payment rails like PayID/Osko. | P16: [unsupported] Recipient verification – confirming the identity/details of the person being paid [unsupported] Communications – notifying recipients about the payment [unsupported] Payment delivery – actually transferring the funds [unsupported] This platform is positioned as CBA's replacement mechanism for cheque-based payments as cheques are wound down.
A17: H1 | B17: Direct answer | C17: What new payout platform has CBA introduced to replace cheque-based payments? | D17: Lexical | E17: 9, 14, 16, 3, 11 | F17: 9 | G17: 1 | H17: 1 | I17: =IF(G17=0,"n/a",H17/G17) -> 1 | J17: 85 | K17: No | L17: 100 | M17: 100 | N17: n/a | O17: Commonwealth Bank has launched **PaidIt**, a new payout platform introduced ahead of the industry-wide phase-out of cheques. PaidIt combines three functions within a single system: - **Recipient verification** - **Communications** - **Payment delivery** This consolidated approach is designed to provide a replacement for cheque-based payouts, streamlining how CBA confirms who a payment is going to, notifies recipients, and delivers funds — all in one platform. | P17: [unsupported] introduced ahead of the industry-wide phase-out of cheques [unsupported] This consolidated approach is designed to provide a replacement for cheque-based payouts
A18: H1 | B18: Direct answer | C18: What new payout platform has CBA introduced to replace cheque-based payments? | D18: Hybrid RRF | E18: 9, 14, 16, 3, 11 | F18: 9 | G18: 1 | H18: 1 | I18: =IF(G18=0,"n/a",H18/G18) -> 1 | J18: 100 | K18: Yes | L18: 100 | M18: 100 | N18: n/a | O18: CBA has introduced **PaidIt**, a new payout platform launched ahead of the phase-out of cheque-based payments. According to Retail Banker International, PaidIt combines three functions into a single system: - **Recipient verification** - **Communications** - **Payment delivery** This appears designed to provide an integrated alternative for disbursing funds as cheques are wound down.
A19: Q6 | B19: Broad, multi-article | C19: What are the latest expectations for Australian interest rates? | D19: Semantic | E19: 7, 12, 10, 5, 6 | F19: 7, 12, 19, 10, 5, 6, 8 | G19: 7 | H19: 5 | I19: =IF(G19=0,"n/a",H19/G19) -> 0.71428571 | J19: 95 | K19: No | L19: 95 | M19: 95 | N19: n/a | O19: Based on the evidence gathered, here's what the latest commentary suggests about Australian interest rate expectations: - **Further rate hikes anticipated**: As of late August, three of Australia's four major banks — Commonwealth Bank of Australia, National Australia Bank, and ANZ — were forecasting another rate hike before year-end, triggered by a hotter-than-expected inflation print. - **Market positioning around a November move**: Speculative investors have reportedly increased bets that the Reserve Bank of Australia (RBA) will raise rates again in November, as inflation remains above the central bank's target. - **Broader market tone**: Related commentary notes that bond yields are reflecting expectations for tighter central bank policy generally, and that higher global rate expectations have pushed up funding costs — a dynamic cited in the context of dividend-paying stocks becoming more attractive as fixed-income alternatives. In short, the prevailing expectation reflected in this evidence is for **at least one more RBA rate hike (with November floated as a likely timing)**, driven by persistent inflation pressures. The evidence does not provide more recent updates beyond this point, so I can't speak to whether these expectations have since shifted. | P19: [unsupported] a dynamic cited in the context of dividend-paying stocks becoming more attractive as fixed-income alternatives | Q19: The knock-on effect on banks/mortgage lending mentioned in the evidence (investors questioning rich valuations of Australian banks as mortgage demand plummets) is not reflected Australian credit growth described as still resilient despite rate expectations
A20: Q6 | B20: Broad, multi-article | C20: What are the latest expectations for Australian interest rates? | D20: Lexical | E20: 5, 7, 12, 6, 11 | F20: 7, 12, 19, 10, 5, 6, 8 | G20: 7 | H20: 4 | I20: =IF(G20=0,"n/a",H20/G20) -> 0.57142857 | J20: 80 | K20: No | L20: 90 | M20: 95 | N20: n/a | O20: Based on the evidence available, here's what's indicated about Australian interest rate expectations: - **Rate hikes were being forecast**: Three of Australia's four major banks — including Commonwealth Bank of Australia (CBA) itself, along with NAB and ANZ — forecast another rate hike in 2023 after a stronger-than-expected inflation print. - **Market positioning pointed to a November hike**: Speculative traders ("fast money") were increasingly pricing in a Reserve Bank of Australia (RBA) rate increase in November, driven by inflation remaining above the RBA's target band. - **Broader market tone reflects tighter-for-longer policy**: Commentary around dividend stocks notes that "higher global interest rate expectations" and expectations of "tighter central bank policy" have pushed up funding costs and made bond/cash yields less certain, reinforcing the theme that rates were expected to stay elevated or rise further. **Caveat**: This evidence is dated (references to 2023 inflation prints, August/November rate-hike forecasts) and does not include the most recent RBA decisions or current market pricing for future moves. If you're looking for up-to-date expectations (e.g., current RBA cash rate target or forward guidance), this evidence set doesn't cover that — it reflects a snapshot from a prior rate-hiking cycle rather than the latest outlook. | P20: [unsupported] forecast another rate hike in 2023 after a stronger-than-expected inflation print [unsupported] This evidence is dated (references to 2023 inflation prints, August/November rate-hike forecasts) [unsupported] inflation remaining above the RBA's target band [unsupported] it reflects a snapshot from a prior rate-hiking cycle rather than the latest outlook | Q20: The knock-on effect on Australian banks: a plunge in mortgage demand/lending downturn is causing investors to question the rich valuations of the big banks (Reuters, Aug 25) Mention that Australian credit growth remains resilient despite higher rate expectations
A21: Q6 | B21: Broad, multi-article | C21: What are the latest expectations for Australian interest rates? | D21: Hybrid RRF | E21: 7, 5, 12, 10, 6 | F21: 7, 12, 19, 10, 5, 6, 8 | G21: 7 | H21: 5 | I21: =IF(G21=0,"n/a",H21/G21) -> 0.71428571 | J21: 95 | K21: No | L21: 95 | M21: 95 | N21: n/a | O21: Based on the gathered evidence, the latest expectations around Australian interest rates point toward further tightening rather than cuts: - **Major bank forecasts**: CBA, NAB, and ANZ (three of Australia's four major banks) have all forecast an additional rate hike this year, a shift driven by a stronger-than-expected inflation print. - **Market positioning**: Speculative/"fast money" investors are increasingly pricing in a Reserve Bank of Australia (RBA) rate hike at its November meeting, reflecting continued concern that inflation remains above the RBA's target band. - **Broader market tone**: Commentary around dividend-paying stocks notes that "higher global interest rate expectations" and bond yields reflecting "tighter central bank policy" are pushing up funding costs and making cash/bond income less certain, reinforcing the theme that markets are bracing for higher-for-longer rates rather than imminent easing. Taken together, the evidence suggests the prevailing expectation at the time of these reports was for at least one more RBA rate hike (potentially in November), driven by persistent inflation pressure. The evidence does not provide specifics on rate expectations beyond this near-term hike (e.g., no detail on a longer-term rate path, terminal rate level, or subsequent cuts). | P21: [unsupported] reflecting continued concern that inflation remains above the RBA's target band [unsupported] reinforcing the theme that markets are bracing for higher-for-longer rates rather than imminent easing | Q21: The Reuters piece on bank investors bracing for tough times notes mortgage demand plummeting / a downturn in mortgage lending and questioned bank valuations — a rate-related market consequence not mentioned in the answer The mention that Australian credit growth remains resilient (from the dividend screener article) was not incorporated
A22: Q3 | B22: Retrieval methods differ | C22: How is CBA modernising its payment services? | D22: Semantic | E22: 16, 19, 14 | F22: 9, 1, 2 | G22: 3 | H22: 0 | I22: =IF(G22=0,"n/a",H22/G22) -> 0 | J22: 100 | K22: Yes | L22: 0 | M22: 90 | N22: n/a | O22: Based on the evidence gathered, I'm unable to directly answer how CBA is modernising its payment services specifically. The available information doesn't contain details on CBA's payment technology initiatives, infrastructure upgrades, or specific payment product developments. What the evidence does touch on are adjacent but distinct topics: - **AI-driven customer service changes** – CBA, along with Microsoft and Uber, has reportedly been replacing customer service roles with AI, which could be tangentially related to how the bank operates digitally but isn't specific to payments infrastructure. - **Lending facility to archTIS** – CBA extended a A$4 million working capital facility to a data security software company, which is a lending relationship rather than a payments modernisation initiative. - **General investment narrative commentary** – A Simply Wall St piece referencing profit trends and RBA rate expectations, which doesn't address payments technology. If you're looking for specifics on CBA's payment modernisation efforts (e.g., real-time payments infrastructure, digital wallet integration, merchant services, or core banking platform upgrades), I'd need additional targeted evidence/news sources covering those areas specifically. | Q22: CBA has unveiled a new payout platform called PaidIt, launched ahead of the exit/phase-out of cheques PaidIt combines recipient verification, communications and payment delivery within a single system CBA is part of a coalition of global banks (with NatWest, Bank of America and others) warning that agentic AI shopping agents could increase risk of scams, fraud and data privacy breaches The banks' concern that AI commerce tools could expose card details and weaken payment security, outpacing current industry fraud safeguards
A23: Q3 | B23: Retrieval methods differ | C23: How is CBA modernising its payment services? | D23: Lexical | E23: 14, 16, 3, 9, 1 | F23: 9, 1, 2 | G23: 3 | H23: 2 | I23: =IF(G23=0,"n/a",H23/G23) -> 0.66666667 | J23: 85 | K23: No | L23: 95 | M23: 85 | N23: n/a | O23: Based on the evidence available, the clearest example of CBA modernising its payment services is: - **Launch of "PaidIt"** – a new payout platform CBA has unveiled ahead of the phase-out of cheques in Australia. It combines recipient verification, communications, and payment delivery into a single integrated system, aimed at helping businesses and institutions transition away from cheque-based payments to digital alternatives. Separately, CBA is investing heavily in AI capabilities more broadly (e.g., its chief AI officer has discussed scaling roughly A$400 million in AI value, with the majority of engineers using AI agents to boost code output and resolve security issues). While this reflects a broader technology modernisation push at the bank, the evidence doesn't specify how much of this AI investment is directly tied to payments infrastructure versus other areas like customer service or engineering productivity. The evidence does not provide further detail on other specific payment modernisation initiatives (e.g., real-time payments infrastructure, NPP upgrades, digital wallet integration, or international payment systems), so a fuller picture of CBA's payments strategy isn't available from what's here. | P23: [unsupported] the phase-out of cheques in Australia [unsupported] aimed at helping businesses and institutions transition away from cheque-based payments to digital alternatives [unsupported] the majority of engineers using AI agents to boost code output and resolve security issues | Q23: The two articles about banks warning that agentic AI shopping agents could expose card details, increase scam/fraud risk and outpace payment security safeguards were not reflected; this industry-level payment-security context (coalition of global banks including NatWest and Bank of America) is only tangentially relevant since CBA is not named
A24: Q3 | B24: Retrieval methods differ | C24: How is CBA modernising its payment services? | D24: Hybrid RRF | E24: 16, 14, 19, 3, 9 | F24: 9, 1, 2 | G24: 3 | H24: 1 | I24: =IF(G24=0,"n/a",H24/G24) -> 0.33333333 | J24: 85 | K24: No | L24: 90 | M24: 95 | N24: n/a | O24: Based on the available evidence, the clearest example of CBA modernising its payment services is the launch of **PaidIt**, a new payout platform highlighted ahead of the phase-out of cheques. Key features reported include: - **Recipient verification** built into the platform to confirm payees before funds are sent - **Integrated communications** with recipients as part of the payment workflow - **Payment delivery** consolidated within a single system, rather than relying on separate processes This appears to be positioned as a digital replacement for cheque-based payouts, aligning with the broader industry shift away from paper cheques. Separately, the evidence also points to CBA investing in **AI capabilities** more broadly across the bank (e.g., AI agents used by engineers, AI chief discussing scaling AI value), which may support operational efficiency, though this isn't specifically tied to payment services in the evidence provided. The other items in the evidence (the archTIS lending facility and general AI/customer service coverage) relate to CBA's business lending and AI strategy more broadly, not specifically to payment service modernisation, so I haven't included them as directly relevant here. If you're looking for more detail on CBA's payments infrastructure (e.g., real-time payments, NPP integration, merchant services, or international payment upgrades), the current evidence doesn't cover those areas specifically. | P24: [unsupported] Recipient verification built into the platform to confirm payees before funds are sent [unsupported] Integrated communications with recipients as part of the payment workflow [unsupported] This appears to be positioned as a digital replacement for cheque-based payouts, aligning with the broader industry shift away from paper cheques. [unsupported] AI agents used by engineers ... which may support operational efficiency | Q24: The evidence includes two items about a coalition of global banks (including NatWest and Bank of America) warning that agentic AI shopping agents could expose card details, increase scams/fraud and data privacy risks, and outpace existing payment fraud protections — this payments-security context was not mentioned at all in the answer
A25: Q12 | B25: Answer absent | C25: What are CBA's climate commitments, such as net-zero targets or limits on fossil-fuel lending? | D25: Semantic | E25: (none) | F25: (none) | G25: 0 | H25: 0 | I25: =IF(G25=0,"n/a",H25/G25) -> n/a | J25: n/a (no evidence) | K25: n/a | L25: n/a | M25: n/a | N25: Yes | O25: Not enough evidence was gathered for CBA.AX to produce an insight. [fixed production message - no LLM call, empty evidence]
A26: Q12 | B26: Answer absent | C26: What are CBA's climate commitments, such as net-zero targets or limits on fossil-fuel lending? | D26: Lexical | E26: 16, 3, 11, 12, 10 | F26: (none) | G26: 0 | H26: 0 | I26: =IF(G26=0,"n/a",H26/G26) -> n/a | J26: 100 | K26: Yes | L26: n/a | M26: 100 | N26: Yes | O26: The evidence provided doesn't actually address CBA's climate commitments, net-zero targets, or fossil-fuel lending policies. The gathered material instead covers unrelated topics — a lending facility extended to a data security company, CBA's internal AI initiatives, interest rate speculation, mortgage demand trends, and an unrelated private bank's earnings. None of this touches on climate strategy, emissions reduction targets, exposure limits to coal/oil/gas financing, or sustainability-linked lending policies, which is what your question is asking about. To properly answer this, I'd need evidence specifically from CBA's climate reporting (such as its Climate Report or Net Zero transition plans), ESG disclosures, or news coverage of its fossil-fuel financing policies — none of which is present here.
A27: Q12 | B27: Answer absent | C27: What are CBA's climate commitments, such as net-zero targets or limits on fossil-fuel lending? | D27: Hybrid RRF | E27: 16, 3, 11, 12, 10 | F27: (none) | G27: 0 | H27: 0 | I27: =IF(G27=0,"n/a",H27/G27) -> n/a | J27: 100 | K27: Yes | L27: n/a | M27: 100 | N27: Yes | O27: The evidence gathered doesn't address this question. None of the available news items discuss CBA's climate strategy, net-zero commitments, emissions-reduction targets, or any policies related to fossil-fuel lending restrictions. The material provided instead covers unrelated topics—such as a small business lending facility, CBA's AI initiatives, interest rate speculation, and broader mortgage market conditions in Australia. To properly answer a question about CBA's climate commitments, you'd want evidence such as the bank's sustainability or climate reports, statements on its Paris Agreement alignment, any thermal coal or oil & gas lending exclusion policies, and progress updates against previously stated emission-reduction targets for its lending portfolio. None of that is present here, so I can't provide a reliable answer based on the current evidence.

Sheet Answer Quality (All)
A1: End-to-end answer quality - all 16 CBA questions x 3 methods, k = 5, 10 (semantic threshold 0.40)
A3: k | B3: Method | C3: Avg Retrieval Recall | D3: Avg Groundedness % | E3: % Fully Grounded | F3: Avg Completeness vs Gold % | G3: Avg Completeness vs Retrieved % | H3: Answer-absent declined (of 2) | I3: Cells reused from lower k
A4: 5 | B4: Semantic | C4: =AVERAGEIFS($I$26:$I$121,$A$26:$A$121,$A4,$D$26:$D$121,$B4,$G$26:$G$121,">0") -> 0.69982993 | D4: =AVERAGEIFS($J$26:$J$121,$A$26:$A$121,$A4,$D$26:$D$121,$B4,$G$26:$G$121,">0") -> 89.071429 | E4: =COUNTIFS($A$26:$A$121,$A4,$D$26:$D$121,$B4,$G$26:$G$121,">0",$K$26:$K$121,"Yes")/COUNTIFS($A$26:$A$121,$A4,$D$26:$D$121,$B4,$G$26:$G$121,">0",$K$26:$K$121,"<>n/a") -> 0.28571429 | F4: =AVERAGEIFS($L$26:$L$121,$A$26:$A$121,$A4,$D$26:$D$121,$B4,$G$26:$G$121,">0") -> 79.071429 | G4: =AVERAGEIFS($M$26:$M$121,$A$26:$A$121,$A4,$D$26:$D$121,$B4,$G$26:$G$121,">0") -> 96.071429 | H4: =COUNTIFS($A$26:$A$121,$A4,$D$26:$D$121,$B4,$N$26:$N$121,"Yes") -> 2 | I4: =COUNTIFS($A$26:$A$121,$A4,$D$26:$D$121,$B4,$O$26:$O$121,"<>") -> 0
A5: 5 | B5: Lexical | C5: =AVERAGEIFS($I$26:$I$121,$A$26:$A$121,$A5,$D$26:$D$121,$B5,$G$26:$G$121,">0") -> 0.7372449 | D5: =AVERAGEIFS($J$26:$J$121,$A$26:$A$121,$A5,$D$26:$D$121,$B5,$G$26:$G$121,">0") -> 88.571429 | E5: =COUNTIFS($A$26:$A$121,$A5,$D$26:$D$121,$B5,$G$26:$G$121,">0",$K$26:$K$121,"Yes")/COUNTIFS($A$26:$A$121,$A5,$D$26:$D$121,$B5,$G$26:$G$121,">0",$K$26:$K$121,"<>n/a") -> 0.071428571 | F5: =AVERAGEIFS($L$26:$L$121,$A$26:$A$121,$A5,$D$26:$D$121,$B5,$G$26:$G$121,">0") -> 82.857143 | G5: =AVERAGEIFS($M$26:$M$121,$A$26:$A$121,$A5,$D$26:$D$121,$B5,$G$26:$G$121,">0") -> 94.642857 | H5: =COUNTIFS($A$26:$A$121,$A5,$D$26:$D$121,$B5,$N$26:$N$121,"Yes") -> 2 | I5: =COUNTIFS($A$26:$A$121,$A5,$D$26:$D$121,$B5,$O$26:$O$121,"<>") -> 0
A6: 5 | B6: Hybrid RRF | C6: =AVERAGEIFS($I$26:$I$121,$A$26:$A$121,$A6,$D$26:$D$121,$B6,$G$26:$G$121,">0") -> 0.75935374 | D6: =AVERAGEIFS($J$26:$J$121,$A$26:$A$121,$A6,$D$26:$D$121,$B6,$G$26:$G$121,">0") -> 86.071429 | E6: =COUNTIFS($A$26:$A$121,$A6,$D$26:$D$121,$B6,$G$26:$G$121,">0",$K$26:$K$121,"Yes")/COUNTIFS($A$26:$A$121,$A6,$D$26:$D$121,$B6,$G$26:$G$121,">0",$K$26:$K$121,"<>n/a") -> 0.21428571 | F6: =AVERAGEIFS($L$26:$L$121,$A$26:$A$121,$A6,$D$26:$D$121,$B6,$G$26:$G$121,">0") -> 86.071429 | G6: =AVERAGEIFS($M$26:$M$121,$A$26:$A$121,$A6,$D$26:$D$121,$B6,$G$26:$G$121,">0") -> 95.357143 | H6: =COUNTIFS($A$26:$A$121,$A6,$D$26:$D$121,$B6,$N$26:$N$121,"Yes") -> 2 | I6: =COUNTIFS($A$26:$A$121,$A6,$D$26:$D$121,$B6,$O$26:$O$121,"<>") -> 0
A7: 10 | B7: Semantic | C7: =AVERAGEIFS($I$26:$I$121,$A$26:$A$121,$A7,$D$26:$D$121,$B7,$G$26:$G$121,">0") -> 0.75595238 | D7: =AVERAGEIFS($J$26:$J$121,$A$26:$A$121,$A7,$D$26:$D$121,$B7,$G$26:$G$121,">0") -> 88 | E7: =COUNTIFS($A$26:$A$121,$A7,$D$26:$D$121,$B7,$G$26:$G$121,">0",$K$26:$K$121,"Yes")/COUNTIFS($A$26:$A$121,$A7,$D$26:$D$121,$B7,$G$26:$G$121,">0",$K$26:$K$121,"<>n/a") -> 0.28571429 | F7: =AVERAGEIFS($L$26:$L$121,$A$26:$A$121,$A7,$D$26:$D$121,$B7,$G$26:$G$121,">0") -> 80.142857 | G7: =AVERAGEIFS($M$26:$M$121,$A$26:$A$121,$A7,$D$26:$D$121,$B7,$G$26:$G$121,">0") -> 95.714286 | H7: =COUNTIFS($A$26:$A$121,$A7,$D$26:$D$121,$B7,$N$26:$N$121,"Yes") -> 2 | I7: =COUNTIFS($A$26:$A$121,$A7,$D$26:$D$121,$B7,$O$26:$O$121,"<>") -> 14
A8: 10 | B8: Lexical | C8: =AVERAGEIFS($I$26:$I$121,$A$26:$A$121,$A8,$D$26:$D$121,$B8,$G$26:$G$121,">0") -> 0.83078231 | D8: =AVERAGEIFS($J$26:$J$121,$A$26:$A$121,$A8,$D$26:$D$121,$B8,$G$26:$G$121,">0") -> 86.785714 | E8: =COUNTIFS($A$26:$A$121,$A8,$D$26:$D$121,$B8,$G$26:$G$121,">0",$K$26:$K$121,"Yes")/COUNTIFS($A$26:$A$121,$A8,$D$26:$D$121,$B8,$G$26:$G$121,">0",$K$26:$K$121,"<>n/a") -> 0.071428571 | F8: =AVERAGEIFS($L$26:$L$121,$A$26:$A$121,$A8,$D$26:$D$121,$B8,$G$26:$G$121,">0") -> 85 | G8: =AVERAGEIFS($M$26:$M$121,$A$26:$A$121,$A8,$D$26:$D$121,$B8,$G$26:$G$121,">0") -> 93.928571 | H8: =COUNTIFS($A$26:$A$121,$A8,$D$26:$D$121,$B8,$N$26:$N$121,"Yes") -> 2 | I8: =COUNTIFS($A$26:$A$121,$A8,$D$26:$D$121,$B8,$O$26:$O$121,"<>") -> 4
A9: 10 | B9: Hybrid RRF | C9: =AVERAGEIFS($I$26:$I$121,$A$26:$A$121,$A9,$D$26:$D$121,$B9,$G$26:$G$121,">0") -> 0.88690476 | D9: =AVERAGEIFS($J$26:$J$121,$A$26:$A$121,$A9,$D$26:$D$121,$B9,$G$26:$G$121,">0") -> 88.928571 | E9: =COUNTIFS($A$26:$A$121,$A9,$D$26:$D$121,$B9,$G$26:$G$121,">0",$K$26:$K$121,"Yes")/COUNTIFS($A$26:$A$121,$A9,$D$26:$D$121,$B9,$G$26:$G$121,">0",$K$26:$K$121,"<>n/a") -> 0.14285714 | F9: =AVERAGEIFS($L$26:$L$121,$A$26:$A$121,$A9,$D$26:$D$121,$B9,$G$26:$G$121,">0") -> 88.928571 | G9: =AVERAGEIFS($M$26:$M$121,$A$26:$A$121,$A9,$D$26:$D$121,$B9,$G$26:$G$121,">0") -> 93.214286 | H9: =COUNTIFS($A$26:$A$121,$A9,$D$26:$D$121,$B9,$N$26:$N$121,"Yes") -> 2 | I9: =COUNTIFS($A$26:$A$121,$A9,$D$26:$D$121,$B9,$O$26:$O$121,"<>") -> 4
A12: k | B12: CORREL(recall, completeness vs gold) | C12: CORREL(recall, groundedness) | D12: Answerable rows
A13: 5 | B13: =CORREL(I26:I73,L26:L73) -> 0.85739371 | C13: =CORREL(I26:I73,J26:J73) -> -0.16474252 | D13: =COUNTIFS(A26:A73,5,G26:G73,">0") -> 42
A14: 10 | B14: =CORREL(I74:I121,L74:L121) -> 0.91109968 | C14: =CORREL(I74:I121,J74:J121) -> -0.23530529 | D14: =COUNTIFS(A74:A121,10,G74:G121,">0") -> 42
A17: Method:
A18: Answerable = 14 questions with at least one human-labelled article; Q11 and Q12 are answer-absent (scored only on whether the answer declines).
A19: Retrieved lists = top k from the Retrieval Comparison tab (semantic already filtered at >= 0.40, so it often returns fewer than k). Evidence fetched read-only from ticker_news in the production tool's exact shape.
A20: Answers: production synthesize_insight (ANALYSIS_MODEL), question passed, no ReAct draft, no external Yahoo tool. Judges: JUDGE_MODEL - groundedness vs retrieved; completeness vs gold (expected facts) and vs retrieved; answer_found for answer-absent.
